Workbook

Sheet Entities
A1: entity | B1: listed_parent | C1: ticker | D1: exchange | E1: currency | F1: note
A2: Agnico Eagle Mexico SA de CV | B2: Agnico Eagle Mines Ltd | C2: AEM | D2: NYSE | E2: USD | F2: Wholly owned subsidiary
A3: Agnico-Eagle Mines Limited | B3: Agnico Eagle Mines Ltd | C3: AEM | D3: NYSE | E3: USD
A4: Anglo Corporate Services South Africa | B4: Anglo American plc | C4: AAL.L | D4: LSE | E4: GBp | F4: Wholly owned subsidiary
A5: ArcelorMittal Mining UK Ltd | B5: ArcelorMittal SA | C5: MT | D5: NYSE | E5: USD | F5: Wholly owned subsidiary
A6: ASARCO, LLC | B6: Grupo Mexico SAB de CV | C6: GMEXICOB.MX | D6: BMV | E6: MXN | F6: Owned via Americas Mining Corp
A7: Barrick Gold of North America, Inc. | B7: Barrick Mining Corp | C7: B | D7: NYSE | E7: USD | F7: NYSE ticker was GOLD until May 2025
A8: BHP Billiton Iron Ore Pty Ltd | B8: BHP Group Ltd | C8: BHP.AX | D8: ASX | E8: AUD | F8: Wholly owned subsidiary
A9: BHP Canada Inc. | B9: BHP Group Ltd | C9: BHP.AX | D9: ASX | E9: AUD | F9: Wholly owned subsidiary
A10: Codelco Chile | F10: State-owned (Chile) - no listed shares
A11: Evolution Mining | B11: Evolution Mining Ltd | C11: EVN.AX | D11: ASX | E11: AUD
A12: FMG Procurement Services Pty Ltd | B12: Fortescue Ltd | C12: FMG.AX | D12: ASX | E12: AUD | F12: Wholly owned subsidiary
A13: Freeport McMoRan Inc. - Corporate Acc. | B13: Freeport-McMoRan Inc | C13: FCX | D13: NYSE | E13: USD
A14: Fresnillo Chile SPA | B14: Fresnillo plc | C14: FRES.L | D14: LSE | E14: GBp | F14: Wholly owned subsidiary
A15: Greenstone Gold Mines | B15: Equinox Gold Corp | C15: EQX | D15: NYSE American | E15: USD | F15: Equinox 100% since 2024 (earlier Premier Gold/Centerra/Orion JV)
A16: Industrial Minera Mexico S.A. de C.V. | B16: Southern Copper Corp | C16: SCCO | D16: NYSE | E16: USD | F16: Part of Minera Mexico (Southern Copper / Grupo Mexico)
A17: Lundin Mining Corporation | B17: Lundin Mining Corp | C17: LUN.TO | D17: TSX | E17: CAD
A18: Luossavaara-Kiirunavaara AB | F18: LKAB - state-owned (Sweden) - no listed shares
A19: Maaden - Exploration | B19: Saudi Arabian Mining Co (Maaden) | C19: 1211.SR | D19: Tadawul | E19: SAR
A20: MIM - a Glencore Company | B20: Glencore plc | C20: GLEN.L | D20: LSE | E20: GBp | F20: Mount Isa Mines - wholly owned
A21: Minera Escondida Ltda | B21: BHP Group Ltd | C21: BHP.AX | D21: ASX | E21: AUD | F21: BHP 57.5% / Rio Tinto 30% / JECO 12.5%
A22: Mineral Resources Limited | B22: Mineral Resources Ltd | C22: MIN.AX | D22: ASX | E22: AUD
A23: MMG | B23: MMG Ltd | C23: 1208.HK | D23: HKEX | E23: HKD
A24: Newmont Goldcorp Services Pty Ltd | B24: Newmont Corp | C24: NEM | D24: NYSE | E24: USD | F24: Wholly owned subsidiary
A25: NEXA RECURSOS MINERAIS S/A | B25: Nexa Resources SA | C25: NEXA | D25: NYSE | E25: USD | F25: Listed Oct 2017
A26: Northern Star Resources Limited | B26: Northern Star Resources Ltd | C26: NST.AX | D26: ASX | E26: AUD
A27: PT Vale Indonesia TBK | B27: PT Vale Indonesia Tbk | C27: INCO.JK | D27: IDX | E27: IDR
A28: PT Vale Indonesia TBK, OPG Tech Dept. | B28: PT Vale Indonesia Tbk | C28: INCO.JK | D28: IDX | E28: IDR
A29: Rio Tinto IS&T Asia Pacific | B29: Rio Tinto plc | C29: RIO.L | D29: LSE | E29: GBp | F29: Wholly owned subsidiary
A30: SGC - Servicio Geologico da Colombia | F30: Government agency (Colombia) - no shares
A31: VALE S.A. | B31: Vale SA | C31: VALE3.SA | D31: B3 | E31: BRL
A32: Vale S/A | B32: Vale SA | C32: VALE3.SA | D32: B3 | E32: BRL
A33: Zangge Mining Co., Ltd | B33: Zangge Mining Co Ltd | C33: 000408.SZ | D33: SZSE | E33: CNY
A34: Zijin Mining Corporation Co.,Ltd | B34: Zijin Mining Group Co Ltd | C34: 2899.HK | D34: HKEX | E34: HKD | F34: H-shares; A-shares are 601899.SS

Sheet Year-end close
A1: ticker | B1: company | C1: currency | D1: 2017 | E1: 2018 | F1: 2019 | G1: 2020 | H1: 2021 | I1: 2022 | J1: 2023 | K1: 2024 | L1: 2025 | M1: 2026
A2: 000408.SZ | B2: Zangge Mining Co Ltd | C2: CNY | D2: 17.7 | E2: 11.22 | F2: 7.38 | G2: 8.01 | H2: 41 | I2: 25.97 | J2: 25.34 | K2: 27.73 | L2: 84.4 | M2: 71.46
A3: 1208.HK | B3: MMG Ltd | C3: HKD | D3: 3.88 | E3: 3.37 | F3: 2.34 | G3: 3.35 | H3: 2.5 | I3: 2 | J3: 2.31 | K3: 2.57 | L3: 8.81 | M3: 8.545
A4: 1211.SR | B4: Saudi Arabian Mining Co (Maaden) | C4: SAR | D4: 52.1 | E4: 49.3 | F4: 44.4 | G4: 40.5 | H4: 78.5 | I4: 64.7 | J4: 48.55 | K4: 50.3 | L4: 60.95 | M4: 61.1
A5: 2899.HK | B5: Zijin Mining Group Co Ltd | C5: HKD | D5: 2.95 | E5: 2.97 | F5: 3.88 | G5: 8.77 | H5: 9.28 | I5: 10.58 | J5: 12.72 | K5: 14.16 | L5: 35.66 | M5: 32.5
A6: AAL.L | B6: Anglo American plc | C6: GBp | D6: 1549.5078 | E6: 1747.8088 | F6: 2173.0111 | G6: 2424.5124 | H6: 3015.987 | I6: 3236.4859 | J6: 1970.5915 | K6: 2363.9897 | L6: 3085 | M6: 4042
A7: AEM | B7: Agnico Eagle Mines Ltd | C7: USD | D7: 46.18 | E7: 40.4 | F7: 61.61 | G7: 70.51 | H7: 53.14 | I7: 51.99 | J7: 54.85 | K7: 78.21 | L7: 169.53 | M7: 194.48
A8: B | B8: Barrick Mining Corp | C8: USD | D8: 14.47 | E8: 13.54 | F8: 18.59 | G8: 22.78 | H8: 19 | I8: 17.18 | J8: 18.09 | K8: 15.5 | L8: 43.55 | M8: 42.88
A9: BHP.AX | B9: BHP Group Ltd | C9: AUD | D9: 29.5699 | E9: 34.2299 | F9: 38.9199 | G9: 42.4299 | H9: 41.4999 | I9: 45.63 | J9: 50.41 | K9: 39.55 | L9: 45.49 | M9: 60.72
A10: EQX | B10: Equinox Gold Corp | C10: USD | F10: 7.7 | G10: 10.34 | H10: 6.76 | I10: 3.28 | J10: 4.89 | K10: 5.02 | L10: 14.04 | M10: 11.94
A11: EVN.AX | B11: Evolution Mining Ltd | C11: AUD | D11: 2.65 | E11: 3.69 | F11: 3.8 | G11: 4.99 | H11: 4.06 | I11: 2.98 | J11: 3.96 | K11: 4.81 | L11: 12.68 | M11: 13.71
A12: FCX | B12: Freeport-McMoRan Inc | C12: USD | D12: 18.96 | E12: 10.31 | F12: 13.12 | G12: 26.02 | H12: 41.73 | I12: 38 | J12: 42.57 | K12: 38.08 | L12: 50.79 | M12: 72.31
A13: FMG.AX | B13: Fortescue Ltd | C13: AUD | D13: 4.88 | E13: 4.19 | F13: 10.69 | G13: 23.43 | H13: 19.21 | I13: 20.51 | J13: 29.02 | K13: 18.25 | L13: 22.01 | M13: 16.37
A14: FRES.L | B14: Fresnillo plc | C14: GBp | D14: 1429 | E14: 860 | F14: 640.2 | G14: 1129.5 | H14: 892.8 | I14: 901.8 | J14: 594.4 | K14: 621.5 | L14: 3334 | M14: 2890
A15: GLEN.L | B15: Glencore plc | C15: GBp | D15: 390 | E15: 291.35 | F15: 235.35 | G15: 233 | H15: 374.95 | I15: 552.4 | J15: 472.1 | K15: 353.4 | L15: 406.55 | M15: 561.1
A16: GMEXICOB.MX | B16: Grupo Mexico SAB de CV | C16: MXN | D16: 64.91 | E16: 40.44 | F16: 51.89 | G16: 84.12 | H16: 89.29 | I16: 68.7 | J16: 94.38 | K16: 99.28 | L16: 170.2001 | M16: 224.11
A17: INCO.JK | B17: PT Vale Indonesia Tbk | C17: IDR | D17: 2890 | E17: 3260 | F17: 3640 | G17: 5100 | H17: 4680 | I17: 7100 | J17: 4310 | K17: 3620 | L17: 5175 | M17: 4680
A18: LUN.TO | B18: Lundin Mining Corp | C18: CAD | D18: 8.36 | E18: 5.64 | F18: 7.76 | G18: 11.3 | H18: 9.88 | I18: 8.31 | J18: 10.84 | K18: 12.37 | L18: 29.5 | M18: 34.98
A19: MIN.AX | B19: Mineral Resources Ltd | C19: AUD | D19: 21.14 | E19: 15.47 | F19: 16.5 | G19: 37.45 | H19: 56 | I19: 77.2 | J19: 70 | K19: 34.25 | L19: 54.38 | M19: 52.41
A20: MT | B20: ArcelorMittal SA | C20: USD | D20: 32.31 | E20: 20.67 | F20: 17.54 | G20: 22.9 | H20: 31.83 | I20: 26.22 | J20: 28.39 | K20: 23.13 | L20: 45.57 | M20: 70.7
A21: NEM | B21: Newmont Corp | C21: USD | D21: 37.52 | E21: 34.65 | F21: 43.45 | G21: 59.89 | H21: 62.02 | I21: 47.2 | J21: 41.39 | K21: 37.22 | L21: 99.85 | M21: 121.43
A22: NEXA | B22: Nexa Resources SA | C22: USD | D22: 19.61 | E22: 11.9 | F22: 8.14 | G22: 9.64 | H22: 7.86 | I22: 6.03 | J22: 7.14 | K22: 8.8 | L22: 8.85 | M22: 12.44
... A26: VALE3.SA | B26: Vale SA | C26: BRL | D26: 40.26 | E26: 51 | F26: 53.3 | G26: 87.45 | H26: 77.96 | I26: 88.88 | J26: 77.2 | K26: 54.55 | L26: 71.96 | M26: 70.77
A28: Last close of each year, in the currency the stock trades in (GBp = pence). 2026 = latest close. Highlighted cells were corrected to the as-traded price; hover for Yahoo's rescaled figure.

Sheet Year-end close USD
A1: ticker | B1: company | C1: currency | D1: 2017 | E1: 2018 | F1: 2019 | G1: 2020 | H1: 2021 | I1: 2022 | J1: 2023 | K1: 2024 | L1: 2025 | M1: 2026
A2: 000408.SZ | B2: Zangge Mining Co Ltd | C2: USD | D2: =IF('Year-end close'!D2="","",'Year-end close'!D2/IF('Year-end close'!$C2="GBp",100,1)/INDEX('FX year-end'!$B$2:$B$11,MATCH(IF('Year-end close'!$C2="GBp","GBP",'Year-end close'!$C2),'FX year-end'!$A$2:$A$11,0))) -> 2.7099026 | E2: =IF('Year-end close'!E2="","",'Year-end close'!E2/IF('Year-end close'!$C2="GBp",100,1)/INDEX('FX year-end'!$C$2:$C$11,MATCH(IF('Year-end close'!$C2="GBp","GBP",'Year-end close'!$C2),'FX year-end'!$A$2:$A$11,0))) -> 1.6314779 | F2: =IF('Year-end close'!F2="","",'Year-end close'!F2/IF('Year-end close'!$C2="GBp",100,1)/INDEX('FX year-end'!$D$2:$D$11,MATCH(IF('Year-end close'!$C2="GBp","GBP",'Year-end close'!$C2),'FX year-end'!$A$2:$A$11,0))) -> 1.0564439 | G2: =IF('Year-end close'!G2="","",'Year-end close'!G2/IF('Year-end close'!$C2="GBp",100,1)/INDEX('FX year-end'!$E$2:$E$11,MATCH(IF('Year-end close'!$C2="GBp","GBP",'Year-end close'!$C2),'FX year-end'!$A$2:$A$11,0))) -> 1.2281132 | H2: =IF('Year-end close'!H2="","",'Year-end close'!H2/IF('Year-end close'!$C2="GBp",100,1)/INDEX('FX year-end'!$F$2:$F$11,MATCH(IF('Year-end close'!$C2="GBp","GBP",'Year-end close'!$C2),'FX year-end'!$A$2:$A$11,0))) -> 6.4342995 | I2: =IF('Year-end close'!I2="","",'Year-end close'!I2/IF('Year-end close'!$C2="GBp",100,1)/INDEX('FX year-end'!$G$2:$G$11,MATCH(IF('Year-end close'!$C2="GBp","GBP",'Year-end close'!$C2),'FX year-end'!$A$2:$A$11,0))) -> 3.7296606 | J2: =IF('Year-end close'!J2="","",'Year-end close'!J2/IF('Year-end close'!$C2="GBp",100,1)/INDEX('FX year-end'!$H$2:$H$11,MATCH(IF('Year-end close'!$C2="GBp","GBP",'Year-end close'!$C2),'FX year-end'!$A$2:$A$11,0))) -> 3.5654988 | K2: =IF('Year-end close'!K2="","",'Year-end close'!K2/IF('Year-end close'!$C2="GBp",100,1)/INDEX('FX year-end'!$I$2:$I$11,MATCH(IF('Year-end close'!$C2="GBp","GBP",'Year-end close'!$C2),'FX year-end'!$A$2:$A$11,0))) -> 3.7996191 | L2: =IF('Year-end close'!L2="","",'Year-end close'!L2/IF('Year-end close'!$C2="GBp",100,1)/INDEX('FX year-end'!$J$2:$J$11,MATCH(IF('Year-end close'!$C2="GBp","GBP",'Year-end close'!$C2),'FX year-end'!$A$2:$A$11,0))) -> 12.063864 | M2: =IF('Year-end close'!M2="","",'Year-end close'!M2/IF('Year-end close'!$C2="GBp",100,1)/INDEX('FX year-end'!$K$2:$K$11,MATCH(IF('Year-end close'!$C2="GBp","GBP",'Year-end close'!$C2),'FX year-end'!$A$2:$A$11,0))) -> 10.646127
A3: 1208.HK | B3: MMG Ltd | C3: USD | D3: =IF('Year-end close'!D3="","",'Year-end close'!D3/IF('Year-end close'!$C3="GBp",100,1)/INDEX('FX year-end'!$B$2:$B$11,MATCH(IF('Year-end close'!$C3="GBp","GBP",'Year-end close'!$C3),'FX year-end'!$A$2:$A$11,0))) -> 0.4963668 | E3: =IF('Year-end close'!E3="","",'Year-end close'!E3/IF('Year-end close'!$C3="GBp",100,1)/INDEX('FX year-end'!$C$2:$C$11,MATCH(IF('Year-end close'!$C3="GBp","GBP",'Year-end close'!$C3),'FX year-end'!$A$2:$A$11,0))) -> 0.43034645 | F3: =IF('Year-end close'!F3="","",'Year-end close'!F3/IF('Year-end close'!$C3="GBp",100,1)/INDEX('FX year-end'!$D$2:$D$11,MATCH(IF('Year-end close'!$C3="GBp","GBP",'Year-end close'!$C3),'FX year-end'!$A$2:$A$11,0))) -> 0.30045839 | G3: =IF('Year-end close'!G3="","",'Year-end close'!G3/IF('Year-end close'!$C3="GBp",100,1)/INDEX('FX year-end'!$E$2:$E$11,MATCH(IF('Year-end close'!$C3="GBp","GBP",'Year-end close'!$C3),'FX year-end'!$A$2:$A$11,0))) -> 0.43213651 | H3: =IF('Year-end close'!H3="","",'Year-end close'!H3/IF('Year-end close'!$C3="GBp",100,1)/INDEX('FX year-end'!$F$2:$F$11,MATCH(IF('Year-end close'!$C3="GBp","GBP",'Year-end close'!$C3),'FX year-end'!$A$2:$A$11,0))) -> 0.32061311 | I3: =IF('Year-end close'!I3="","",'Year-end close'!I3/IF('Year-end close'!$C3="GBp",100,1)/INDEX('FX year-end'!$G$2:$G$11,MATCH(IF('Year-end close'!$C3="GBp","GBP",'Year-end close'!$C3),'FX year-end'!$A$2:$A$11,0))) -> 0.25659448 | J3: =IF('Year-end close'!J3="","",'Year-end close'!J3/IF('Year-end close'!$C3="GBp",100,1)/INDEX('FX year-end'!$H$2:$H$11,MATCH(IF('Year-end close'!$C3="GBp","GBP",'Year-end close'!$C3),'FX year-end'!$A$2:$A$11,0))) -> 0.2957065 | K3: =IF('Year-end close'!K3="","",'Year-end close'!K3/IF('Year-end close'!$C3="GBp",100,1)/INDEX('FX year-end'!$I$2:$I$11,MATCH(IF('Year-end close'!$C3="GBp","GBP",'Year-end close'!$C3),'FX year-end'!$A$2:$A$11,0))) -> 0.33103626 | L3: =IF('Year-end close'!L3="","",'Year-end close'!L3/IF('Year-end close'!$C3="GBp",100,1)/INDEX('FX year-end'!$J$2:$J$11,MATCH(IF('Year-end close'!$C3="GBp","GBP",'Year-end close'!$C3),'FX year-end'!$A$2:$A$11,0))) -> 1.1322947 | M3: =IF('Year-end close'!M3="","",'Year-end close'!M3/IF('Year-end close'!$C3="GBp",100,1)/INDEX('FX year-end'!$K$2:$K$11,MATCH(IF('Year-end close'!$C3="GBp","GBP",'Year-end close'!$C3),'FX year-end'!$A$2:$A$11,0))) -> 1.089451
A4: 1211.SR | B4: Saudi Arabian Mining Co (Maaden) | C4: USD | D4: =IF('Year-end close'!D4="","",'Year-end close'!D4/IF('Year-end close'!$C4="GBp",100,1)/INDEX('FX year-end'!$B$2:$B$11,MATCH(IF('Year-end close'!$C4="GBp","GBP",'Year-end close'!$C4),'FX year-end'!$A$2:$A$11,0))) -> 13.909654 | E4: =IF('Year-end close'!E4="","",'Year-end close'!E4/IF('Year-end close'!$C4="GBp",100,1)/INDEX('FX year-end'!$C$2:$C$11,MATCH(IF('Year-end close'!$C4="GBp","GBP",'Year-end close'!$C4),'FX year-end'!$A$2:$A$11,0))) -> 13.14141 | F4: =IF('Year-end close'!F4="","",'Year-end close'!F4/IF('Year-end close'!$C4="GBp",100,1)/INDEX('FX year-end'!$D$2:$D$11,MATCH(IF('Year-end close'!$C4="GBp","GBP",'Year-end close'!$C4),'FX year-end'!$A$2:$A$11,0))) -> 11.84518 | G4: =IF('Year-end close'!G4="","",'Year-end close'!G4/IF('Year-end close'!$C4="GBp",100,1)/INDEX('FX year-end'!$E$2:$E$11,MATCH(IF('Year-end close'!$C4="GBp","GBP",'Year-end close'!$C4),'FX year-end'!$A$2:$A$11,0))) -> 10.806611 | H4: =IF('Year-end close'!H4="","",'Year-end close'!H4/IF('Year-end close'!$C4="GBp",100,1)/INDEX('FX year-end'!$F$2:$F$11,MATCH(IF('Year-end close'!$C4="GBp","GBP",'Year-end close'!$C4),'FX year-end'!$A$2:$A$11,0))) -> 20.93349 | I4: =IF('Year-end close'!I4="","",'Year-end close'!I4/IF('Year-end close'!$C4="GBp",100,1)/INDEX('FX year-end'!$G$2:$G$11,MATCH(IF('Year-end close'!$C4="GBp","GBP",'Year-end close'!$C4),'FX year-end'!$A$2:$A$11,0))) -> 17.230626 | J4: =IF('Year-end close'!J4="","",'Year-end close'!J4/IF('Year-end close'!$C4="GBp",100,1)/INDEX('FX year-end'!$H$2:$H$11,MATCH(IF('Year-end close'!$C4="GBp","GBP",'Year-end close'!$C4),'FX year-end'!$A$2:$A$11,0))) -> 12.963194 | K4: =IF('Year-end close'!K4="","",'Year-end close'!K4/IF('Year-end close'!$C4="GBp",100,1)/INDEX('FX year-end'!$I$2:$I$11,MATCH(IF('Year-end close'!$C4="GBp","GBP",'Year-end close'!$C4),'FX year-end'!$A$2:$A$11,0))) -> 13.406244 | L4: =IF('Year-end close'!L4="","",'Year-end close'!L4/IF('Year-end close'!$C4="GBp",100,1)/INDEX('FX year-end'!$J$2:$J$11,MATCH(IF('Year-end close'!$C4="GBp","GBP",'Year-end close'!$C4),'FX year-end'!$A$2:$A$11,0))) -> 16.26244 | M4: =IF('Year-end close'!M4="","",'Year-end close'!M4/IF('Year-end close'!$C4="GBp",100,1)/INDEX('FX year-end'!$K$2:$K$11,MATCH(IF('Year-end close'!$C4="GBp","GBP",'Year-end close'!$C4),'FX year-end'!$A$2:$A$11,0))) -> 16.274672
A5: 2899.HK | B5: Zijin Mining Group Co Ltd | C5: USD | D5: =IF('Year-end close'!D5="","",'Year-end close'!D5/IF('Year-end close'!$C5="GBp",100,1)/INDEX('FX year-end'!$B$2:$B$11,MATCH(IF('Year-end close'!$C5="GBp","GBP",'Year-end close'!$C5),'FX year-end'!$A$2:$A$11,0))) -> 0.37739228 | E5: =IF('Year-end close'!E5="","",'Year-end close'!E5/IF('Year-end close'!$C5="GBp",100,1)/INDEX('FX year-end'!$C$2:$C$11,MATCH(IF('Year-end close'!$C5="GBp","GBP",'Year-end close'!$C5),'FX year-end'!$A$2:$A$11,0))) -> 0.37926675 | F5: =IF('Year-end close'!F5="","",'Year-end close'!F5/IF('Year-end close'!$C5="GBp",100,1)/INDEX('FX year-end'!$D$2:$D$11,MATCH(IF('Year-end close'!$C5="GBp","GBP",'Year-end close'!$C5),'FX year-end'!$A$2:$A$11,0))) -> 0.49819597 | G5: =IF('Year-end close'!G5="","",'Year-end close'!G5/IF('Year-end close'!$C5="GBp",100,1)/INDEX('FX year-end'!$E$2:$E$11,MATCH(IF('Year-end close'!$C5="GBp","GBP",'Year-end close'!$C5),'FX year-end'!$A$2:$A$11,0))) -> 1.1312947 | H5: =IF('Year-end close'!H5="","",'Year-end close'!H5/IF('Year-end close'!$C5="GBp",100,1)/INDEX('FX year-end'!$F$2:$F$11,MATCH(IF('Year-end close'!$C5="GBp","GBP",'Year-end close'!$C5),'FX year-end'!$A$2:$A$11,0))) -> 1.1901159 | I5: =IF('Year-end close'!I5="","",'Year-end close'!I5/IF('Year-end close'!$C5="GBp",100,1)/INDEX('FX year-end'!$G$2:$G$11,MATCH(IF('Year-end close'!$C5="GBp","GBP",'Year-end close'!$C5),'FX year-end'!$A$2:$A$11,0))) -> 1.3573848 | J5: =IF('Year-end close'!J5="","",'Year-end close'!J5/IF('Year-end close'!$C5="GBp",100,1)/INDEX('FX year-end'!$H$2:$H$11,MATCH(IF('Year-end close'!$C5="GBp","GBP",'Year-end close'!$C5),'FX year-end'!$A$2:$A$11,0))) -> 1.6283059 | K5: =IF('Year-end close'!K5="","",'Year-end close'!K5/IF('Year-end close'!$C5="GBp",100,1)/INDEX('FX year-end'!$I$2:$I$11,MATCH(IF('Year-end close'!$C5="GBp","GBP",'Year-end close'!$C5),'FX year-end'!$A$2:$A$11,0))) -> 1.8239196 | L5: =IF('Year-end close'!L5="","",'Year-end close'!L5/IF('Year-end close'!$C5="GBp",100,1)/INDEX('FX year-end'!$J$2:$J$11,MATCH(IF('Year-end close'!$C5="GBp","GBP",'Year-end close'!$C5),'FX year-end'!$A$2:$A$11,0))) -> 4.5831588 | M5: =IF('Year-end close'!M5="","",'Year-end close'!M5/IF('Year-end close'!$C5="GBp",100,1)/INDEX('FX year-end'!$K$2:$K$11,MATCH(IF('Year-end close'!$C5="GBp","GBP",'Year-end close'!$C5),'FX year-end'!$A$2:$A$11,0))) -> 4.1436112
A6: AAL.L | B6: Anglo American plc | C6: USD | D6: =IF('Year-end close'!D6="","",'Year-end close'!D6/IF('Year-end close'!$C6="GBp",100,1)/INDEX('FX year-end'!$B$2:$B$11,MATCH(IF('Year-end close'!$C6="GBp","GBP",'Year-end close'!$C6),'FX year-end'!$A$2:$A$11,0))) -> 20.826718 | E6: =IF('Year-end close'!E6="","",'Year-end close'!E6/IF('Year-end close'!$C6="GBp",100,1)/INDEX('FX year-end'!$C$2:$C$11,MATCH(IF('Year-end close'!$C6="GBp","GBP",'Year-end close'!$C6),'FX year-end'!$A$2:$A$11,0))) -> 22.185946 | F6: =IF('Year-end close'!F6="","",'Year-end close'!F6/IF('Year-end close'!$C6="GBp",100,1)/INDEX('FX year-end'!$D$2:$D$11,MATCH(IF('Year-end close'!$C6="GBp","GBP",'Year-end close'!$C6),'FX year-end'!$A$2:$A$11,0))) -> 28.494769 | G6: =IF('Year-end close'!G6="","",'Year-end close'!G6/IF('Year-end close'!$C6="GBp",100,1)/INDEX('FX year-end'!$E$2:$E$11,MATCH(IF('Year-end close'!$C6="GBp","GBP",'Year-end close'!$C6),'FX year-end'!$A$2:$A$11,0))) -> 33.047713 | H6: =IF('Year-end close'!H6="","",'Year-end close'!H6/IF('Year-end close'!$C6="GBp",100,1)/INDEX('FX year-end'!$F$2:$F$11,MATCH(IF('Year-end close'!$C6="GBp","GBP",'Year-end close'!$C6),'FX year-end'!$A$2:$A$11,0))) -> 40.710919 | I6: =IF('Year-end close'!I6="","",'Year-end close'!I6/IF('Year-end close'!$C6="GBp",100,1)/INDEX('FX year-end'!$G$2:$G$11,MATCH(IF('Year-end close'!$C6="GBp","GBP",'Year-end close'!$C6),'FX year-end'!$A$2:$A$11,0))) -> 39.020133 | J6: =IF('Year-end close'!J6="","",'Year-end close'!J6/IF('Year-end close'!$C6="GBp",100,1)/INDEX('FX year-end'!$H$2:$H$11,MATCH(IF('Year-end close'!$C6="GBp","GBP",'Year-end close'!$C6),'FX year-end'!$A$2:$A$11,0))) -> 25.093487 | K6: =IF('Year-end close'!K6="","",'Year-end close'!K6/IF('Year-end close'!$C6="GBp",100,1)/INDEX('FX year-end'!$I$2:$I$11,MATCH(IF('Year-end close'!$C6="GBp","GBP",'Year-end close'!$C6),'FX year-end'!$A$2:$A$11,0))) -> 29.665939 | L6: =IF('Year-end close'!L6="","",'Year-end close'!L6/IF('Year-end close'!$C6="GBp",100,1)/INDEX('FX year-end'!$J$2:$J$11,MATCH(IF('Year-end close'!$C6="GBp","GBP",'Year-end close'!$C6),'FX year-end'!$A$2:$A$11,0))) -> 41.546304 | M6: =IF('Year-end close'!M6="","",'Year-end close'!M6/IF('Year-end close'!$C6="GBp",100,1)/INDEX('FX year-end'!$K$2:$K$11,MATCH(IF('Year-end close'!$C6="GBp","GBP",'Year-end close'!$C6),'FX year-end'!$A$2:$A$11,0))) -> 53.489665
A7: AEM | B7: Agnico Eagle Mines Ltd | C7: USD | D7: =IF('Year-end close'!D7="","",'Year-end close'!D7/IF('Year-end close'!$C7="GBp",100,1)/INDEX('FX year-end'!$B$2:$B$11,MATCH(IF('Year-end close'!$C7="GBp","GBP",'Year-end close'!$C7),'FX year-end'!$A$2:$A$11,0))) -> 46.18 | E7: =IF('Year-end close'!E7="","",'Year-end close'!E7/IF('Year-end close'!$C7="GBp",100,1)/INDEX('FX year-end'!$C$2:$C$11,MATCH(IF('Year-end close'!$C7="GBp","GBP",'Year-end close'!$C7),'FX year-end'!$A$2:$A$11,0))) -> 40.4 | F7: =IF('Year-end close'!F7="","",'Year-end close'!F7/IF('Year-end close'!$C7="GBp",100,1)/INDEX('FX year-end'!$D$2:$D$11,MATCH(IF('Year-end close'!$C7="GBp","GBP",'Year-end close'!$C7),'FX year-end'!$A$2:$A$11,0))) -> 61.61 | G7: =IF('Year-end close'!G7="","",'Year-end close'!G7/IF('Year-end close'!$C7="GBp",100,1)/INDEX('FX year-end'!$E$2:$E$11,MATCH(IF('Year-end close'!$C7="GBp","GBP",'Year-end close'!$C7),'FX year-end'!$A$2:$A$11,0))) -> 70.51 | H7: =IF('Year-end close'!H7="","",'Year-end close'!H7/IF('Year-end close'!$C7="GBp",100,1)/INDEX('FX year-end'!$F$2:$F$11,MATCH(IF('Year-end close'!$C7="GBp","GBP",'Year-end close'!$C7),'FX year-end'!$A$2:$A$11,0))) -> 53.14 | I7: =IF('Year-end close'!I7="","",'Year-end close'!I7/IF('Year-end close'!$C7="GBp",100,1)/INDEX('FX year-end'!$G$2:$G$11,MATCH(IF('Year-end close'!$C7="GBp","GBP",'Year-end close'!$C7),'FX year-end'!$A$2:$A$11,0))) -> 51.99 | J7: =IF('Year-end close'!J7="","",'Year-end close'!J7/IF('Year-end close'!$C7="GBp",100,1)/INDEX('FX year-end'!$H$2:$H$11,MATCH(IF('Year-end close'!$C7="GBp","GBP",'Year-end close'!$C7),'FX year-end'!$A$2:$A$11,0))) -> 54.85 | K7: =IF('Year-end close'!K7="","",'Year-end close'!K7/IF('Year-end close'!$C7="GBp",100,1)/INDEX('FX year-end'!$I$2:$I$11,MATCH(IF('Year-end close'!$C7="GBp","GBP",'Year-end close'!$C7),'FX year-end'!$A$2:$A$11,0))) -> 78.21 | L7: =IF('Year-end close'!L7="","",'Year-end close'!L7/IF('Year-end close'!$C7="GBp",100,1)/INDEX('FX year-end'!$J$2:$J$11,MATCH(IF('Year-end close'!$C7="GBp","GBP",'Year-end close'!$C7),'FX year-end'!$A$2:$A$11,0))) -> 169.53 | M7: =IF('Year-end close'!M7="","",'Year-end close'!M7/IF('Year-end close'!$C7="GBp",100,1)/INDEX('FX year-end'!$K$2:$K$11,MATCH(IF('Year-end close'!$C7="GBp","GBP",'Year-end close'!$C7),'FX year-end'!$A$2:$A$11,0))) -> 194.48
A8: B | B8: Barrick Mining Corp | C8: USD | D8: =IF('Year-end close'!D8="","",'Year-end close'!D8/IF('Year-end close'!$C8="GBp",100,1)/INDEX('FX year-end'!$B$2:$B$11,MATCH(IF('Year-end close'!$C8="GBp","GBP",'Year-end close'!$C8),'FX year-end'!$A$2:$A$11,0))) -> 14.47 | E8: =IF('Year-end close'!E8="","",'Year-end close'!E8/IF('Year-end close'!$C8="GBp",100,1)/INDEX('FX year-end'!$C$2:$C$11,MATCH(IF('Year-end close'!$C8="GBp","GBP",'Year-end close'!$C8),'FX year-end'!$A$2:$A$11,0))) -> 13.54 | F8: =IF('Year-end close'!F8="","",'Year-end close'!F8/IF('Year-end close'!$C8="GBp",100,1)/INDEX('FX year-end'!$D$2:$D$11,MATCH(IF('Year-end close'!$C8="GBp","GBP",'Year-end close'!$C8),'FX year-end'!$A$2:$A$11,0))) -> 18.59 | G8: =IF('Year-end close'!G8="","",'Year-end close'!G8/IF('Year-end close'!$C8="GBp",100,1)/INDEX('FX year-end'!$E$2:$E$11,MATCH(IF('Year-end close'!$C8="GBp","GBP",'Year-end close'!$C8),'FX year-end'!$A$2:$A$11,0))) -> 22.78 | H8: =IF('Year-end close'!H8="","",'Year-end close'!H8/IF('Year-end close'!$C8="GBp",100,1)/INDEX('FX year-end'!$F$2:$F$11,MATCH(IF('Year-end close'!$C8="GBp","GBP",'Year-end close'!$C8),'FX year-end'!$A$2:$A$11,0))) -> 19 | I8: =IF('Year-end close'!I8="","",'Year-end close'!I8/IF('Year-end close'!$C8="GBp",100,1)/INDEX('FX year-end'!$G$2:$G$11,MATCH(IF('Year-end close'!$C8="GBp","GBP",'Year-end close'!$C8),'FX year-end'!$A$2:$A$11,0))) -> 17.18 | J8: =IF('Year-end close'!J8="","",'Year-end close'!J8/IF('Year-end close'!$C8="GBp",100,1)/INDEX('FX year-end'!$H$2:$H$11,MATCH(IF('Year-end close'!$C8="GBp","GBP",'Year-end close'!$C8),'FX year-end'!$A$2:$A$11,0))) -> 18.09 | K8: =IF('Year-end close'!K8="","",'Year-end close'!K8/IF('Year-end close'!$C8="GBp",100,1)/INDEX('FX year-end'!$I$2:$I$11,MATCH(IF('Year-end close'!$C8="GBp","GBP",'Year-end close'!$C8),'FX year-end'!$A$2:$A$11,0))) -> 15.5 | L8: =IF('Year-end close'!L8="","",'Year-end close'!L8/IF('Year-end close'!$C8="GBp",100,1)/INDEX('FX year-end'!$J$2:$J$11,MATCH(IF('Year-end close'!$C8="GBp","GBP",'Year-end close'!$C8),'FX year-end'!$A$2:$A$11,0))) -> 43.55 | M8: =IF('Year-end close'!M8="","",'Year-end close'!M8/IF('Year-end close'!$C8="GBp",100,1)/INDEX('FX year-end'!$K$2:$K$11,MATCH(IF('Year-end close'!$C8="GBp","GBP",'Year-end close'!$C8),'FX year-end'!$A$2:$A$11,0))) -> 42.88
A9: BHP.AX | B9: BHP Group Ltd | C9: USD | D9: =IF('Year-end close'!D9="","",'Year-end close'!D9/IF('Year-end close'!$C9="GBp",100,1)/INDEX('FX year-end'!$B$2:$B$11,MATCH(IF('Year-end close'!$C9="GBp","GBP",'Year-end close'!$C9),'FX year-end'!$A$2:$A$11,0))) -> 23.047647 | E9: =IF('Year-end close'!E9="","",'Year-end close'!E9/IF('Year-end close'!$C9="GBp",100,1)/INDEX('FX year-end'!$C$2:$C$11,MATCH(IF('Year-end close'!$C9="GBp","GBP",'Year-end close'!$C9),'FX year-end'!$A$2:$A$11,0))) -> 24.114054 | F9: =IF('Year-end close'!F9="","",'Year-end close'!F9/IF('Year-end close'!$C9="GBp",100,1)/INDEX('FX year-end'!$D$2:$D$11,MATCH(IF('Year-end close'!$C9="GBp","GBP",'Year-end close'!$C9),'FX year-end'!$A$2:$A$11,0))) -> 27.249374 | G9: =IF('Year-end close'!G9="","",'Year-end close'!G9/IF('Year-end close'!$C9="GBp",100,1)/INDEX('FX year-end'!$E$2:$E$11,MATCH(IF('Year-end close'!$C9="GBp","GBP",'Year-end close'!$C9),'FX year-end'!$A$2:$A$11,0))) -> 32.625585 | H9: =IF('Year-end close'!H9="","",'Year-end close'!H9/IF('Year-end close'!$C9="GBp",100,1)/INDEX('FX year-end'!$F$2:$F$11,MATCH(IF('Year-end close'!$C9="GBp","GBP",'Year-end close'!$C9),'FX year-end'!$A$2:$A$11,0))) -> 30.086606 | I9: =IF('Year-end close'!I9="","",'Year-end close'!I9/IF('Year-end close'!$C9="GBp",100,1)/INDEX('FX year-end'!$G$2:$G$11,MATCH(IF('Year-end close'!$C9="GBp","GBP",'Year-end close'!$C9),'FX year-end'!$A$2:$A$11,0))) -> 30.873261 | J9: =IF('Year-end close'!J9="","",'Year-end close'!J9/IF('Year-end close'!$C9="GBp",100,1)/INDEX('FX year-end'!$H$2:$H$11,MATCH(IF('Year-end close'!$C9="GBp","GBP",'Year-end close'!$C9),'FX year-end'!$A$2:$A$11,0))) -> 34.411388 | K9: =IF('Year-end close'!K9="","",'Year-end close'!K9/IF('Year-end close'!$C9="GBp",100,1)/INDEX('FX year-end'!$I$2:$I$11,MATCH(IF('Year-end close'!$C9="GBp","GBP",'Year-end close'!$C9),'FX year-end'!$A$2:$A$11,0))) -> 24.600101 | L9: =IF('Year-end close'!L9="","",'Year-end close'!L9/IF('Year-end close'!$C9="GBp",100,1)/INDEX('FX year-end'!$J$2:$J$11,MATCH(IF('Year-end close'!$C9="GBp","GBP",'Year-end close'!$C9),'FX year-end'!$A$2:$A$11,0))) -> 30.469202 | M9: =IF('Year-end close'!M9="","",'Year-end close'!M9/IF('Year-end close'!$C9="GBp",100,1)/INDEX('FX year-end'!$K$2:$K$11,MATCH(IF('Year-end close'!$C9="GBp","GBP",'Year-end close'!$C9),'FX year-end'!$A$2:$A$11,0))) -> 42.586618
A10: EQX | B10: Equinox Gold Corp | C10: USD | D10: =IF('Year-end close'!D10="","",'Year-end close'!D10/IF('Year-end close'!$C10="GBp",100,1)/INDEX('FX year-end'!$B$2:$B$11,MATCH(IF('Year-end close'!$C10="GBp","GBP",'Year-end close'!$C10),'FX year-end'!$A$2:$A$11,0))) | E10: =IF('Year-end close'!E10="","",'Year-end close'!E10/IF('Year-end close'!$C10="GBp",100,1)/INDEX('FX year-end'!$C$2:$C$11,MATCH(IF('Year-end close'!$C10="GBp","GBP",'Year-end close'!$C10),'FX year-end'!$A$2:$A$11,0))) | F10: =IF('Year-end close'!F10="","",'Year-end close'!F10/IF('Year-end close'!$C10="GBp",100,1)/INDEX('FX year-end'!$D$2:$D$11,MATCH(IF('Year-end close'!$C10="GBp","GBP",'Year-end close'!$C10),'FX year-end'!$A$2:$A$11,0))) -> 7.7 | G10: =IF('Year-end close'!G10="","",'Year-end close'!G10/IF('Year-end close'!$C10="GBp",100,1)/INDEX('FX year-end'!$E$2:$E$11,MATCH(IF('Year-end close'!$C10="GBp","GBP",'Year-end close'!$C10),'FX year-end'!$A$2:$A$11,0))) -> 10.34 | H10: =IF('Year-end close'!H10="","",'Year-end close'!H10/IF('Year-end close'!$C10="GBp",100,1)/INDEX('FX year-end'!$F$2:$F$11,MATCH(IF('Year-end close'!$C10="GBp","GBP",'Year-end close'!$C10),'FX year-end'!$A$2:$A$11,0))) -> 6.76 | I10: =IF('Year-end close'!I10="","",'Year-end close'!I10/IF('Year-end close'!$C10="GBp",100,1)/INDEX('FX year-end'!$G$2:$G$11,MATCH(IF('Year-end close'!$C10="GBp","GBP",'Year-end close'!$C10),'FX year-end'!$A$2:$A$11,0))) -> 3.28 | J10: =IF('Year-end close'!J10="","",'Year-end close'!J10/IF('Year-end close'!$C10="GBp",100,1)/INDEX('FX year-end'!$H$2:$H$11,MATCH(IF('Year-end close'!$C10="GBp","GBP",'Year-end close'!$C10),'FX year-end'!$A$2:$A$11,0))) -> 4.89 | K10: =IF('Year-end close'!K10="","",'Year-end close'!K10/IF('Year-end close'!$C10="GBp",100,1)/INDEX('FX year-end'!$I$2:$I$11,MATCH(IF('Year-end close'!$C10="GBp","GBP",'Year-end close'!$C10),'FX year-end'!$A$2:$A$11,0))) -> 5.02 | L10: =IF('Year-end close'!L10="","",'Year-end close'!L10/IF('Year-end close'!$C10="GBp",100,1)/INDEX('FX year-end'!$J$2:$J$11,MATCH(IF('Year-end close'!$C10="GBp","GBP",'Year-end close'!$C10),'FX year-end'!$A$2:$A$11,0))) -> 14.04 | M10: =IF('Year-end close'!M10="","",'Year-end close'!M10/IF('Year-end close'!$C10="GBp",100,1)/INDEX('FX year-end'!$K$2:$K$11,MATCH(IF('Year-end close'!$C10="GBp","GBP",'Year-end close'!$C10),'FX year-end'!$A$2:$A$11,0))) -> 11.94
A11: EVN.AX | B11: Evolution Mining Ltd | C11: USD | D11: =IF('Year-end close'!D11="","",'Year-end close'!D11/IF('Year-end close'!$C11="GBp",100,1)/INDEX('FX year-end'!$B$2:$B$11,MATCH(IF('Year-end close'!$C11="GBp","GBP",'Year-end close'!$C11),'FX year-end'!$A$2:$A$11,0))) -> 2.0654876 | E11: =IF('Year-end close'!E11="","",'Year-end close'!E11/IF('Year-end close'!$C11="GBp",100,1)/INDEX('FX year-end'!$C$2:$C$11,MATCH(IF('Year-end close'!$C11="GBp","GBP",'Year-end close'!$C11),'FX year-end'!$A$2:$A$11,0))) -> 2.5995069 | F11: =IF('Year-end close'!F11="","",'Year-end close'!F11/IF('Year-end close'!$C11="GBp",100,1)/INDEX('FX year-end'!$D$2:$D$11,MATCH(IF('Year-end close'!$C11="GBp","GBP",'Year-end close'!$C11),'FX year-end'!$A$2:$A$11,0))) -> 2.6605316 | G11: =IF('Year-end close'!G11="","",'Year-end close'!G11/IF('Year-end close'!$C11="GBp",100,1)/INDEX('FX year-end'!$E$2:$E$11,MATCH(IF('Year-end close'!$C11="GBp","GBP",'Year-end close'!$C11),'FX year-end'!$A$2:$A$11,0))) -> 3.8369563 | H11: =IF('Year-end close'!H11="","",'Year-end close'!H11/IF('Year-end close'!$C11="GBp",100,1)/INDEX('FX year-end'!$F$2:$F$11,MATCH(IF('Year-end close'!$C11="GBp","GBP",'Year-end close'!$C11),'FX year-end'!$A$2:$A$11,0))) -> 2.9434196 | I11: =IF('Year-end close'!I11="","",'Year-end close'!I11/IF('Year-end close'!$C11="GBp",100,1)/INDEX('FX year-end'!$G$2:$G$11,MATCH(IF('Year-end close'!$C11="GBp","GBP",'Year-end close'!$C11),'FX year-end'!$A$2:$A$11,0))) -> 2.0162682 | J11: =IF('Year-end close'!J11="","",'Year-end close'!J11/IF('Year-end close'!$C11="GBp",100,1)/INDEX('FX year-end'!$H$2:$H$11,MATCH(IF('Year-end close'!$C11="GBp","GBP",'Year-end close'!$C11),'FX year-end'!$A$2:$A$11,0))) -> 2.7032156 | K11: =IF('Year-end close'!K11="","",'Year-end close'!K11/IF('Year-end close'!$C11="GBp",100,1)/INDEX('FX year-end'!$I$2:$I$11,MATCH(IF('Year-end close'!$C11="GBp","GBP",'Year-end close'!$C11),'FX year-end'!$A$2:$A$11,0))) -> 2.9918201 | L11: =IF('Year-end close'!L11="","",'Year-end close'!L11/IF('Year-end close'!$C11="GBp",100,1)/INDEX('FX year-end'!$J$2:$J$11,MATCH(IF('Year-end close'!$C11="GBp","GBP",'Year-end close'!$C11),'FX year-end'!$A$2:$A$11,0))) -> 8.4930639 | M11: =IF('Year-end close'!M11="","",'Year-end close'!M11/IF('Year-end close'!$C11="GBp",100,1)/INDEX('FX year-end'!$K$2:$K$11,MATCH(IF('Year-end close'!$C11="GBp","GBP",'Year-end close'!$C11),'FX year-end'!$A$2:$A$11,0))) -> 9.6156544
A12: FCX | B12: Freeport-McMoRan Inc | C12: USD | D12: =IF('Year-end close'!D12="","",'Year-end close'!D12/IF('Year-end close'!$C12="GBp",100,1)/INDEX('FX year-end'!$B$2:$B$11,MATCH(IF('Year-end close'!$C12="GBp","GBP",'Year-end close'!$C12),'FX year-end'!$A$2:$A$11,0))) -> 18.96 | E12: =IF('Year-end close'!E12="","",'Year-end close'!E12/IF('Year-end close'!$C12="GBp",100,1)/INDEX('FX year-end'!$C$2:$C$11,MATCH(IF('Year-end close'!$C12="GBp","GBP",'Year-end close'!$C12),'FX year-end'!$A$2:$A$11,0))) -> 10.31 | F12: =IF('Year-end close'!F12="","",'Year-end close'!F12/IF('Year-end close'!$C12="GBp",100,1)/INDEX('FX year-end'!$D$2:$D$11,MATCH(IF('Year-end close'!$C12="GBp","GBP",'Year-end close'!$C12),'FX year-end'!$A$2:$A$11,0))) -> 13.12 | G12: =IF('Year-end close'!G12="","",'Year-end close'!G12/IF('Year-end close'!$C12="GBp",100,1)/INDEX('FX year-end'!$E$2:$E$11,MATCH(IF('Year-end close'!$C12="GBp","GBP",'Year-end close'!$C12),'FX year-end'!$A$2:$A$11,0))) -> 26.02 | H12: =IF('Year-end close'!H12="","",'Year-end close'!H12/IF('Year-end close'!$C12="GBp",100,1)/INDEX('FX year-end'!$F$2:$F$11,MATCH(IF('Year-end close'!$C12="GBp","GBP",'Year-end close'!$C12),'FX year-end'!$A$2:$A$11,0))) -> 41.73 | I12: =IF('Year-end close'!I12="","",'Year-end close'!I12/IF('Year-end close'!$C12="GBp",100,1)/INDEX('FX year-end'!$G$2:$G$11,MATCH(IF('Year-end close'!$C12="GBp","GBP",'Year-end close'!$C12),'FX year-end'!$A$2:$A$11,0))) -> 38 | J12: =IF('Year-end close'!J12="","",'Year-end close'!J12/IF('Year-end close'!$C12="GBp",100,1)/INDEX('FX year-end'!$H$2:$H$11,MATCH(IF('Year-end close'!$C12="GBp","GBP",'Year-end close'!$C12),'FX year-end'!$A$2:$A$11,0))) -> 42.57 | K12: =IF('Year-end close'!K12="","",'Year-end close'!K12/IF('Year-end close'!$C12="GBp",100,1)/INDEX('FX year-end'!$I$2:$I$11,MATCH(IF('Year-end close'!$C12="GBp","GBP",'Year-end close'!$C12),'FX year-end'!$A$2:$A$11,0))) -> 38.08 | L12: =IF('Year-end close'!L12="","",'Year-end close'!L12/IF('Year-end close'!$C12="GBp",100,1)/INDEX('FX year-end'!$J$2:$J$11,MATCH(IF('Year-end close'!$C12="GBp","GBP",'Year-end close'!$C12),'FX year-end'!$A$2:$A$11,0))) -> 50.79 | M12: =IF('Year-end close'!M12="","",'Year-end close'!M12/IF('Year-end close'!$C12="GBp",100,1)/INDEX('FX year-end'!$K$2:$K$11,MATCH(IF('Year-end close'!$C12="GBp","GBP",'Year-end close'!$C12),'FX year-end'!$A$2:$A$11,0))) -> 72.31
A13: FMG.AX | B13: Fortescue Ltd | C13: USD | D13: =IF('Year-end close'!D13="","",'Year-end close'!D13/IF('Year-end close'!$C13="GBp",100,1)/INDEX('FX year-end'!$B$2:$B$11,MATCH(IF('Year-end close'!$C13="GBp","GBP",'Year-end close'!$C13),'FX year-end'!$A$2:$A$11,0))) -> 3.803615 | E13: =IF('Year-end close'!E13="","",'Year-end close'!E13/IF('Year-end close'!$C13="GBp",100,1)/INDEX('FX year-end'!$C$2:$C$11,MATCH(IF('Year-end close'!$C13="GBp","GBP",'Year-end close'!$C13),'FX year-end'!$A$2:$A$11,0))) -> 2.9517436 | F13: =IF('Year-end close'!F13="","",'Year-end close'!F13/IF('Year-end close'!$C13="GBp",100,1)/INDEX('FX year-end'!$D$2:$D$11,MATCH(IF('Year-end close'!$C13="GBp","GBP",'Year-end close'!$C13),'FX year-end'!$A$2:$A$11,0))) -> 7.4844954 | G13: =IF('Year-end close'!G13="","",'Year-end close'!G13/IF('Year-end close'!$C13="GBp",100,1)/INDEX('FX year-end'!$E$2:$E$11,MATCH(IF('Year-end close'!$C13="GBp","GBP",'Year-end close'!$C13),'FX year-end'!$A$2:$A$11,0))) -> 18.016009 | H13: =IF('Year-end close'!H13="","",'Year-end close'!H13/IF('Year-end close'!$C13="GBp",100,1)/INDEX('FX year-end'!$F$2:$F$11,MATCH(IF('Year-end close'!$C13="GBp","GBP",'Year-end close'!$C13),'FX year-end'!$A$2:$A$11,0))) -> 13.92687 | I13: =IF('Year-end close'!I13="","",'Year-end close'!I13/IF('Year-end close'!$C13="GBp",100,1)/INDEX('FX year-end'!$G$2:$G$11,MATCH(IF('Year-end close'!$C13="GBp","GBP",'Year-end close'!$C13),'FX year-end'!$A$2:$A$11,0))) -> 13.877067 | J13: =IF('Year-end close'!J13="","",'Year-end close'!J13/IF('Year-end close'!$C13="GBp",100,1)/INDEX('FX year-end'!$H$2:$H$11,MATCH(IF('Year-end close'!$C13="GBp","GBP",'Year-end close'!$C13),'FX year-end'!$A$2:$A$11,0))) -> 19.809928 | K13: =IF('Year-end close'!K13="","",'Year-end close'!K13/IF('Year-end close'!$C13="GBp",100,1)/INDEX('FX year-end'!$I$2:$I$11,MATCH(IF('Year-end close'!$C13="GBp","GBP",'Year-end close'!$C13),'FX year-end'!$A$2:$A$11,0))) -> 11.3515 | L13: =IF('Year-end close'!L13="","",'Year-end close'!L13/IF('Year-end close'!$C13="GBp",100,1)/INDEX('FX year-end'!$J$2:$J$11,MATCH(IF('Year-end close'!$C13="GBp","GBP",'Year-end close'!$C13),'FX year-end'!$A$2:$A$11,0))) -> 14.742298 | M13: =IF('Year-end close'!M13="","",'Year-end close'!M13/IF('Year-end close'!$C13="GBp",100,1)/INDEX('FX year-end'!$K$2:$K$11,MATCH(IF('Year-end close'!$C13="GBp","GBP",'Year-end close'!$C13),'FX year-end'!$A$2:$A$11,0))) -> 11.481274
... A26: VALE3.SA | B26: Vale SA | C26: USD | D26: =IF('Year-end close'!D26="","",'Year-end close'!D26/IF('Year-end close'!$C26="GBp",100,1)/INDEX('FX year-end'!$B$2:$B$11,MATCH(IF('Year-end close'!$C26="GBp","GBP",'Year-end close'!$C26),'FX year-end'!$A$2:$A$11,0))) -> 12.159101 | E26: =IF('Year-end close'!E26="","",'Year-end close'!E26/IF('Year-end close'!$C26="GBp",100,1)/INDEX('FX year-end'!$C$2:$C$11,MATCH(IF('Year-end close'!$C26="GBp","GBP",'Year-end close'!$C26),'FX year-end'!$A$2:$A$11,0))) -> 13.164008 | F26: =IF('Year-end close'!F26="","",'Year-end close'!F26/IF('Year-end close'!$C26="GBp",100,1)/INDEX('FX year-end'!$D$2:$D$11,MATCH(IF('Year-end close'!$C26="GBp","GBP",'Year-end close'!$C26),'FX year-end'!$A$2:$A$11,0))) -> 13.272867 | G26: =IF('Year-end close'!G26="","",'Year-end close'!G26/IF('Year-end close'!$C26="GBp",100,1)/INDEX('FX year-end'!$E$2:$E$11,MATCH(IF('Year-end close'!$C26="GBp","GBP",'Year-end close'!$C26),'FX year-end'!$A$2:$A$11,0))) -> 16.846988 | H26: =IF('Year-end close'!H26="","",'Year-end close'!H26/IF('Year-end close'!$C26="GBp",100,1)/INDEX('FX year-end'!$F$2:$F$11,MATCH(IF('Year-end close'!$C26="GBp","GBP",'Year-end close'!$C26),'FX year-end'!$A$2:$A$11,0))) -> 13.995907 | I26: =IF('Year-end close'!I26="","",'Year-end close'!I26/IF('Year-end close'!$C26="GBp",100,1)/INDEX('FX year-end'!$G$2:$G$11,MATCH(IF('Year-end close'!$C26="GBp","GBP",'Year-end close'!$C26),'FX year-end'!$A$2:$A$11,0))) -> 16.818681 | J26: =IF('Year-end close'!J26="","",'Year-end close'!J26/IF('Year-end close'!$C26="GBp",100,1)/INDEX('FX year-end'!$H$2:$H$11,MATCH(IF('Year-end close'!$C26="GBp","GBP",'Year-end close'!$C26),'FX year-end'!$A$2:$A$11,0))) -> 15.916869 | K26: =IF('Year-end close'!K26="","",'Year-end close'!K26/IF('Year-end close'!$C26="GBp",100,1)/INDEX('FX year-end'!$I$2:$I$11,MATCH(IF('Year-end close'!$C26="GBp","GBP",'Year-end close'!$C26),'FX year-end'!$A$2:$A$11,0))) -> 8.8298613 | L26: =IF('Year-end close'!L26="","",'Year-end close'!L26/IF('Year-end close'!$C26="GBp",100,1)/INDEX('FX year-end'!$J$2:$J$11,MATCH(IF('Year-end close'!$C26="GBp","GBP",'Year-end close'!$C26),'FX year-end'!$A$2:$A$11,0))) -> 13.140499 | M26: =IF('Year-end close'!M26="","",'Year-end close'!M26/IF('Year-end close'!$C26="GBp",100,1)/INDEX('FX year-end'!$K$2:$K$11,MATCH(IF('Year-end close'!$C26="GBp","GBP",'Year-end close'!$C26),'FX year-end'!$A$2:$A$11,0))) -> 13.651094
A28: Year-end close / year-end FX rate (pence divided by 100 first).

Sheet 2y forward
A1: ticker | B1: company | C1: currency | D1: 2019 | E1: 2020 | F1: 2021 | G1: 2022 | H1: 2023 | I1: 2024 | J1: 2025 | K1: 2026 | L1: 2027 | M1: 2028
A2: 000408.SZ | B2: Zangge Mining Co Ltd | C2: CNY | D2: =IF('Year-end close'!D2="","",'Year-end close'!D2*EXP((INDEX('Rates 2y'!$B$2:$B$11,MATCH(IF($C2="GBp","GBP",$C2),'Rates 2y'!$A$2:$A$11,0))-'Dividend yield'!D2)*2)) -> 18.35068 | E2: =IF('Year-end close'!E2="","",'Year-end close'!E2*EXP((INDEX('Rates 2y'!$C$2:$C$11,MATCH(IF($C2="GBp","GBP",$C2),'Rates 2y'!$A$2:$A$11,0))-'Dividend yield'!E2)*2)) -> 11.842537 | F2: =IF('Year-end close'!F2="","",'Year-end close'!F2*EXP((INDEX('Rates 2y'!$D$2:$D$11,MATCH(IF($C2="GBp","GBP",$C2),'Rates 2y'!$A$2:$A$11,0))-'Dividend yield'!F2)*2)) -> 7.773913 | G2: =IF('Year-end close'!G2="","",'Year-end close'!G2*EXP((INDEX('Rates 2y'!$E$2:$E$11,MATCH(IF($C2="GBp","GBP",$C2),'Rates 2y'!$A$2:$A$11,0))-'Dividend yield'!G2)*2)) -> 8.4544317 | H2: =IF('Year-end close'!H2="","",'Year-end close'!H2*EXP((INDEX('Rates 2y'!$F$2:$F$11,MATCH(IF($C2="GBp","GBP",$C2),'Rates 2y'!$A$2:$A$11,0))-'Dividend yield'!H2)*2)) -> 42.930051 | I2: =IF('Year-end close'!I2="","",'Year-end close'!I2*EXP((INDEX('Rates 2y'!$G$2:$G$11,MATCH(IF($C2="GBp","GBP",$C2),'Rates 2y'!$A$2:$A$11,0))-'Dividend yield'!I2)*2)) -> 23.49468 | J2: =IF('Year-end close'!J2="","",'Year-end close'!J2*EXP((INDEX('Rates 2y'!$H$2:$H$11,MATCH(IF($C2="GBp","GBP",$C2),'Rates 2y'!$A$2:$A$11,0))-'Dividend yield'!J2)*2)) -> 23.045584 | K2: =IF('Year-end close'!K2="","",'Year-end close'!K2*EXP((INDEX('Rates 2y'!$I$2:$I$11,MATCH(IF($C2="GBp","GBP",$C2),'Rates 2y'!$A$2:$A$11,0))-'Dividend yield'!K2)*2)) -> 26.26042 | L2: =IF('Year-end close'!L2="","",'Year-end close'!L2*EXP((INDEX('Rates 2y'!$J$2:$J$11,MATCH(IF($C2="GBp","GBP",$C2),'Rates 2y'!$A$2:$A$11,0))-'Dividend yield'!L2)*2)) -> 84.76404 | M2: =IF('Year-end close'!M2="","",'Year-end close'!M2*EXP((INDEX('Rates 2y'!$K$2:$K$11,MATCH(IF($C2="GBp","GBP",$C2),'Rates 2y'!$A$2:$A$11,0))-'Dividend yield'!M2)*2)) -> 68.52289
A3: 1208.HK | B3: MMG Ltd | C3: HKD | D3: =IF('Year-end close'!D3="","",'Year-end close'!D3*EXP((INDEX('Rates 2y'!$B$2:$B$11,MATCH(IF($C3="GBp","GBP",$C3),'Rates 2y'!$A$2:$A$11,0))-'Dividend yield'!D3)*2)) -> 3.9822029 | E3: =IF('Year-end close'!E3="","",'Year-end close'!E3*EXP((INDEX('Rates 2y'!$C$2:$C$11,MATCH(IF($C3="GBp","GBP",$C3),'Rates 2y'!$A$2:$A$11,0))-'Dividend yield'!E3)*2)) -> 3.4935302 | F3: =IF('Year-end close'!F3="","",'Year-end close'!F3*EXP((INDEX('Rates 2y'!$D$2:$D$11,MATCH(IF($C3="GBp","GBP",$C3),'Rates 2y'!$A$2:$A$11,0))-'Dividend yield'!F3)*2)) -> 2.420928 | G3: =IF('Year-end close'!G3="","",'Year-end close'!G3*EXP((INDEX('Rates 2y'!$E$2:$E$11,MATCH(IF($C3="GBp","GBP",$C3),'Rates 2y'!$A$2:$A$11,0))-'Dividend yield'!G3)*2)) -> 3.3634268 | H3: =IF('Year-end close'!H3="","",'Year-end close'!H3*EXP((INDEX('Rates 2y'!$F$2:$F$11,MATCH(IF($C3="GBp","GBP",$C3),'Rates 2y'!$A$2:$A$11,0))-'Dividend yield'!H3)*2)) -> 2.5301807 | I3: =IF('Year-end close'!I3="","",'Year-end close'!I3*EXP((INDEX('Rates 2y'!$G$2:$G$11,MATCH(IF($C3="GBp","GBP",$C3),'Rates 2y'!$A$2:$A$11,0))-'Dividend yield'!I3)*2)) -> 2.1665741 | J3: =IF('Year-end close'!J3="","",'Year-end close'!J3*EXP((INDEX('Rates 2y'!$H$2:$H$11,MATCH(IF($C3="GBp","GBP",$C3),'Rates 2y'!$A$2:$A$11,0))-'Dividend yield'!J3)*2)) -> 2.4824538 | K3: =IF('Year-end close'!K3="","",'Year-end close'!K3*EXP((INDEX('Rates 2y'!$I$2:$I$11,MATCH(IF($C3="GBp","GBP",$C3),'Rates 2y'!$A$2:$A$11,0))-'Dividend yield'!K3)*2)) -> 2.7508388 | L3: =IF('Year-end close'!L3="","",'Year-end close'!L3*EXP((INDEX('Rates 2y'!$J$2:$J$11,MATCH(IF($C3="GBp","GBP",$C3),'Rates 2y'!$A$2:$A$11,0))-'Dividend yield'!L3)*2)) -> 9.2802403 | M3: =IF('Year-end close'!M3="","",'Year-end close'!M3*EXP((INDEX('Rates 2y'!$K$2:$K$11,MATCH(IF($C3="GBp","GBP",$C3),'Rates 2y'!$A$2:$A$11,0))-'Dividend yield'!M3)*2)) -> 9.0010957
A4: 1211.SR | B4: Saudi Arabian Mining Co (Maaden) | C4: SAR | D4: =IF('Year-end close'!D4="","",'Year-end close'!D4*EXP((INDEX('Rates 2y'!$B$2:$B$11,MATCH(IF($C4="GBp","GBP",$C4),'Rates 2y'!$A$2:$A$11,0))-'Dividend yield'!D4)*2)) -> 54.226241 | E4: =IF('Year-end close'!E4="","",'Year-end close'!E4*EXP((INDEX('Rates 2y'!$C$2:$C$11,MATCH(IF($C4="GBp","GBP",$C4),'Rates 2y'!$A$2:$A$11,0))-'Dividend yield'!E4)*2)) -> 52.243949 | F4: =IF('Year-end close'!F4="","",'Year-end close'!F4*EXP((INDEX('Rates 2y'!$D$2:$D$11,MATCH(IF($C4="GBp","GBP",$C4),'Rates 2y'!$A$2:$A$11,0))-'Dividend yield'!F4)*2)) -> 46.490104 | G4: =IF('Year-end close'!G4="","",'Year-end close'!G4*EXP((INDEX('Rates 2y'!$E$2:$E$11,MATCH(IF($C4="GBp","GBP",$C4),'Rates 2y'!$A$2:$A$11,0))-'Dividend yield'!G4)*2)) -> 41.235601 | H4: =IF('Year-end close'!H4="","",'Year-end close'!H4*EXP((INDEX('Rates 2y'!$F$2:$F$11,MATCH(IF($C4="GBp","GBP",$C4),'Rates 2y'!$A$2:$A$11,0))-'Dividend yield'!H4)*2)) -> 80.40679 | I4: =IF('Year-end close'!I4="","",'Year-end close'!I4*EXP((INDEX('Rates 2y'!$G$2:$G$11,MATCH(IF($C4="GBp","GBP",$C4),'Rates 2y'!$A$2:$A$11,0))-'Dividend yield'!I4)*2)) -> 71.504558 | J4: =IF('Year-end close'!J4="","",'Year-end close'!J4*EXP((INDEX('Rates 2y'!$H$2:$H$11,MATCH(IF($C4="GBp","GBP",$C4),'Rates 2y'!$A$2:$A$11,0))-'Dividend yield'!J4)*2)) -> 54.087018 | K4: =IF('Year-end close'!K4="","",'Year-end close'!K4*EXP((INDEX('Rates 2y'!$I$2:$I$11,MATCH(IF($C4="GBp","GBP",$C4),'Rates 2y'!$A$2:$A$11,0))-'Dividend yield'!K4)*2)) -> 55.812903 | L4: =IF('Year-end close'!L4="","",'Year-end close'!L4*EXP((INDEX('Rates 2y'!$J$2:$J$11,MATCH(IF($C4="GBp","GBP",$C4),'Rates 2y'!$A$2:$A$11,0))-'Dividend yield'!L4)*2)) -> 66.823436 | M4: =IF('Year-end close'!M4="","",'Year-end close'!M4*EXP((INDEX('Rates 2y'!$K$2:$K$11,MATCH(IF($C4="GBp","GBP",$C4),'Rates 2y'!$A$2:$A$11,0))-'Dividend yield'!M4)*2)) -> 66.987891
A5: 2899.HK | B5: Zijin Mining Group Co Ltd | C5: HKD | D5: =IF('Year-end close'!D5="","",'Year-end close'!D5*EXP((INDEX('Rates 2y'!$B$2:$B$11,MATCH(IF($C5="GBp","GBP",$C5),'Rates 2y'!$A$2:$A$11,0))-'Dividend yield'!D5)*2)) -> 2.8899673 | E5: =IF('Year-end close'!E5="","",'Year-end close'!E5*EXP((INDEX('Rates 2y'!$C$2:$C$11,MATCH(IF($C5="GBp","GBP",$C5),'Rates 2y'!$A$2:$A$11,0))-'Dividend yield'!E5)*2)) -> 2.8568795 | F5: =IF('Year-end close'!F5="","",'Year-end close'!F5*EXP((INDEX('Rates 2y'!$D$2:$D$11,MATCH(IF($C5="GBp","GBP",$C5),'Rates 2y'!$A$2:$A$11,0))-'Dividend yield'!F5)*2)) -> 3.785459 | G5: =IF('Year-end close'!G5="","",'Year-end close'!G5*EXP((INDEX('Rates 2y'!$E$2:$E$11,MATCH(IF($C5="GBp","GBP",$C5),'Rates 2y'!$A$2:$A$11,0))-'Dividend yield'!G5)*2)) -> 8.5879736 | H5: =IF('Year-end close'!H5="","",'Year-end close'!H5*EXP((INDEX('Rates 2y'!$F$2:$F$11,MATCH(IF($C5="GBp","GBP",$C5),'Rates 2y'!$A$2:$A$11,0))-'Dividend yield'!H5)*2)) -> 9.1029592 | I5: =IF('Year-end close'!I5="","",'Year-end close'!I5*EXP((INDEX('Rates 2y'!$G$2:$G$11,MATCH(IF($C5="GBp","GBP",$C5),'Rates 2y'!$A$2:$A$11,0))-'Dividend yield'!I5)*2)) -> 10.968148 | J5: =IF('Year-end close'!J5="","",'Year-end close'!J5*EXP((INDEX('Rates 2y'!$H$2:$H$11,MATCH(IF($C5="GBp","GBP",$C5),'Rates 2y'!$A$2:$A$11,0))-'Dividend yield'!J5)*2)) -> 13.085641 | K5: =IF('Year-end close'!K5="","",'Year-end close'!K5*EXP((INDEX('Rates 2y'!$I$2:$I$11,MATCH(IF($C5="GBp","GBP",$C5),'Rates 2y'!$A$2:$A$11,0))-'Dividend yield'!K5)*2)) -> 14.467331 | L5: =IF('Year-end close'!L5="","",'Year-end close'!L5*EXP((INDEX('Rates 2y'!$J$2:$J$11,MATCH(IF($C5="GBp","GBP",$C5),'Rates 2y'!$A$2:$A$11,0))-'Dividend yield'!L5)*2)) -> 36.433971 | M5: =IF('Year-end close'!M5="","",'Year-end close'!M5*EXP((INDEX('Rates 2y'!$K$2:$K$11,MATCH(IF($C5="GBp","GBP",$C5),'Rates 2y'!$A$2:$A$11,0))-'Dividend yield'!M5)*2)) -> 32.348967
A6: AAL.L | B6: Anglo American plc | C6: GBp | D6: =IF('Year-end close'!D6="","",'Year-end close'!D6*EXP((INDEX('Rates 2y'!$B$2:$B$11,MATCH(IF($C6="GBp","GBP",$C6),'Rates 2y'!$A$2:$A$11,0))-'Dividend yield'!D6)*2)) -> 1479.1881 | E6: =IF('Year-end close'!E6="","",'Year-end close'!E6*EXP((INDEX('Rates 2y'!$C$2:$C$11,MATCH(IF($C6="GBp","GBP",$C6),'Rates 2y'!$A$2:$A$11,0))-'Dividend yield'!E6)*2)) -> 1602.391 | F6: =IF('Year-end close'!F6="","",'Year-end close'!F6*EXP((INDEX('Rates 2y'!$D$2:$D$11,MATCH(IF($C6="GBp","GBP",$C6),'Rates 2y'!$A$2:$A$11,0))-'Dividend yield'!F6)*2)) -> 1994.4889 | G6: =IF('Year-end close'!G6="","",'Year-end close'!G6*EXP((INDEX('Rates 2y'!$E$2:$E$11,MATCH(IF($C6="GBp","GBP",$C6),'Rates 2y'!$A$2:$A$11,0))-'Dividend yield'!G6)*2)) -> 2283.74 | H6: =IF('Year-end close'!H6="","",'Year-end close'!H6*EXP((INDEX('Rates 2y'!$F$2:$F$11,MATCH(IF($C6="GBp","GBP",$C6),'Rates 2y'!$A$2:$A$11,0))-'Dividend yield'!H6)*2)) -> 2556.5563 | I6: =IF('Year-end close'!I6="","",'Year-end close'!I6*EXP((INDEX('Rates 2y'!$G$2:$G$11,MATCH(IF($C6="GBp","GBP",$C6),'Rates 2y'!$A$2:$A$11,0))-'Dividend yield'!I6)*2)) -> 2937.3157 | J6: =IF('Year-end close'!J6="","",'Year-end close'!J6*EXP((INDEX('Rates 2y'!$H$2:$H$11,MATCH(IF($C6="GBp","GBP",$C6),'Rates 2y'!$A$2:$A$11,0))-'Dividend yield'!J6)*2)) -> 1891.3555 | K6: =IF('Year-end close'!K6="","",'Year-end close'!K6*EXP((INDEX('Rates 2y'!$I$2:$I$11,MATCH(IF($C6="GBp","GBP",$C6),'Rates 2y'!$A$2:$A$11,0))-'Dividend yield'!K6)*2)) -> 2422.5646 | L6: =IF('Year-end close'!L6="","",'Year-end close'!L6*EXP((INDEX('Rates 2y'!$J$2:$J$11,MATCH(IF($C6="GBp","GBP",$C6),'Rates 2y'!$A$2:$A$11,0))-'Dividend yield'!L6)*2)) -> 3273.8991 | M6: =IF('Year-end close'!M6="","",'Year-end close'!M6*EXP((INDEX('Rates 2y'!$K$2:$K$11,MATCH(IF($C6="GBp","GBP",$C6),'Rates 2y'!$A$2:$A$11,0))-'Dividend yield'!M6)*2)) -> 4295.1463
A7: AEM | B7: Agnico Eagle Mines Ltd | C7: USD | D7: =IF('Year-end close'!D7="","",'Year-end close'!D7*EXP((INDEX('Rates 2y'!$B$2:$B$11,MATCH(IF($C7="GBp","GBP",$C7),'Rates 2y'!$A$2:$A$11,0))-'Dividend yield'!D7)*2)) -> 47.114971 | E7: =IF('Year-end close'!E7="","",'Year-end close'!E7*EXP((INDEX('Rates 2y'!$C$2:$C$11,MATCH(IF($C7="GBp","GBP",$C7),'Rates 2y'!$A$2:$A$11,0))-'Dividend yield'!E7)*2)) -> 41.547934 | F7: =IF('Year-end close'!F7="","",'Year-end close'!F7*EXP((INDEX('Rates 2y'!$D$2:$D$11,MATCH(IF($C7="GBp","GBP",$C7),'Rates 2y'!$A$2:$A$11,0))-'Dividend yield'!F7)*2)) -> 62.462739 | G7: =IF('Year-end close'!G7="","",'Year-end close'!G7*EXP((INDEX('Rates 2y'!$E$2:$E$11,MATCH(IF($C7="GBp","GBP",$C7),'Rates 2y'!$A$2:$A$11,0))-'Dividend yield'!G7)*2)) -> 68.814092 | H7: =IF('Year-end close'!H7="","",'Year-end close'!H7*EXP((INDEX('Rates 2y'!$F$2:$F$11,MATCH(IF($C7="GBp","GBP",$C7),'Rates 2y'!$A$2:$A$11,0))-'Dividend yield'!H7)*2)) -> 51.153859 | I7: =IF('Year-end close'!I7="","",'Year-end close'!I7*EXP((INDEX('Rates 2y'!$G$2:$G$11,MATCH(IF($C7="GBp","GBP",$C7),'Rates 2y'!$A$2:$A$11,0))-'Dividend yield'!I7)*2)) -> 53.415523 | J7: =IF('Year-end close'!J7="","",'Year-end close'!J7*EXP((INDEX('Rates 2y'!$H$2:$H$11,MATCH(IF($C7="GBp","GBP",$C7),'Rates 2y'!$A$2:$A$11,0))-'Dividend yield'!J7)*2)) -> 56.331968 | K7: =IF('Year-end close'!K7="","",'Year-end close'!K7*EXP((INDEX('Rates 2y'!$I$2:$I$11,MATCH(IF($C7="GBp","GBP",$C7),'Rates 2y'!$A$2:$A$11,0))-'Dividend yield'!K7)*2)) -> 81.71859 | L7: =IF('Year-end close'!L7="","",'Year-end close'!L7*EXP((INDEX('Rates 2y'!$J$2:$J$11,MATCH(IF($C7="GBp","GBP",$C7),'Rates 2y'!$A$2:$A$11,0))-'Dividend yield'!L7)*2)) -> 178.35107 | M7: =IF('Year-end close'!M7="","",'Year-end close'!M7*EXP((INDEX('Rates 2y'!$K$2:$K$11,MATCH(IF($C7="GBp","GBP",$C7),'Rates 2y'!$A$2:$A$11,0))-'Dividend yield'!M7)*2)) -> 205.62319
A8: B | B8: Barrick Mining Corp | C8: USD | D8: =IF('Year-end close'!D8="","",'Year-end close'!D8*EXP((INDEX('Rates 2y'!$B$2:$B$11,MATCH(IF($C8="GBp","GBP",$C8),'Rates 2y'!$A$2:$A$11,0))-'Dividend yield'!D8)*2)) -> 14.780246 | E8: =IF('Year-end close'!E8="","",'Year-end close'!E8*EXP((INDEX('Rates 2y'!$C$2:$C$11,MATCH(IF($C8="GBp","GBP",$C8),'Rates 2y'!$A$2:$A$11,0))-'Dividend yield'!E8)*2)) -> 13.837527 | F8: =IF('Year-end close'!F8="","",'Year-end close'!F8*EXP((INDEX('Rates 2y'!$D$2:$D$11,MATCH(IF($C8="GBp","GBP",$C8),'Rates 2y'!$A$2:$A$11,0))-'Dividend yield'!F8)*2)) -> 18.920345 | G8: =IF('Year-end close'!G8="","",'Year-end close'!G8*EXP((INDEX('Rates 2y'!$E$2:$E$11,MATCH(IF($C8="GBp","GBP",$C8),'Rates 2y'!$A$2:$A$11,0))-'Dividend yield'!G8)*2)) -> 22.226093 | H8: =IF('Year-end close'!H8="","",'Year-end close'!H8*EXP((INDEX('Rates 2y'!$F$2:$F$11,MATCH(IF($C8="GBp","GBP",$C8),'Rates 2y'!$A$2:$A$11,0))-'Dividend yield'!H8)*2)) -> 17.75972 | I8: =IF('Year-end close'!I8="","",'Year-end close'!I8*EXP((INDEX('Rates 2y'!$G$2:$G$11,MATCH(IF($C8="GBp","GBP",$C8),'Rates 2y'!$A$2:$A$11,0))-'Dividend yield'!I8)*2)) -> 17.40358 | J8: =IF('Year-end close'!J8="","",'Year-end close'!J8*EXP((INDEX('Rates 2y'!$H$2:$H$11,MATCH(IF($C8="GBp","GBP",$C8),'Rates 2y'!$A$2:$A$11,0))-'Dividend yield'!J8)*2)) -> 18.842883 | K8: =IF('Year-end close'!K8="","",'Year-end close'!K8*EXP((INDEX('Rates 2y'!$I$2:$I$11,MATCH(IF($C8="GBp","GBP",$C8),'Rates 2y'!$A$2:$A$11,0))-'Dividend yield'!K8)*2)) -> 16.023045 | L8: =IF('Year-end close'!L8="","",'Year-end close'!L8*EXP((INDEX('Rates 2y'!$J$2:$J$11,MATCH(IF($C8="GBp","GBP",$C8),'Rates 2y'!$A$2:$A$11,0))-'Dividend yield'!L8)*2)) -> 45.57684 | M8: =IF('Year-end close'!M8="","",'Year-end close'!M8*EXP((INDEX('Rates 2y'!$K$2:$K$11,MATCH(IF($C8="GBp","GBP",$C8),'Rates 2y'!$A$2:$A$11,0))-'Dividend yield'!M8)*2)) -> 44.34906
A9: BHP.AX | B9: BHP Group Ltd | C9: AUD | D9: =IF('Year-end close'!D9="","",'Year-end close'!D9*EXP((INDEX('Rates 2y'!$B$2:$B$11,MATCH(IF($C9="GBp","GBP",$C9),'Rates 2y'!$A$2:$A$11,0))-'Dividend yield'!D9)*2)) -> 28.393009 | E9: =IF('Year-end close'!E9="","",'Year-end close'!E9*EXP((INDEX('Rates 2y'!$C$2:$C$11,MATCH(IF($C9="GBp","GBP",$C9),'Rates 2y'!$A$2:$A$11,0))-'Dividend yield'!E9)*2)) -> 32.092217 | F9: =IF('Year-end close'!F9="","",'Year-end close'!F9*EXP((INDEX('Rates 2y'!$D$2:$D$11,MATCH(IF($C9="GBp","GBP",$C9),'Rates 2y'!$A$2:$A$11,0))-'Dividend yield'!F9)*2)) -> 32.697208 | G9: =IF('Year-end close'!G9="","",'Year-end close'!G9*EXP((INDEX('Rates 2y'!$E$2:$E$11,MATCH(IF($C9="GBp","GBP",$C9),'Rates 2y'!$A$2:$A$11,0))-'Dividend yield'!G9)*2)) -> 38.755989 | H9: =IF('Year-end close'!H9="","",'Year-end close'!H9*EXP((INDEX('Rates 2y'!$F$2:$F$11,MATCH(IF($C9="GBp","GBP",$C9),'Rates 2y'!$A$2:$A$11,0))-'Dividend yield'!H9)*2)) -> 33.776085 | I9: =IF('Year-end close'!I9="","",'Year-end close'!I9*EXP((INDEX('Rates 2y'!$G$2:$G$11,MATCH(IF($C9="GBp","GBP",$C9),'Rates 2y'!$A$2:$A$11,0))-'Dividend yield'!I9)*2)) -> 39.945794 | J9: =IF('Year-end close'!J9="","",'Year-end close'!J9*EXP((INDEX('Rates 2y'!$H$2:$H$11,MATCH(IF($C9="GBp","GBP",$C9),'Rates 2y'!$A$2:$A$11,0))-'Dividend yield'!J9)*2)) -> 48.933859 | K9: =IF('Year-end close'!K9="","",'Year-end close'!K9*EXP((INDEX('Rates 2y'!$I$2:$I$11,MATCH(IF($C9="GBp","GBP",$C9),'Rates 2y'!$A$2:$A$11,0))-'Dividend yield'!K9)*2)) -> 38.206349 | L9: =IF('Year-end close'!L9="","",'Year-end close'!L9*EXP((INDEX('Rates 2y'!$J$2:$J$11,MATCH(IF($C9="GBp","GBP",$C9),'Rates 2y'!$A$2:$A$11,0))-'Dividend yield'!L9)*2)) -> 45.618007 | M9: =IF('Year-end close'!M9="","",'Year-end close'!M9*EXP((INDEX('Rates 2y'!$K$2:$K$11,MATCH(IF($C9="GBp","GBP",$C9),'Rates 2y'!$A$2:$A$11,0))-'Dividend yield'!M9)*2)) -> 60.619531
A10: EQX | B10: Equinox Gold Corp | C10: USD | D10: =IF('Year-end close'!D10="","",'Year-end close'!D10*EXP((INDEX('Rates 2y'!$B$2:$B$11,MATCH(IF($C10="GBp","GBP",$C10),'Rates 2y'!$A$2:$A$11,0))-'Dividend yield'!D10)*2)) | E10: =IF('Year-end close'!E10="","",'Year-end close'!E10*EXP((INDEX('Rates 2y'!$C$2:$C$11,MATCH(IF($C10="GBp","GBP",$C10),'Rates 2y'!$A$2:$A$11,0))-'Dividend yield'!E10)*2)) | F10: =IF('Year-end close'!F10="","",'Year-end close'!F10*EXP((INDEX('Rates 2y'!$D$2:$D$11,MATCH(IF($C10="GBp","GBP",$C10),'Rates 2y'!$A$2:$A$11,0))-'Dividend yield'!F10)*2)) -> 7.9472053 | G10: =IF('Year-end close'!G10="","",'Year-end close'!G10*EXP((INDEX('Rates 2y'!$E$2:$E$11,MATCH(IF($C10="GBp","GBP",$C10),'Rates 2y'!$A$2:$A$11,0))-'Dividend yield'!G10)*2)) -> 10.366919 | H10: =IF('Year-end close'!H10="","",'Year-end close'!H10*EXP((INDEX('Rates 2y'!$F$2:$F$11,MATCH(IF($C10="GBp","GBP",$C10),'Rates 2y'!$A$2:$A$11,0))-'Dividend yield'!H10)*2)) -> 6.85942 | I10: =IF('Year-end close'!I10="","",'Year-end close'!I10*EXP((INDEX('Rates 2y'!$G$2:$G$11,MATCH(IF($C10="GBp","GBP",$C10),'Rates 2y'!$A$2:$A$11,0))-'Dividend yield'!I10)*2)) -> 3.5838707 | J10: =IF('Year-end close'!J10="","",'Year-end close'!J10*EXP((INDEX('Rates 2y'!$H$2:$H$11,MATCH(IF($C10="GBp","GBP",$C10),'Rates 2y'!$A$2:$A$11,0))-'Dividend yield'!J10)*2)) -> 5.3238265 | K10: =IF('Year-end close'!K10="","",'Year-end close'!K10*EXP((INDEX('Rates 2y'!$I$2:$I$11,MATCH(IF($C10="GBp","GBP",$C10),'Rates 2y'!$A$2:$A$11,0))-'Dividend yield'!K10)*2)) -> 5.4642667 | L10: =IF('Year-end close'!L10="","",'Year-end close'!L10*EXP((INDEX('Rates 2y'!$J$2:$J$11,MATCH(IF($C10="GBp","GBP",$C10),'Rates 2y'!$A$2:$A$11,0))-'Dividend yield'!L10)*2)) -> 15.051993 | M10: =IF('Year-end close'!M10="","",'Year-end close'!M10*EXP((INDEX('Rates 2y'!$K$2:$K$11,MATCH(IF($C10="GBp","GBP",$C10),'Rates 2y'!$A$2:$A$11,0))-'Dividend yield'!M10)*2)) -> 12.687485
A11: EVN.AX | B11: Evolution Mining Ltd | C11: AUD | D11: =IF('Year-end close'!D11="","",'Year-end close'!D11*EXP((INDEX('Rates 2y'!$B$2:$B$11,MATCH(IF($C11="GBp","GBP",$C11),'Rates 2y'!$A$2:$A$11,0))-'Dividend yield'!D11)*2)) -> 2.6560064 | E11: =IF('Year-end close'!E11="","",'Year-end close'!E11*EXP((INDEX('Rates 2y'!$C$2:$C$11,MATCH(IF($C11="GBp","GBP",$C11),'Rates 2y'!$A$2:$A$11,0))-'Dividend yield'!E11)*2)) -> 3.6802344 | F11: =IF('Year-end close'!F11="","",'Year-end close'!F11*EXP((INDEX('Rates 2y'!$D$2:$D$11,MATCH(IF($C11="GBp","GBP",$C11),'Rates 2y'!$A$2:$A$11,0))-'Dividend yield'!F11)*2)) -> 3.680325 | G11: =IF('Year-end close'!G11="","",'Year-end close'!G11*EXP((INDEX('Rates 2y'!$E$2:$E$11,MATCH(IF($C11="GBp","GBP",$C11),'Rates 2y'!$A$2:$A$11,0))-'Dividend yield'!G11)*2)) -> 4.6894153 | H11: =IF('Year-end close'!H11="","",'Year-end close'!H11*EXP((INDEX('Rates 2y'!$F$2:$F$11,MATCH(IF($C11="GBp","GBP",$C11),'Rates 2y'!$A$2:$A$11,0))-'Dividend yield'!H11)*2)) -> 3.8731533 | I11: =IF('Year-end close'!I11="","",'Year-end close'!I11*EXP((INDEX('Rates 2y'!$G$2:$G$11,MATCH(IF($C11="GBp","GBP",$C11),'Rates 2y'!$A$2:$A$11,0))-'Dividend yield'!I11)*2)) -> 3.0699317 | J11: =IF('Year-end close'!J11="","",'Year-end close'!J11*EXP((INDEX('Rates 2y'!$H$2:$H$11,MATCH(IF($C11="GBp","GBP",$C11),'Rates 2y'!$A$2:$A$11,0))-'Dividend yield'!J11)*2)) -> 4.1788748 | K11: =IF('Year-end close'!K11="","",'Year-end close'!K11*EXP((INDEX('Rates 2y'!$I$2:$I$11,MATCH(IF($C11="GBp","GBP",$C11),'Rates 2y'!$A$2:$A$11,0))-'Dividend yield'!K11)*2)) -> 5.045976 | L11: =IF('Year-end close'!L11="","",'Year-end close'!L11*EXP((INDEX('Rates 2y'!$J$2:$J$11,MATCH(IF($C11="GBp","GBP",$C11),'Rates 2y'!$A$2:$A$11,0))-'Dividend yield'!L11)*2)) -> 13.282933 | M11: =IF('Year-end close'!M11="","",'Year-end close'!M11*EXP((INDEX('Rates 2y'!$K$2:$K$11,MATCH(IF($C11="GBp","GBP",$C11),'Rates 2y'!$A$2:$A$11,0))-'Dividend yield'!M11)*2)) -> 13.961667
A12: FCX | B12: Freeport-McMoRan Inc | C12: USD | D12: =IF('Year-end close'!D12="","",'Year-end close'!D12*EXP((INDEX('Rates 2y'!$B$2:$B$11,MATCH(IF($C12="GBp","GBP",$C12),'Rates 2y'!$A$2:$A$11,0))-'Dividend yield'!D12)*2)) -> 19.690406 | E12: =IF('Year-end close'!E12="","",'Year-end close'!E12*EXP((INDEX('Rates 2y'!$C$2:$C$11,MATCH(IF($C12="GBp","GBP",$C12),'Rates 2y'!$A$2:$A$11,0))-'Dividend yield'!E12)*2)) -> 10.525662 | F12: =IF('Year-end close'!F12="","",'Year-end close'!F12*EXP((INDEX('Rates 2y'!$D$2:$D$11,MATCH(IF($C12="GBp","GBP",$C12),'Rates 2y'!$A$2:$A$11,0))-'Dividend yield'!F12)*2)) -> 13.134598 | G12: =IF('Year-end close'!G12="","",'Year-end close'!G12*EXP((INDEX('Rates 2y'!$E$2:$E$11,MATCH(IF($C12="GBp","GBP",$C12),'Rates 2y'!$A$2:$A$11,0))-'Dividend yield'!G12)*2)) -> 25.987651 | H12: =IF('Year-end close'!H12="","",'Year-end close'!H12*EXP((INDEX('Rates 2y'!$F$2:$F$11,MATCH(IF($C12="GBp","GBP",$C12),'Rates 2y'!$A$2:$A$11,0))-'Dividend yield'!H12)*2)) -> 41.889546 | I12: =IF('Year-end close'!I12="","",'Year-end close'!I12*EXP((INDEX('Rates 2y'!$G$2:$G$11,MATCH(IF($C12="GBp","GBP",$C12),'Rates 2y'!$A$2:$A$11,0))-'Dividend yield'!I12)*2)) -> 40.229806 | J12: =IF('Year-end close'!J12="","",'Year-end close'!J12*EXP((INDEX('Rates 2y'!$H$2:$H$11,MATCH(IF($C12="GBp","GBP",$C12),'Rates 2y'!$A$2:$A$11,0))-'Dividend yield'!J12)*2)) -> 45.058506 | K12: =IF('Year-end close'!K12="","",'Year-end close'!K12*EXP((INDEX('Rates 2y'!$I$2:$I$11,MATCH(IF($C12="GBp","GBP",$C12),'Rates 2y'!$A$2:$A$11,0))-'Dividend yield'!K12)*2)) -> 40.164247 | L12: =IF('Year-end close'!L12="","",'Year-end close'!L12*EXP((INDEX('Rates 2y'!$J$2:$J$11,MATCH(IF($C12="GBp","GBP",$C12),'Rates 2y'!$A$2:$A$11,0))-'Dividend yield'!L12)*2)) -> 53.179527 | M12: =IF('Year-end close'!M12="","",'Year-end close'!M12*EXP((INDEX('Rates 2y'!$K$2:$K$11,MATCH(IF($C12="GBp","GBP",$C12),'Rates 2y'!$A$2:$A$11,0))-'Dividend yield'!M12)*2)) -> 76.563191
A13: FMG.AX | B13: Fortescue Ltd | C13: AUD | D13: =IF('Year-end close'!D13="","",'Year-end close'!D13*EXP((INDEX('Rates 2y'!$B$2:$B$11,MATCH(IF($C13="GBp","GBP",$C13),'Rates 2y'!$A$2:$A$11,0))-'Dividend yield'!D13)*2)) -> 4.2237325 | E13: =IF('Year-end close'!E13="","",'Year-end close'!E13*EXP((INDEX('Rates 2y'!$C$2:$C$11,MATCH(IF($C13="GBp","GBP",$C13),'Rates 2y'!$A$2:$A$11,0))-'Dividend yield'!E13)*2)) -> 3.8997589 | F13: =IF('Year-end close'!F13="","",'Year-end close'!F13*EXP((INDEX('Rates 2y'!$D$2:$D$11,MATCH(IF($C13="GBp","GBP",$C13),'Rates 2y'!$A$2:$A$11,0))-'Dividend yield'!F13)*2)) -> 8.7936048 | G13: =IF('Year-end close'!G13="","",'Year-end close'!G13*EXP((INDEX('Rates 2y'!$E$2:$E$11,MATCH(IF($C13="GBp","GBP",$C13),'Rates 2y'!$A$2:$A$11,0))-'Dividend yield'!G13)*2)) -> 20.202033 | H13: =IF('Year-end close'!H13="","",'Year-end close'!H13*EXP((INDEX('Rates 2y'!$F$2:$F$11,MATCH(IF($C13="GBp","GBP",$C13),'Rates 2y'!$A$2:$A$11,0))-'Dividend yield'!H13)*2)) -> 13.392689 | I13: =IF('Year-end close'!I13="","",'Year-end close'!I13*EXP((INDEX('Rates 2y'!$G$2:$G$11,MATCH(IF($C13="GBp","GBP",$C13),'Rates 2y'!$A$2:$A$11,0))-'Dividend yield'!I13)*2)) -> 17.976414 | J13: =IF('Year-end close'!J13="","",'Year-end close'!J13*EXP((INDEX('Rates 2y'!$H$2:$H$11,MATCH(IF($C13="GBp","GBP",$C13),'Rates 2y'!$A$2:$A$11,0))-'Dividend yield'!J13)*2)) -> 27.698527 | K13: =IF('Year-end close'!K13="","",'Year-end close'!K13*EXP((INDEX('Rates 2y'!$I$2:$I$11,MATCH(IF($C13="GBp","GBP",$C13),'Rates 2y'!$A$2:$A$11,0))-'Dividend yield'!K13)*2)) -> 15.883409 | L13: =IF('Year-end close'!L13="","",'Year-end close'!L13*EXP((INDEX('Rates 2y'!$J$2:$J$11,MATCH(IF($C13="GBp","GBP",$C13),'Rates 2y'!$A$2:$A$11,0))-'Dividend yield'!L13)*2)) -> 21.532058 | M13: =IF('Year-end close'!M13="","",'Year-end close'!M13*EXP((INDEX('Rates 2y'!$K$2:$K$11,MATCH(IF($C13="GBp","GBP",$C13),'Rates 2y'!$A$2:$A$11,0))-'Dividend yield'!M13)*2)) -> 15.51027
... A26: VALE3.SA | B26: Vale SA | C26: BRL | D26: =IF('Year-end close'!D26="","",'Year-end close'!D26*EXP((INDEX('Rates 2y'!$B$2:$B$11,MATCH(IF($C26="GBp","GBP",$C26),'Rates 2y'!$A$2:$A$11,0))-'Dividend yield'!D26)*2)) -> 43.794683 | E26: =IF('Year-end close'!E26="","",'Year-end close'!E26*EXP((INDEX('Rates 2y'!$C$2:$C$11,MATCH(IF($C26="GBp","GBP",$C26),'Rates 2y'!$A$2:$A$11,0))-'Dividend yield'!E26)*2)) -> 54.522618 | F26: =IF('Year-end close'!F26="","",'Year-end close'!F26*EXP((INDEX('Rates 2y'!$D$2:$D$11,MATCH(IF($C26="GBp","GBP",$C26),'Rates 2y'!$A$2:$A$11,0))-'Dividend yield'!F26)*2)) -> 56.197054 | G26: =IF('Year-end close'!G26="","",'Year-end close'!G26*EXP((INDEX('Rates 2y'!$E$2:$E$11,MATCH(IF($C26="GBp","GBP",$C26),'Rates 2y'!$A$2:$A$11,0))-'Dividend yield'!G26)*2)) -> 90.197995 | H26: =IF('Year-end close'!H26="","",'Year-end close'!H26*EXP((INDEX('Rates 2y'!$F$2:$F$11,MATCH(IF($C26="GBp","GBP",$C26),'Rates 2y'!$A$2:$A$11,0))-'Dividend yield'!H26)*2)) -> 67.114484 | I26: =IF('Year-end close'!I26="","",'Year-end close'!I26*EXP((INDEX('Rates 2y'!$G$2:$G$11,MATCH(IF($C26="GBp","GBP",$C26),'Rates 2y'!$A$2:$A$11,0))-'Dividend yield'!I26)*2)) -> 97.968416 | J26: =IF('Year-end close'!J26="","",'Year-end close'!J26*EXP((INDEX('Rates 2y'!$H$2:$H$11,MATCH(IF($C26="GBp","GBP",$C26),'Rates 2y'!$A$2:$A$11,0))-'Dividend yield'!J26)*2)) -> 81.040048 | K26: =IF('Year-end close'!K26="","",'Year-end close'!K26*EXP((INDEX('Rates 2y'!$I$2:$I$11,MATCH(IF($C26="GBp","GBP",$C26),'Rates 2y'!$A$2:$A$11,0))-'Dividend yield'!K26)*2)) -> 60.999259 | L26: =IF('Year-end close'!L26="","",'Year-end close'!L26*EXP((INDEX('Rates 2y'!$J$2:$J$11,MATCH(IF($C26="GBp","GBP",$C26),'Rates 2y'!$A$2:$A$11,0))-'Dividend yield'!L26)*2)) -> 76.888353 | M26: =IF('Year-end close'!M26="","",'Year-end close'!M26*EXP((INDEX('Rates 2y'!$K$2:$K$11,MATCH(IF($C26="GBp","GBP",$C26),'Rates 2y'!$A$2:$A$11,0))-'Dividend yield'!M26)*2)) -> 88.238659
A28: Price a 2-year future set at the end of (column year - 2) would have had: close x exp((2y rate - dividend yield) x 2). Carry only, not a forecast.

Sheet 2y forward USD
A1: ticker | B1: company | C1: currency | D1: 2019 | E1: 2020 | F1: 2021 | G1: 2022 | H1: 2023 | I1: 2024 | J1: 2025 | K1: 2026 | L1: 2027 | M1: 2028
A2: 000408.SZ | B2: Zangge Mining Co Ltd | C2: USD | D2: =IF('2y forward'!D2="","",'2y forward'!D2/IF('2y forward'!$C2="GBp",100,1)/INDEX('FX 2y forward'!$B$2:$B$11,MATCH(IF('2y forward'!$C2="GBp","GBP",'2y forward'!$C2),'FX 2y forward'!$A$2:$A$11,0))) -> 2.7204973 | E2: =IF('2y forward'!E2="","",'2y forward'!E2/IF('2y forward'!$C2="GBp",100,1)/INDEX('FX 2y forward'!$C$2:$C$11,MATCH(IF('2y forward'!$C2="GBp","GBP",'2y forward'!$C2),'FX 2y forward'!$A$2:$A$11,0))) -> 1.7147826 | F2: =IF('2y forward'!F2="","",'2y forward'!F2/IF('2y forward'!$C2="GBp",100,1)/INDEX('FX 2y forward'!$D$2:$D$11,MATCH(IF('2y forward'!$C2="GBp","GBP",'2y forward'!$C2),'FX 2y forward'!$A$2:$A$11,0))) -> 1.0903606 | G2: =IF('2y forward'!G2="","",'2y forward'!G2/IF('2y forward'!$C2="GBp",100,1)/INDEX('FX 2y forward'!$E$2:$E$11,MATCH(IF('2y forward'!$C2="GBp","GBP",'2y forward'!$C2),'FX 2y forward'!$A$2:$A$11,0))) -> 1.2313105 | H2: =IF('2y forward'!H2="","",'2y forward'!H2/IF('2y forward'!$C2="GBp",100,1)/INDEX('FX 2y forward'!$F$2:$F$11,MATCH(IF('2y forward'!$C2="GBp","GBP",'2y forward'!$C2),'FX 2y forward'!$A$2:$A$11,0))) -> 6.5289294 | I2: =IF('2y forward'!I2="","",'2y forward'!I2/IF('2y forward'!$C2="GBp",100,1)/INDEX('FX 2y forward'!$G$2:$G$11,MATCH(IF('2y forward'!$C2="GBp","GBP",'2y forward'!$C2),'FX 2y forward'!$A$2:$A$11,0))) -> 3.5210148 | J2: =IF('2y forward'!J2="","",'2y forward'!J2/IF('2y forward'!$C2="GBp",100,1)/INDEX('FX 2y forward'!$H$2:$H$11,MATCH(IF('2y forward'!$C2="GBp","GBP",'2y forward'!$C2),'FX 2y forward'!$A$2:$A$11,0))) -> 3.3783721 | K2: =IF('2y forward'!K2="","",'2y forward'!K2/IF('2y forward'!$C2="GBp",100,1)/INDEX('FX 2y forward'!$I$2:$I$11,MATCH(IF('2y forward'!$C2="GBp","GBP",'2y forward'!$C2),'FX 2y forward'!$A$2:$A$11,0))) -> 3.8314711 | L2: =IF('2y forward'!L2="","",'2y forward'!L2/IF('2y forward'!$C2="GBp",100,1)/INDEX('FX 2y forward'!$J$2:$J$11,MATCH(IF('2y forward'!$C2="GBp","GBP",'2y forward'!$C2),'FX 2y forward'!$A$2:$A$11,0))) -> 12.630551 | M2: =IF('2y forward'!M2="","",'2y forward'!M2/IF('2y forward'!$C2="GBp",100,1)/INDEX('FX 2y forward'!$K$2:$K$11,MATCH(IF('2y forward'!$C2="GBp","GBP",'2y forward'!$C2),'FX 2y forward'!$A$2:$A$11,0))) -> 10.642189
A3: 1208.HK | B3: MMG Ltd | C3: USD | D3: =IF('2y forward'!D3="","",'2y forward'!D3/IF('2y forward'!$C3="GBp",100,1)/INDEX('FX 2y forward'!$B$2:$B$11,MATCH(IF('2y forward'!$C3="GBp","GBP",'2y forward'!$C3),'FX 2y forward'!$A$2:$A$11,0))) -> 0.51548859 | E3: =IF('2y forward'!E3="","",'2y forward'!E3/IF('2y forward'!$C3="GBp",100,1)/INDEX('FX 2y forward'!$C$2:$C$11,MATCH(IF('2y forward'!$C3="GBp","GBP",'2y forward'!$C3),'FX 2y forward'!$A$2:$A$11,0))) -> 0.45232031 | F3: =IF('2y forward'!F3="","",'2y forward'!F3/IF('2y forward'!$C3="GBp",100,1)/INDEX('FX 2y forward'!$D$2:$D$11,MATCH(IF('2y forward'!$C3="GBp","GBP",'2y forward'!$C3),'FX 2y forward'!$A$2:$A$11,0))) -> 0.31010448 | G3: =IF('2y forward'!G3="","",'2y forward'!G3/IF('2y forward'!$C3="GBp",100,1)/INDEX('FX 2y forward'!$E$2:$E$11,MATCH(IF('2y forward'!$C3="GBp","GBP",'2y forward'!$C3),'FX 2y forward'!$A$2:$A$11,0))) -> 0.43326153 | H3: =IF('2y forward'!H3="","",'2y forward'!H3/IF('2y forward'!$C3="GBp",100,1)/INDEX('FX 2y forward'!$F$2:$F$11,MATCH(IF('2y forward'!$C3="GBp","GBP",'2y forward'!$C3),'FX 2y forward'!$A$2:$A$11,0))) -> 0.3253284 | I3: =IF('2y forward'!I3="","",'2y forward'!I3/IF('2y forward'!$C3="GBp",100,1)/INDEX('FX 2y forward'!$G$2:$G$11,MATCH(IF('2y forward'!$C3="GBp","GBP",'2y forward'!$C3),'FX 2y forward'!$A$2:$A$11,0))) -> 0.28036629 | J3: =IF('2y forward'!J3="","",'2y forward'!J3/IF('2y forward'!$C3="GBp",100,1)/INDEX('FX 2y forward'!$H$2:$H$11,MATCH(IF('2y forward'!$C3="GBp","GBP",'2y forward'!$C3),'FX 2y forward'!$A$2:$A$11,0))) -> 0.32194071 | K3: =IF('2y forward'!K3="","",'2y forward'!K3/IF('2y forward'!$C3="GBp",100,1)/INDEX('FX 2y forward'!$I$2:$I$11,MATCH(IF('2y forward'!$C3="GBp","GBP",'2y forward'!$C3),'FX 2y forward'!$A$2:$A$11,0))) -> 0.36033275 | L3: =IF('2y forward'!L3="","",'2y forward'!L3/IF('2y forward'!$C3="GBp",100,1)/INDEX('FX 2y forward'!$J$2:$J$11,MATCH(IF('2y forward'!$C3="GBp","GBP",'2y forward'!$C3),'FX 2y forward'!$A$2:$A$11,0))) -> 1.2139097 | M3: =IF('2y forward'!M3="","",'2y forward'!M3/IF('2y forward'!$C3="GBp",100,1)/INDEX('FX 2y forward'!$K$2:$K$11,MATCH(IF('2y forward'!$C3="GBp","GBP",'2y forward'!$C3),'FX 2y forward'!$A$2:$A$11,0))) -> 1.1679778
A4: 1211.SR | B4: Saudi Arabian Mining Co (Maaden) | C4: USD | D4: =IF('2y forward'!D4="","",'2y forward'!D4/IF('2y forward'!$C4="GBp",100,1)/INDEX('FX 2y forward'!$B$2:$B$11,MATCH(IF('2y forward'!$C4="GBp","GBP",'2y forward'!$C4),'FX 2y forward'!$A$2:$A$11,0))) -> 14.445503 | E4: =IF('2y forward'!E4="","",'2y forward'!E4/IF('2y forward'!$C4="GBp",100,1)/INDEX('FX 2y forward'!$C$2:$C$11,MATCH(IF('2y forward'!$C4="GBp","GBP",'2y forward'!$C4),'FX 2y forward'!$A$2:$A$11,0))) -> 13.812422 | F4: =IF('2y forward'!F4="","",'2y forward'!F4/IF('2y forward'!$C4="GBp",100,1)/INDEX('FX 2y forward'!$D$2:$D$11,MATCH(IF('2y forward'!$C4="GBp","GBP",'2y forward'!$C4),'FX 2y forward'!$A$2:$A$11,0))) -> 12.225465 | G4: =IF('2y forward'!G4="","",'2y forward'!G4/IF('2y forward'!$C4="GBp",100,1)/INDEX('FX 2y forward'!$E$2:$E$11,MATCH(IF('2y forward'!$C4="GBp","GBP",'2y forward'!$C4),'FX 2y forward'!$A$2:$A$11,0))) -> 10.834745 | H4: =IF('2y forward'!H4="","",'2y forward'!H4/IF('2y forward'!$C4="GBp",100,1)/INDEX('FX 2y forward'!$F$2:$F$11,MATCH(IF('2y forward'!$C4="GBp","GBP",'2y forward'!$C4),'FX 2y forward'!$A$2:$A$11,0))) -> 21.241361 | I4: =IF('2y forward'!I4="","",'2y forward'!I4/IF('2y forward'!$C4="GBp",100,1)/INDEX('FX 2y forward'!$G$2:$G$11,MATCH(IF('2y forward'!$C4="GBp","GBP",'2y forward'!$C4),'FX 2y forward'!$A$2:$A$11,0))) -> 18.826931 | J4: =IF('2y forward'!J4="","",'2y forward'!J4/IF('2y forward'!$C4="GBp",100,1)/INDEX('FX 2y forward'!$H$2:$H$11,MATCH(IF('2y forward'!$C4="GBp","GBP",'2y forward'!$C4),'FX 2y forward'!$A$2:$A$11,0))) -> 14.11325 | K4: =IF('2y forward'!K4="","",'2y forward'!K4/IF('2y forward'!$C4="GBp",100,1)/INDEX('FX 2y forward'!$I$2:$I$11,MATCH(IF('2y forward'!$C4="GBp","GBP",'2y forward'!$C4),'FX 2y forward'!$A$2:$A$11,0))) -> 14.592688 | L4: =IF('2y forward'!L4="","",'2y forward'!L4/IF('2y forward'!$C4="GBp",100,1)/INDEX('FX 2y forward'!$J$2:$J$11,MATCH(IF('2y forward'!$C4="GBp","GBP",'2y forward'!$C4),'FX 2y forward'!$A$2:$A$11,0))) -> 17.434625 | M4: =IF('2y forward'!M4="","",'2y forward'!M4/IF('2y forward'!$C4="GBp",100,1)/INDEX('FX 2y forward'!$K$2:$K$11,MATCH(IF('2y forward'!$C4="GBp","GBP",'2y forward'!$C4),'FX 2y forward'!$A$2:$A$11,0))) -> 17.447738
A5: 2899.HK | B5: Zijin Mining Group Co Ltd | C5: USD | D5: =IF('2y forward'!D5="","",'2y forward'!D5/IF('2y forward'!$C5="GBp",100,1)/INDEX('FX 2y forward'!$B$2:$B$11,MATCH(IF('2y forward'!$C5="GBp","GBP",'2y forward'!$C5),'FX 2y forward'!$A$2:$A$11,0))) -> 0.37410076 | E5: =IF('2y forward'!E5="","",'2y forward'!E5/IF('2y forward'!$C5="GBp",100,1)/INDEX('FX 2y forward'!$C$2:$C$11,MATCH(IF('2y forward'!$C5="GBp","GBP",'2y forward'!$C5),'FX 2y forward'!$A$2:$A$11,0))) -> 0.36989078 | F5: =IF('2y forward'!F5="","",'2y forward'!F5/IF('2y forward'!$C5="GBp",100,1)/INDEX('FX 2y forward'!$D$2:$D$11,MATCH(IF('2y forward'!$C5="GBp","GBP",'2y forward'!$C5),'FX 2y forward'!$A$2:$A$11,0))) -> 0.48489167 | G5: =IF('2y forward'!G5="","",'2y forward'!G5/IF('2y forward'!$C5="GBp",100,1)/INDEX('FX 2y forward'!$E$2:$E$11,MATCH(IF('2y forward'!$C5="GBp","GBP",'2y forward'!$C5),'FX 2y forward'!$A$2:$A$11,0))) -> 1.1062642 | H5: =IF('2y forward'!H5="","",'2y forward'!H5/IF('2y forward'!$C5="GBp",100,1)/INDEX('FX 2y forward'!$F$2:$F$11,MATCH(IF('2y forward'!$C5="GBp","GBP",'2y forward'!$C5),'FX 2y forward'!$A$2:$A$11,0))) -> 1.1704505 | I5: =IF('2y forward'!I5="","",'2y forward'!I5/IF('2y forward'!$C5="GBp",100,1)/INDEX('FX 2y forward'!$G$2:$G$11,MATCH(IF('2y forward'!$C5="GBp","GBP",'2y forward'!$C5),'FX 2y forward'!$A$2:$A$11,0))) -> 1.4193371 | J5: =IF('2y forward'!J5="","",'2y forward'!J5/IF('2y forward'!$C5="GBp",100,1)/INDEX('FX 2y forward'!$H$2:$H$11,MATCH(IF('2y forward'!$C5="GBp","GBP",'2y forward'!$C5),'FX 2y forward'!$A$2:$A$11,0))) -> 1.6970308 | K5: =IF('2y forward'!K5="","",'2y forward'!K5/IF('2y forward'!$C5="GBp",100,1)/INDEX('FX 2y forward'!$I$2:$I$11,MATCH(IF('2y forward'!$C5="GBp","GBP",'2y forward'!$C5),'FX 2y forward'!$A$2:$A$11,0))) -> 1.8950777 | L5: =IF('2y forward'!L5="","",'2y forward'!L5/IF('2y forward'!$C5="GBp",100,1)/INDEX('FX 2y forward'!$J$2:$J$11,MATCH(IF('2y forward'!$C5="GBp","GBP",'2y forward'!$C5),'FX 2y forward'!$A$2:$A$11,0))) -> 4.7657763 | M5: =IF('2y forward'!M5="","",'2y forward'!M5/IF('2y forward'!$C5="GBp",100,1)/INDEX('FX 2y forward'!$K$2:$K$11,MATCH(IF('2y forward'!$C5="GBp","GBP",'2y forward'!$C5),'FX 2y forward'!$A$2:$A$11,0))) -> 4.1975863
A6: AAL.L | B6: Anglo American plc | C6: USD | D6: =IF('2y forward'!D6="","",'2y forward'!D6/IF('2y forward'!$C6="GBp",100,1)/INDEX('FX 2y forward'!$B$2:$B$11,MATCH(IF('2y forward'!$C6="GBp","GBP",'2y forward'!$C6),'FX 2y forward'!$A$2:$A$11,0))) -> 20.462474 | E6: =IF('2y forward'!E6="","",'2y forward'!E6/IF('2y forward'!$C6="GBp",100,1)/INDEX('FX 2y forward'!$C$2:$C$11,MATCH(IF('2y forward'!$C6="GBp","GBP",'2y forward'!$C6),'FX 2y forward'!$A$2:$A$11,0))) -> 21.060369 | F6: =IF('2y forward'!F6="","",'2y forward'!F6/IF('2y forward'!$C6="GBp",100,1)/INDEX('FX 2y forward'!$D$2:$D$11,MATCH(IF('2y forward'!$C6="GBp","GBP",'2y forward'!$C6),'FX 2y forward'!$A$2:$A$11,0))) -> 26.698157 | G6: =IF('2y forward'!G6="","",'2y forward'!G6/IF('2y forward'!$C6="GBp",100,1)/INDEX('FX 2y forward'!$E$2:$E$11,MATCH(IF('2y forward'!$C6="GBp","GBP",'2y forward'!$C6),'FX 2y forward'!$A$2:$A$11,0))) -> 31.303702 | H6: =IF('2y forward'!H6="","",'2y forward'!H6/IF('2y forward'!$C6="GBp",100,1)/INDEX('FX 2y forward'!$F$2:$F$11,MATCH(IF('2y forward'!$C6="GBp","GBP",'2y forward'!$C6),'FX 2y forward'!$A$2:$A$11,0))) -> 34.530063 | I6: =IF('2y forward'!I6="","",'2y forward'!I6/IF('2y forward'!$C6="GBp",100,1)/INDEX('FX 2y forward'!$G$2:$G$11,MATCH(IF('2y forward'!$C6="GBp","GBP",'2y forward'!$C6),'FX 2y forward'!$A$2:$A$11,0))) -> 36.006005 | J6: =IF('2y forward'!J6="","",'2y forward'!J6/IF('2y forward'!$C6="GBp",100,1)/INDEX('FX 2y forward'!$H$2:$H$11,MATCH(IF('2y forward'!$C6="GBp","GBP",'2y forward'!$C6),'FX 2y forward'!$A$2:$A$11,0))) -> 24.20522 | K6: =IF('2y forward'!K6="","",'2y forward'!K6/IF('2y forward'!$C6="GBp",100,1)/INDEX('FX 2y forward'!$I$2:$I$11,MATCH(IF('2y forward'!$C6="GBp","GBP",'2y forward'!$C6),'FX 2y forward'!$A$2:$A$11,0))) -> 30.303874 | L6: =IF('2y forward'!L6="","",'2y forward'!L6/IF('2y forward'!$C6="GBp",100,1)/INDEX('FX 2y forward'!$J$2:$J$11,MATCH(IF('2y forward'!$C6="GBp","GBP",'2y forward'!$C6),'FX 2y forward'!$A$2:$A$11,0))) -> 43.852799 | M6: =IF('2y forward'!M6="","",'2y forward'!M6/IF('2y forward'!$C6="GBp",100,1)/INDEX('FX 2y forward'!$K$2:$K$11,MATCH(IF('2y forward'!$C6="GBp","GBP",'2y forward'!$C6),'FX 2y forward'!$A$2:$A$11,0))) -> 56.53356
A7: AEM | B7: Agnico Eagle Mines Ltd | C7: USD | D7: =IF('2y forward'!D7="","",'2y forward'!D7/IF('2y forward'!$C7="GBp",100,1)/INDEX('FX 2y forward'!$B$2:$B$11,MATCH(IF('2y forward'!$C7="GBp","GBP",'2y forward'!$C7),'FX 2y forward'!$A$2:$A$11,0))) -> 47.114971 | E7: =IF('2y forward'!E7="","",'2y forward'!E7/IF('2y forward'!$C7="GBp",100,1)/INDEX('FX 2y forward'!$C$2:$C$11,MATCH(IF('2y forward'!$C7="GBp","GBP",'2y forward'!$C7),'FX 2y forward'!$A$2:$A$11,0))) -> 41.547934 | F7: =IF('2y forward'!F7="","",'2y forward'!F7/IF('2y forward'!$C7="GBp",100,1)/INDEX('FX 2y forward'!$D$2:$D$11,MATCH(IF('2y forward'!$C7="GBp","GBP",'2y forward'!$C7),'FX 2y forward'!$A$2:$A$11,0))) -> 62.462739 | G7: =IF('2y forward'!G7="","",'2y forward'!G7/IF('2y forward'!$C7="GBp",100,1)/INDEX('FX 2y forward'!$E$2:$E$11,MATCH(IF('2y forward'!$C7="GBp","GBP",'2y forward'!$C7),'FX 2y forward'!$A$2:$A$11,0))) -> 68.814092 | H7: =IF('2y forward'!H7="","",'2y forward'!H7/IF('2y forward'!$C7="GBp",100,1)/INDEX('FX 2y forward'!$F$2:$F$11,MATCH(IF('2y forward'!$C7="GBp","GBP",'2y forward'!$C7),'FX 2y forward'!$A$2:$A$11,0))) -> 51.153859 | I7: =IF('2y forward'!I7="","",'2y forward'!I7/IF('2y forward'!$C7="GBp",100,1)/INDEX('FX 2y forward'!$G$2:$G$11,MATCH(IF('2y forward'!$C7="GBp","GBP",'2y forward'!$C7),'FX 2y forward'!$A$2:$A$11,0))) -> 53.415523 | J7: =IF('2y forward'!J7="","",'2y forward'!J7/IF('2y forward'!$C7="GBp",100,1)/INDEX('FX 2y forward'!$H$2:$H$11,MATCH(IF('2y forward'!$C7="GBp","GBP",'2y forward'!$C7),'FX 2y forward'!$A$2:$A$11,0))) -> 56.331968 | K7: =IF('2y forward'!K7="","",'2y forward'!K7/IF('2y forward'!$C7="GBp",100,1)/INDEX('FX 2y forward'!$I$2:$I$11,MATCH(IF('2y forward'!$C7="GBp","GBP",'2y forward'!$C7),'FX 2y forward'!$A$2:$A$11,0))) -> 81.71859 | L7: =IF('2y forward'!L7="","",'2y forward'!L7/IF('2y forward'!$C7="GBp",100,1)/INDEX('FX 2y forward'!$J$2:$J$11,MATCH(IF('2y forward'!$C7="GBp","GBP",'2y forward'!$C7),'FX 2y forward'!$A$2:$A$11,0))) -> 178.35107 | M7: =IF('2y forward'!M7="","",'2y forward'!M7/IF('2y forward'!$C7="GBp",100,1)/INDEX('FX 2y forward'!$K$2:$K$11,MATCH(IF('2y forward'!$C7="GBp","GBP",'2y forward'!$C7),'FX 2y forward'!$A$2:$A$11,0))) -> 205.62319
A8: B | B8: Barrick Mining Corp | C8: USD | D8: =IF('2y forward'!D8="","",'2y forward'!D8/IF('2y forward'!$C8="GBp",100,1)/INDEX('FX 2y forward'!$B$2:$B$11,MATCH(IF('2y forward'!$C8="GBp","GBP",'2y forward'!$C8),'FX 2y forward'!$A$2:$A$11,0))) -> 14.780246 | E8: =IF('2y forward'!E8="","",'2y forward'!E8/IF('2y forward'!$C8="GBp",100,1)/INDEX('FX 2y forward'!$C$2:$C$11,MATCH(IF('2y forward'!$C8="GBp","GBP",'2y forward'!$C8),'FX 2y forward'!$A$2:$A$11,0))) -> 13.837527 | F8: =IF('2y forward'!F8="","",'2y forward'!F8/IF('2y forward'!$C8="GBp",100,1)/INDEX('FX 2y forward'!$D$2:$D$11,MATCH(IF('2y forward'!$C8="GBp","GBP",'2y forward'!$C8),'FX 2y forward'!$A$2:$A$11,0))) -> 18.920345 | G8: =IF('2y forward'!G8="","",'2y forward'!G8/IF('2y forward'!$C8="GBp",100,1)/INDEX('FX 2y forward'!$E$2:$E$11,MATCH(IF('2y forward'!$C8="GBp","GBP",'2y forward'!$C8),'FX 2y forward'!$A$2:$A$11,0))) -> 22.226093 | H8: =IF('2y forward'!H8="","",'2y forward'!H8/IF('2y forward'!$C8="GBp",100,1)/INDEX('FX 2y forward'!$F$2:$F$11,MATCH(IF('2y forward'!$C8="GBp","GBP",'2y forward'!$C8),'FX 2y forward'!$A$2:$A$11,0))) -> 17.75972 | I8: =IF('2y forward'!I8="","",'2y forward'!I8/IF('2y forward'!$C8="GBp",100,1)/INDEX('FX 2y forward'!$G$2:$G$11,MATCH(IF('2y forward'!$C8="GBp","GBP",'2y forward'!$C8),'FX 2y forward'!$A$2:$A$11,0))) -> 17.40358 | J8: =IF('2y forward'!J8="","",'2y forward'!J8/IF('2y forward'!$C8="GBp",100,1)/INDEX('FX 2y forward'!$H$2:$H$11,MATCH(IF('2y forward'!$C8="GBp","GBP",'2y forward'!$C8),'FX 2y forward'!$A$2:$A$11,0))) -> 18.842883 | K8: =IF('2y forward'!K8="","",'2y forward'!K8/IF('2y forward'!$C8="GBp",100,1)/INDEX('FX 2y forward'!$I$2:$I$11,MATCH(IF('2y forward'!$C8="GBp","GBP",'2y forward'!$C8),'FX 2y forward'!$A$2:$A$11,0))) -> 16.023045 | L8: =IF('2y forward'!L8="","",'2y forward'!L8/IF('2y forward'!$C8="GBp",100,1)/INDEX('FX 2y forward'!$J$2:$J$11,MATCH(IF('2y forward'!$C8="GBp","GBP",'2y forward'!$C8),'FX 2y forward'!$A$2:$A$11,0))) -> 45.57684 | M8: =IF('2y forward'!M8="","",'2y forward'!M8/IF('2y forward'!$C8="GBp",100,1)/INDEX('FX 2y forward'!$K$2:$K$11,MATCH(IF('2y forward'!$C8="GBp","GBP",'2y forward'!$C8),'FX 2y forward'!$A$2:$A$11,0))) -> 44.34906
A9: BHP.AX | B9: BHP Group Ltd | C9: USD | D9: =IF('2y forward'!D9="","",'2y forward'!D9/IF('2y forward'!$C9="GBp",100,1)/INDEX('FX 2y forward'!$B$2:$B$11,MATCH(IF('2y forward'!$C9="GBp","GBP",'2y forward'!$C9),'FX 2y forward'!$A$2:$A$11,0))) -> 22.08171 | E9: =IF('2y forward'!E9="","",'2y forward'!E9/IF('2y forward'!$C9="GBp",100,1)/INDEX('FX 2y forward'!$C$2:$C$11,MATCH(IF('2y forward'!$C9="GBp","GBP",'2y forward'!$C9),'FX 2y forward'!$A$2:$A$11,0))) -> 22.876469 | F9: =IF('2y forward'!F9="","",'2y forward'!F9/IF('2y forward'!$C9="GBp",100,1)/INDEX('FX 2y forward'!$D$2:$D$11,MATCH(IF('2y forward'!$C9="GBp","GBP",'2y forward'!$C9),'FX 2y forward'!$A$2:$A$11,0))) -> 23.206086 | G9: =IF('2y forward'!G9="","",'2y forward'!G9/IF('2y forward'!$C9="GBp",100,1)/INDEX('FX 2y forward'!$E$2:$E$11,MATCH(IF('2y forward'!$C9="GBp","GBP",'2y forward'!$C9),'FX 2y forward'!$A$2:$A$11,0))) -> 29.818494 | H9: =IF('2y forward'!H9="","",'2y forward'!H9/IF('2y forward'!$C9="GBp",100,1)/INDEX('FX 2y forward'!$F$2:$F$11,MATCH(IF('2y forward'!$C9="GBp","GBP",'2y forward'!$C9),'FX 2y forward'!$A$2:$A$11,0))) -> 24.550742 | I9: =IF('2y forward'!I9="","",'2y forward'!I9/IF('2y forward'!$C9="GBp",100,1)/INDEX('FX 2y forward'!$G$2:$G$11,MATCH(IF('2y forward'!$C9="GBp","GBP",'2y forward'!$C9),'FX 2y forward'!$A$2:$A$11,0))) -> 27.534739 | J9: =IF('2y forward'!J9="","",'2y forward'!J9/IF('2y forward'!$C9="GBp",100,1)/INDEX('FX 2y forward'!$H$2:$H$11,MATCH(IF('2y forward'!$C9="GBp","GBP",'2y forward'!$C9),'FX 2y forward'!$A$2:$A$11,0))) -> 33.773199 | K9: =IF('2y forward'!K9="","",'2y forward'!K9/IF('2y forward'!$C9="GBp",100,1)/INDEX('FX 2y forward'!$I$2:$I$11,MATCH(IF('2y forward'!$C9="GBp","GBP",'2y forward'!$C9),'FX 2y forward'!$A$2:$A$11,0))) -> 23.950436 | L9: =IF('2y forward'!L9="","",'2y forward'!L9/IF('2y forward'!$C9="GBp",100,1)/INDEX('FX 2y forward'!$J$2:$J$11,MATCH(IF('2y forward'!$C9="GBp","GBP",'2y forward'!$C9),'FX 2y forward'!$A$2:$A$11,0))) -> 30.299354 | M9: =IF('2y forward'!M9="","",'2y forward'!M9/IF('2y forward'!$C9="GBp",100,1)/INDEX('FX 2y forward'!$K$2:$K$11,MATCH(IF('2y forward'!$C9="GBp","GBP",'2y forward'!$C9),'FX 2y forward'!$A$2:$A$11,0))) -> 42.160513
A10: EQX | B10: Equinox Gold Corp | C10: USD | D10: =IF('2y forward'!D10="","",'2y forward'!D10/IF('2y forward'!$C10="GBp",100,1)/INDEX('FX 2y forward'!$B$2:$B$11,MATCH(IF('2y forward'!$C10="GBp","GBP",'2y forward'!$C10),'FX 2y forward'!$A$2:$A$11,0))) | E10: =IF('2y forward'!E10="","",'2y forward'!E10/IF('2y forward'!$C10="GBp",100,1)/INDEX('FX 2y forward'!$C$2:$C$11,MATCH(IF('2y forward'!$C10="GBp","GBP",'2y forward'!$C10),'FX 2y forward'!$A$2:$A$11,0))) | F10: =IF('2y forward'!F10="","",'2y forward'!F10/IF('2y forward'!$C10="GBp",100,1)/INDEX('FX 2y forward'!$D$2:$D$11,MATCH(IF('2y forward'!$C10="GBp","GBP",'2y forward'!$C10),'FX 2y forward'!$A$2:$A$11,0))) -> 7.9472053 | G10: =IF('2y forward'!G10="","",'2y forward'!G10/IF('2y forward'!$C10="GBp",100,1)/INDEX('FX 2y forward'!$E$2:$E$11,MATCH(IF('2y forward'!$C10="GBp","GBP",'2y forward'!$C10),'FX 2y forward'!$A$2:$A$11,0))) -> 10.366919 | H10: =IF('2y forward'!H10="","",'2y forward'!H10/IF('2y forward'!$C10="GBp",100,1)/INDEX('FX 2y forward'!$F$2:$F$11,MATCH(IF('2y forward'!$C10="GBp","GBP",'2y forward'!$C10),'FX 2y forward'!$A$2:$A$11,0))) -> 6.85942 | I10: =IF('2y forward'!I10="","",'2y forward'!I10/IF('2y forward'!$C10="GBp",100,1)/INDEX('FX 2y forward'!$G$2:$G$11,MATCH(IF('2y forward'!$C10="GBp","GBP",'2y forward'!$C10),'FX 2y forward'!$A$2:$A$11,0))) -> 3.5838707 | J10: =IF('2y forward'!J10="","",'2y forward'!J10/IF('2y forward'!$C10="GBp",100,1)/INDEX('FX 2y forward'!$H$2:$H$11,MATCH(IF('2y forward'!$C10="GBp","GBP",'2y forward'!$C10),'FX 2y forward'!$A$2:$A$11,0))) -> 5.3238265 | K10: =IF('2y forward'!K10="","",'2y forward'!K10/IF('2y forward'!$C10="GBp",100,1)/INDEX('FX 2y forward'!$I$2:$I$11,MATCH(IF('2y forward'!$C10="GBp","GBP",'2y forward'!$C10),'FX 2y forward'!$A$2:$A$11,0))) -> 5.4642667 | L10: =IF('2y forward'!L10="","",'2y forward'!L10/IF('2y forward'!$C10="GBp",100,1)/INDEX('FX 2y forward'!$J$2:$J$11,MATCH(IF('2y forward'!$C10="GBp","GBP",'2y forward'!$C10),'FX 2y forward'!$A$2:$A$11,0))) -> 15.051993 | M10: =IF('2y forward'!M10="","",'2y forward'!M10/IF('2y forward'!$C10="GBp",100,1)/INDEX('FX 2y forward'!$K$2:$K$11,MATCH(IF('2y forward'!$C10="GBp","GBP",'2y forward'!$C10),'FX 2y forward'!$A$2:$A$11,0))) -> 12.687485
A11: EVN.AX | B11: Evolution Mining Ltd | C11: USD | D11: =IF('2y forward'!D11="","",'2y forward'!D11/IF('2y forward'!$C11="GBp",100,1)/INDEX('FX 2y forward'!$B$2:$B$11,MATCH(IF('2y forward'!$C11="GBp","GBP",'2y forward'!$C11),'FX 2y forward'!$A$2:$A$11,0))) -> 2.0656198 | E11: =IF('2y forward'!E11="","",'2y forward'!E11/IF('2y forward'!$C11="GBp",100,1)/INDEX('FX 2y forward'!$C$2:$C$11,MATCH(IF('2y forward'!$C11="GBp","GBP",'2y forward'!$C11),'FX 2y forward'!$A$2:$A$11,0))) -> 2.6234015 | F11: =IF('2y forward'!F11="","",'2y forward'!F11/IF('2y forward'!$C11="GBp",100,1)/INDEX('FX 2y forward'!$D$2:$D$11,MATCH(IF('2y forward'!$C11="GBp","GBP",'2y forward'!$C11),'FX 2y forward'!$A$2:$A$11,0))) -> 2.6120254 | G11: =IF('2y forward'!G11="","",'2y forward'!G11/IF('2y forward'!$C11="GBp",100,1)/INDEX('FX 2y forward'!$E$2:$E$11,MATCH(IF('2y forward'!$C11="GBp","GBP",'2y forward'!$C11),'FX 2y forward'!$A$2:$A$11,0))) -> 3.6079921 | H11: =IF('2y forward'!H11="","",'2y forward'!H11/IF('2y forward'!$C11="GBp",100,1)/INDEX('FX 2y forward'!$F$2:$F$11,MATCH(IF('2y forward'!$C11="GBp","GBP",'2y forward'!$C11),'FX 2y forward'!$A$2:$A$11,0))) -> 2.8152697 | I11: =IF('2y forward'!I11="","",'2y forward'!I11/IF('2y forward'!$C11="GBp",100,1)/INDEX('FX 2y forward'!$G$2:$G$11,MATCH(IF('2y forward'!$C11="GBp","GBP",'2y forward'!$C11),'FX 2y forward'!$A$2:$A$11,0))) -> 2.1161118 | J11: =IF('2y forward'!J11="","",'2y forward'!J11/IF('2y forward'!$C11="GBp",100,1)/INDEX('FX 2y forward'!$H$2:$H$11,MATCH(IF('2y forward'!$C11="GBp","GBP",'2y forward'!$C11),'FX 2y forward'!$A$2:$A$11,0))) -> 2.8841783 | K11: =IF('2y forward'!K11="","",'2y forward'!K11/IF('2y forward'!$C11="GBp",100,1)/INDEX('FX 2y forward'!$I$2:$I$11,MATCH(IF('2y forward'!$C11="GBp","GBP",'2y forward'!$C11),'FX 2y forward'!$A$2:$A$11,0))) -> 3.1631739 | L11: =IF('2y forward'!L11="","",'2y forward'!L11/IF('2y forward'!$C11="GBp",100,1)/INDEX('FX 2y forward'!$J$2:$J$11,MATCH(IF('2y forward'!$C11="GBp","GBP",'2y forward'!$C11),'FX 2y forward'!$A$2:$A$11,0))) -> 8.8224871 | M11: =IF('2y forward'!M11="","",'2y forward'!M11/IF('2y forward'!$C11="GBp",100,1)/INDEX('FX 2y forward'!$K$2:$K$11,MATCH(IF('2y forward'!$C11="GBp","GBP",'2y forward'!$C11),'FX 2y forward'!$A$2:$A$11,0))) -> 9.7102539
A12: FCX | B12: Freeport-McMoRan Inc | C12: USD | D12: =IF('2y forward'!D12="","",'2y forward'!D12/IF('2y forward'!$C12="GBp",100,1)/INDEX('FX 2y forward'!$B$2:$B$11,MATCH(IF('2y forward'!$C12="GBp","GBP",'2y forward'!$C12),'FX 2y forward'!$A$2:$A$11,0))) -> 19.690406 | E12: =IF('2y forward'!E12="","",'2y forward'!E12/IF('2y forward'!$C12="GBp",100,1)/INDEX('FX 2y forward'!$C$2:$C$11,MATCH(IF('2y forward'!$C12="GBp","GBP",'2y forward'!$C12),'FX 2y forward'!$A$2:$A$11,0))) -> 10.525662 | F12: =IF('2y forward'!F12="","",'2y forward'!F12/IF('2y forward'!$C12="GBp",100,1)/INDEX('FX 2y forward'!$D$2:$D$11,MATCH(IF('2y forward'!$C12="GBp","GBP",'2y forward'!$C12),'FX 2y forward'!$A$2:$A$11,0))) -> 13.134598 | G12: =IF('2y forward'!G12="","",'2y forward'!G12/IF('2y forward'!$C12="GBp",100,1)/INDEX('FX 2y forward'!$E$2:$E$11,MATCH(IF('2y forward'!$C12="GBp","GBP",'2y forward'!$C12),'FX 2y forward'!$A$2:$A$11,0))) -> 25.987651 | H12: =IF('2y forward'!H12="","",'2y forward'!H12/IF('2y forward'!$C12="GBp",100,1)/INDEX('FX 2y forward'!$F$2:$F$11,MATCH(IF('2y forward'!$C12="GBp","GBP",'2y forward'!$C12),'FX 2y forward'!$A$2:$A$11,0))) -> 41.889546 | I12: =IF('2y forward'!I12="","",'2y forward'!I12/IF('2y forward'!$C12="GBp",100,1)/INDEX('FX 2y forward'!$G$2:$G$11,MATCH(IF('2y forward'!$C12="GBp","GBP",'2y forward'!$C12),'FX 2y forward'!$A$2:$A$11,0))) -> 40.229806 | J12: =IF('2y forward'!J12="","",'2y forward'!J12/IF('2y forward'!$C12="GBp",100,1)/INDEX('FX 2y forward'!$H$2:$H$11,MATCH(IF('2y forward'!$C12="GBp","GBP",'2y forward'!$C12),'FX 2y forward'!$A$2:$A$11,0))) -> 45.058506 | K12: =IF('2y forward'!K12="","",'2y forward'!K12/IF('2y forward'!$C12="GBp",100,1)/INDEX('FX 2y forward'!$I$2:$I$11,MATCH(IF('2y forward'!$C12="GBp","GBP",'2y forward'!$C12),'FX 2y forward'!$A$2:$A$11,0))) -> 40.164247 | L12: =IF('2y forward'!L12="","",'2y forward'!L12/IF('2y forward'!$C12="GBp",100,1)/INDEX('FX 2y forward'!$J$2:$J$11,MATCH(IF('2y forward'!$C12="GBp","GBP",'2y forward'!$C12),'FX 2y forward'!$A$2:$A$11,0))) -> 53.179527 | M12: =IF('2y forward'!M12="","",'2y forward'!M12/IF('2y forward'!$C12="GBp",100,1)/INDEX('FX 2y forward'!$K$2:$K$11,MATCH(IF('2y forward'!$C12="GBp","GBP",'2y forward'!$C12),'FX 2y forward'!$A$2:$A$11,0))) -> 76.563191
A13: FMG.AX | B13: Fortescue Ltd | C13: USD | D13: =IF('2y forward'!D13="","",'2y forward'!D13/IF('2y forward'!$C13="GBp",100,1)/INDEX('FX 2y forward'!$B$2:$B$11,MATCH(IF('2y forward'!$C13="GBp","GBP",'2y forward'!$C13),'FX 2y forward'!$A$2:$A$11,0))) -> 3.2848662 | E13: =IF('2y forward'!E13="","",'2y forward'!E13/IF('2y forward'!$C13="GBp",100,1)/INDEX('FX 2y forward'!$C$2:$C$11,MATCH(IF('2y forward'!$C13="GBp","GBP",'2y forward'!$C13),'FX 2y forward'!$A$2:$A$11,0))) -> 2.7798863 | F13: =IF('2y forward'!F13="","",'2y forward'!F13/IF('2y forward'!$C13="GBp",100,1)/INDEX('FX 2y forward'!$D$2:$D$11,MATCH(IF('2y forward'!$C13="GBp","GBP",'2y forward'!$C13),'FX 2y forward'!$A$2:$A$11,0))) -> 6.2410573 | G13: =IF('2y forward'!G13="","",'2y forward'!G13/IF('2y forward'!$C13="GBp",100,1)/INDEX('FX 2y forward'!$E$2:$E$11,MATCH(IF('2y forward'!$C13="GBp","GBP",'2y forward'!$C13),'FX 2y forward'!$A$2:$A$11,0))) -> 15.543255 | H13: =IF('2y forward'!H13="","",'2y forward'!H13/IF('2y forward'!$C13="GBp",100,1)/INDEX('FX 2y forward'!$F$2:$F$11,MATCH(IF('2y forward'!$C13="GBp","GBP",'2y forward'!$C13),'FX 2y forward'!$A$2:$A$11,0))) -> 9.734712 | I13: =IF('2y forward'!I13="","",'2y forward'!I13/IF('2y forward'!$C13="GBp",100,1)/INDEX('FX 2y forward'!$G$2:$G$11,MATCH(IF('2y forward'!$C13="GBp","GBP",'2y forward'!$C13),'FX 2y forward'!$A$2:$A$11,0))) -> 12.391189 | J13: =IF('2y forward'!J13="","",'2y forward'!J13/IF('2y forward'!$C13="GBp",100,1)/INDEX('FX 2y forward'!$H$2:$H$11,MATCH(IF('2y forward'!$C13="GBp","GBP",'2y forward'!$C13),'FX 2y forward'!$A$2:$A$11,0))) -> 19.116986 | K13: =IF('2y forward'!K13="","",'2y forward'!K13/IF('2y forward'!$C13="GBp",100,1)/INDEX('FX 2y forward'!$I$2:$I$11,MATCH(IF('2y forward'!$C13="GBp","GBP",'2y forward'!$C13),'FX 2y forward'!$A$2:$A$11,0))) -> 9.9568417 | L13: =IF('2y forward'!L13="","",'2y forward'!L13/IF('2y forward'!$C13="GBp",100,1)/INDEX('FX 2y forward'!$J$2:$J$11,MATCH(IF('2y forward'!$C13="GBp","GBP",'2y forward'!$C13),'FX 2y forward'!$A$2:$A$11,0))) -> 14.301533 | M13: =IF('2y forward'!M13="","",'2y forward'!M13/IF('2y forward'!$C13="GBp",100,1)/INDEX('FX 2y forward'!$K$2:$K$11,MATCH(IF('2y forward'!$C13="GBp","GBP",'2y forward'!$C13),'FX 2y forward'!$A$2:$A$11,0))) -> 10.787298
... A26: VALE3.SA | B26: Vale SA | C26: USD | D26: =IF('2y forward'!D26="","",'2y forward'!D26/IF('2y forward'!$C26="GBp",100,1)/INDEX('FX 2y forward'!$B$2:$B$11,MATCH(IF('2y forward'!$C26="GBp","GBP",'2y forward'!$C26),'FX 2y forward'!$A$2:$A$11,0))) -> 11.822825 | E26: =IF('2y forward'!E26="","",'2y forward'!E26/IF('2y forward'!$C26="GBp",100,1)/INDEX('FX 2y forward'!$C$2:$C$11,MATCH(IF('2y forward'!$C26="GBp","GBP",'2y forward'!$C26),'FX 2y forward'!$A$2:$A$11,0))) -> 12.808083 | F26: =IF('2y forward'!F26="","",'2y forward'!F26/IF('2y forward'!$C26="GBp",100,1)/INDEX('FX 2y forward'!$D$2:$D$11,MATCH(IF('2y forward'!$C26="GBp","GBP",'2y forward'!$C26),'FX 2y forward'!$A$2:$A$11,0))) -> 12.99091 | G26: =IF('2y forward'!G26="","",'2y forward'!G26/IF('2y forward'!$C26="GBp",100,1)/INDEX('FX 2y forward'!$E$2:$E$11,MATCH(IF('2y forward'!$C26="GBp","GBP",'2y forward'!$C26),'FX 2y forward'!$A$2:$A$11,0))) -> 15.985976 | H26: =IF('2y forward'!H26="","",'2y forward'!H26/IF('2y forward'!$C26="GBp",100,1)/INDEX('FX 2y forward'!$F$2:$F$11,MATCH(IF('2y forward'!$C26="GBp","GBP",'2y forward'!$C26),'FX 2y forward'!$A$2:$A$11,0))) -> 9.7529413 | I26: =IF('2y forward'!I26="","",'2y forward'!I26/IF('2y forward'!$C26="GBp",100,1)/INDEX('FX 2y forward'!$G$2:$G$11,MATCH(IF('2y forward'!$C26="GBp","GBP",'2y forward'!$C26),'FX 2y forward'!$A$2:$A$11,0))) -> 15.493928 | J26: =IF('2y forward'!J26="","",'2y forward'!J26/IF('2y forward'!$C26="GBp",100,1)/INDEX('FX 2y forward'!$H$2:$H$11,MATCH(IF('2y forward'!$C26="GBp","GBP",'2y forward'!$C26),'FX 2y forward'!$A$2:$A$11,0))) -> 14.804386 | K26: =IF('2y forward'!K26="","",'2y forward'!K26/IF('2y forward'!$C26="GBp",100,1)/INDEX('FX 2y forward'!$I$2:$I$11,MATCH(IF('2y forward'!$C26="GBp","GBP",'2y forward'!$C26),'FX 2y forward'!$A$2:$A$11,0))) -> 7.8985824 | L26: =IF('2y forward'!L26="","",'2y forward'!L26/IF('2y forward'!$C26="GBp",100,1)/INDEX('FX 2y forward'!$J$2:$J$11,MATCH(IF('2y forward'!$C26="GBp","GBP",'2y forward'!$C26),'FX 2y forward'!$A$2:$A$11,0))) -> 11.399198 | M26: =IF('2y forward'!M26="","",'2y forward'!M26/IF('2y forward'!$C26="GBp",100,1)/INDEX('FX 2y forward'!$K$2:$K$11,MATCH(IF('2y forward'!$C26="GBp","GBP",'2y forward'!$C26),'FX 2y forward'!$A$2:$A$11,0))) -> 13.818795
A28: 2y forward (local) / 2-year FX forward from the 'FX 2y forward' tab.

Sheet Dividend yield
A1: ticker | B1: company | C1: currency | D1: 2017 | E1: 2018 | F1: 2019 | G1: 2020 | H1: 2021 | I1: 2022 | J1: 2023 | K1: 2024 | L1: 2025 | M1: 2026
A2: 000408.SZ | B2: Zangge Mining Co Ltd | C2: CNY | D2: 0.016949 | E2: 0 | F2: 0 | G2: 0 | H2: 0 | I2: 0.073084 | J2: 0.069455 | K2: 0.038226 | L2: 0.011848 | M2: 0.034985
A3: 1208.HK | B3: MMG Ltd | C3: HKD | D3: 0 | E3: 0 | F3: 0 | G3: 0 | H3: 0 | I3: 0 | J3: 0 | K3: 0 | L3: 0 | M3: 0
A4: 1211.SR | B4: Saudi Arabian Mining Co (Maaden) | C4: SAR | D4: 0 | E4: 0 | F4: 0 | G4: 0 | H4: 0 | I4: 0 | J4: 0 | K4: 0 | L4: 0 | M4: 0
A5: 2899.HK | B5: Zijin Mining Group Co Ltd | C5: HKD | D5: 0.02328 | E5: 0.037416 | F5: 0.029334 | G5: 0.012487 | H5: 0.015631 | I5: 0.021985 | J5: 0.02183 | K5: 0.023264 | L5: 0.015264 | M5: 0.028329
A6: AAL.L | B6: Anglo American plc | C6: GBp | D6: 0.027722 | E6: 0.050933 | F6: 0.048363 | G6: 0.028408 | H6: 0.089633 | I6: 0.084496 | J6: 0.06052 | K6: 0.031762 | L6: 0.007785 | M6: 0.007127
A7: AEM | B7: Agnico Eagle Mines Ltd | C7: USD | D7: 0.008878 | E7: 0.010891 | F7: 0.008927 | G7: 0.013473 | H7: 0.026346 | I7: 0.030775 | J7: 0.02917 | K7: 0.020458 | L7: 0.009438 | M7: 0.006942
A8: B | B8: Barrick Mining Corp | C8: USD | D8: 0.008293 | E8: 0.014032 | F8: 0.006993 | G8: 0.013608 | H8: 0.041053 | I8: 0.037835 | J8: 0.022112 | K8: 0.025806 | L8: 0.012055 | M8: 0.017957
A9: BHP.AX | B9: BHP Group Ltd | C9: AUD | D9: 0.040307 | E9: 0.051243 | F9: 0.096108 | G9: 0.046284 | H9: 0.108969 | I9: 0.101521 | J9: 0.05186 | K9: 0.055782 | L9: 0.037595 | M9: 0.039828
A10: EQX | B10: Equinox Gold Corp | C10: USD | F10: 0 | G10: 0 | H10: 0 | I10: 0 | J10: 0 | K10: 0 | L10: 0 | M10: 0.004439
A11: EVN.AX | B11: Evolution Mining Ltd | C11: AUD | D11: 0.018868 | E11: 0.020325 | F11: 0.025 | G11: 0.032064 | H11: 0.029557 | I11: 0.020134 | J11: 0.010101 | K11: 0.014553 | L11: 0.015773 | M11: 0.029905
A12: FCX | B12: Freeport-McMoRan Inc | C12: USD | D12: 0 | E12: 0.014549 | F12: 0.015244 | G12: 0.001922 | H12: 0.005392 | I12: 0.015789 | J12: 0.014094 | K12: 0.015756 | L12: 0.011813 | M12: 0.006223
A13: FMG.AX | B13: Fortescue Ltd | C13: AUD | D13: 0.092213 | E13: 0.054893 | F13: 0.106642 | G13: 0.075117 | H13: 0.186361 | I13: 0.100926 | J13: 0.060303 | K13: 0.107945 | L13: 0.049977 | M13: 0.065974
A14: FRES.L | B14: Fresnillo plc | C14: GBp | D14: 0.017357 | E14: 0.03489 | F14: 0.023545 | G14: 0.010042 | H14: 0.02659 | I14: 0.024388 | J14: 0.019821 | K14: 0.013535 | L14: 0.01995 | M14: 0.038675
A15: GLEN.L | B15: Glencore plc | C15: GBp | D15: 0.013563 | E15: 0.051595 | F15: 0.066526 | G15: 0 | H15: 0.031628 | I15: 0.056734 | J15: 0.088297 | K15: 0.028677 | L15: 0.0184 | M15: 0.022393
A16: GMEXICOB.MX | B16: Grupo Mexico SAB de CV | C16: MXN | D16: 0.019412 | E16: 0.066766 | F16: 0.046252 | G16: 0.035663 | H16: 0.069997 | I16: 0.07278 | J16: 0.040263 | K16: 0.043312 | L16: 0.029965 | M16: 0.017553
A17: INCO.JK | B17: PT Vale Indonesia Tbk | C17: IDR | D17: 0 | E17: 0 | F17: 0 | G17: 0 | H17: 0.009964 | I17: 0 | J17: 0.020495 | K17: 0 | L17: 0.010319 | M17: 0.016645
A18: LUN.TO | B18: Lundin Mining Corp | C18: CAD | D18: 0.014354 | E18: 0.021277 | F18: 0.015464 | G18: 0.014159 | H18: 0.039474 | I18: 0.056558 | J18: 0.03321 | K18: 0.036378 | L18: 0.005898 | M18: 0.002401
A19: MIN.AX | B19: Mineral Resources Ltd | C19: AUD | D19: 0.025544 | E19: 0.042017 | F19: 0.026667 | G19: 0.026702 | H19: 0.049107 | I19: 0.012953 | J19: 0.027143 | K19: 0.005839 | L19: 0 | M19: 0.015837
A20: MT | B20: ArcelorMittal SA | C20: USD | D20: 0 | E20: 0.004838 | F20: 0.011403 | G20: 0 | H20: 0.009425 | I20: 0.014493 | J20: 0.015498 | K20: 0.021617 | L20: 0.012069 | M20: 0.006365
A21: NEM | B21: Newmont Corp | C21: USD | D21: 0.006663 | E21: 0.016162 | F21: 0.033142 | G21: 0.017365 | H21: 0.035472 | I21: 0.04661 | J21: 0.038657 | K21: 0.026867 | L21: 0.010015 | M21: 0.006423
A22: NEXA | B22: Nexa Resources SA | C22: USD | D22: 0 | E22: 0.05042 | F22: 0.064496 | G22: 0.039212 | H22: 0.033588 | I22: 0.062687 | J22: 0.026471 | K22: 0 | L22: 0.011412 | M22: 0.010611
... A26: VALE3.SA | B26: Vale SA | C26: BRL | D26: 0.032923 | E26: 0.038605 | F26: 0.026536 | G26: 0.02753 | H26: 0.187898 | I26: 0.085321 | J26: 0.078728 | K26: 0.098128 | L26: 0.105878 | M26: 0.028695
A28: Dividends paid during the year / year-end close.

Sheet Rates 2y
A1: currency | B1: 2017 | C1: 2018 | D1: 2019 | E1: 2020 | F1: 2021 | G1: 2022 | H1: 2023 | I1: 2024 | J1: 2025 | K1: 2026
A2: USD | B2: 0.0189 | C2: 0.0249 | D2: 0.0158 | E2: 0.0013 | F2: 0.0073 | G2: 0.0443 | H2: 0.0425 | I2: 0.0424 | J2: 0.0348 | K2: 0.0348
A3: CAD | B3: 0.0169 | C3: 0.0186 | D3: 0.017 | E3: 0.002 | F3: 0.0095 | G3: 0.0405 | H3: 0.0388 | I3: 0.0293 | J3: 0.026 | K3: 0.026
A4: AUD | B4: 0.02 | C4: 0.019 | D4: 0.009 | E4: 0.001 | F4: 0.006 | G4: 0.035 | H4: 0.037 | I4: 0.0385 | J4: 0.039 | K4: 0.039
A5: GBP | B5: 0.0045 | C5: 0.0075 | D5: 0.0055 | E5: -0.0015 | F5: 0.007 | G5: 0.036 | H5: 0.04 | I5: 0.044 | J5: 0.0375 | K5: 0.0375
A6: MXN | B6: 0.076 | C6: 0.086 | D6: 0.069 | E6: 0.043 | F6: 0.072 | G6: 0.105 | H6: 0.103 | I6: 0.099 | J6: 0.073 | K6: 0.073
A7: BRL | B7: 0.075 | C7: 0.072 | D7: 0.053 | E7: 0.043 | F7: 0.113 | G7: 0.134 | H7: 0.103 | I7: 0.154 | J7: 0.139 | K7: 0.139
A8: SAR | B8: 0.02 | C8: 0.029 | D8: 0.023 | E8: 0.009 | F8: 0.012 | G8: 0.05 | H8: 0.054 | I8: 0.052 | J8: 0.046 | K8: 0.046
A9: HKD | B9: 0.013 | C9: 0.018 | D9: 0.017 | E9: 0.002 | F9: 0.006 | G9: 0.04 | H9: 0.036 | I9: 0.034 | J9: 0.026 | K9: 0.026
A10: CNY | B10: 0.035 | C10: 0.027 | D10: 0.026 | E10: 0.027 | F10: 0.023 | G10: 0.023 | H10: 0.022 | I10: 0.011 | J10: 0.014 | K10: 0.014
A11: IDR | B11: 0.058 | C11: 0.077 | D11: 0.057 | E11: 0.041 | F11: 0.039 | G11: 0.059 | H11: 0.064 | I11: 0.069 | J11: 0.05 | K11: 0.05
A13: Approximate year-end 2-year government bond yields (SAR: interbank proxy). Entered from memory, not from a data source: replace with exact figures if needed. 2026 repeats 2025.

Sheet FX year-end
A1: currency | B1: 2017 | C1: 2018 | D1: 2019 | E1: 2020 | F1: 2021 | G1: 2022 | H1: 2023 | I1: 2024 | J1: 2025 | K1: 2026
A2: USD | B2: 1 | C2: 1 | D2: 1 | E2: 1 | F2: 1 | G2: 1 | H2: 1 | I2: 1 | J2: 1 | K2: 1
A3: CAD | B3: 1.25655 | C3: 1.3622 | D3: 1.30606 | E3: 1.27507 | F3: 1.27444 | G3: 1.3552 | H3: 1.32296 | I3: 1.43498 | J3: 1.36947 | K3: 1.413
A4: AUD | B4: 1.28299 | C4: 1.4195 | D4: 1.428286 | E4: 1.30051 | F4: 1.379348 | G4: 1.477978 | H4: 1.464922 | I4: 1.607717 | J4: 1.492983 | K4: 1.4258
A5: GBP | B5: 0.744 | C5: 0.7878 | D5: 0.7626 | E5: 0.73364 | F5: 0.74083 | G5: 0.82944 | H5: 0.7853 | I5: 0.79687 | J5: 0.742545 | K5: 0.75566
A6: MXN | B6: 19.65539 | C6: 19.64537 | D6: 18.9177 | E6: 19.8909 | F6: 20.459101 | G6: 19.4576 | H6: 16.9512 | I6: 20.6322 | J6: 17.9788 | K6: 17.7325
A7: BRL | B7: 3.3111 | C7: 3.8742 | D7: 4.015711 | E7: 5.190839 | F7: 5.5702 | G7: 5.2846 | H7: 4.8502 | I7: 6.1779 | J7: 5.4762 | K7: 5.1842
A8: SAR | B8: 3.7456 | C8: 3.7515 | D8: 3.74836 | E8: 3.747706 | F8: 3.749972 | G8: 3.754942 | H8: 3.745219 | I8: 3.751983 | J8: 3.7479 | K8: 3.7543
A9: HKD | B9: 7.8168 | C9: 7.8309 | D9: 7.7881 | E9: 7.75218 | F9: 7.79756 | G9: 7.7944 | H9: 7.8118 | I9: 7.7635 | J9: 7.78066 | K9: 7.8434
A10: CNY | B10: 6.5316 | C10: 6.8772 | D10: 6.9857 | E10: 6.5222 | F10: 6.3721 | G10: 6.9631 | H10: 7.107 | I10: 7.2981 | J10: 6.9961 | K10: 6.7123
A11: IDR | B11: 13558 | C11: 14553 | D11: 13919 | E11: 13832.56 | F11: 14285.2 | G11: 15620 | H11: 15425 | I11: 16085.6 | J11: 16709 | K11: 17912
A13: Units of currency per 1 USD at the last trading day of each year (2026: latest). Source: Yahoo Finance (CAD=X, GBP=X, ...).

Sheet FX 2y forward
A1: currency | B1: 2017->2019 | C1: 2018->2020 | D1: 2019->2021 | E1: 2020->2022 | F1: 2021->2023 | G1: 2022->2024 | H1: 2023->2025 | I1: 2024->2026 | J1: 2025->2027 | K1: 2026->2028
A2: USD | B2: ='FX year-end'!B2*EXP((INDEX('Rates 2y'!$B$2:$B$11,MATCH($A2,'Rates 2y'!$A$2:$A$11,0))-INDEX('Rates 2y'!$B$2:$B$11,MATCH("USD",'Rates 2y'!$A$2:$A$11,0)))*2) -> 1 | C2: ='FX year-end'!C2*EXP((INDEX('Rates 2y'!$C$2:$C$11,MATCH($A2,'Rates 2y'!$A$2:$A$11,0))-INDEX('Rates 2y'!$C$2:$C$11,MATCH("USD",'Rates 2y'!$A$2:$A$11,0)))*2) -> 1 | D2: ='FX year-end'!D2*EXP((INDEX('Rates 2y'!$D$2:$D$11,MATCH($A2,'Rates 2y'!$A$2:$A$11,0))-INDEX('Rates 2y'!$D$2:$D$11,MATCH("USD",'Rates 2y'!$A$2:$A$11,0)))*2) -> 1 | E2: ='FX year-end'!E2*EXP((INDEX('Rates 2y'!$E$2:$E$11,MATCH($A2,'Rates 2y'!$A$2:$A$11,0))-INDEX('Rates 2y'!$E$2:$E$11,MATCH("USD",'Rates 2y'!$A$2:$A$11,0)))*2) -> 1 | F2: ='FX year-end'!F2*EXP((INDEX('Rates 2y'!$F$2:$F$11,MATCH($A2,'Rates 2y'!$A$2:$A$11,0))-INDEX('Rates 2y'!$F$2:$F$11,MATCH("USD",'Rates 2y'!$A$2:$A$11,0)))*2) -> 1 | G2: ='FX year-end'!G2*EXP((INDEX('Rates 2y'!$G$2:$G$11,MATCH($A2,'Rates 2y'!$A$2:$A$11,0))-INDEX('Rates 2y'!$G$2:$G$11,MATCH("USD",'Rates 2y'!$A$2:$A$11,0)))*2) -> 1 | H2: ='FX year-end'!H2*EXP((INDEX('Rates 2y'!$H$2:$H$11,MATCH($A2,'Rates 2y'!$A$2:$A$11,0))-INDEX('Rates 2y'!$H$2:$H$11,MATCH("USD",'Rates 2y'!$A$2:$A$11,0)))*2) -> 1 | I2: ='FX year-end'!I2*EXP((INDEX('Rates 2y'!$I$2:$I$11,MATCH($A2,'Rates 2y'!$A$2:$A$11,0))-INDEX('Rates 2y'!$I$2:$I$11,MATCH("USD",'Rates 2y'!$A$2:$A$11,0)))*2) -> 1 | J2: ='FX year-end'!J2*EXP((INDEX('Rates 2y'!$J$2:$J$11,MATCH($A2,'Rates 2y'!$A$2:$A$11,0))-INDEX('Rates 2y'!$J$2:$J$11,MATCH("USD",'Rates 2y'!$A$2:$A$11,0)))*2) -> 1 | K2: ='FX year-end'!K2*EXP((INDEX('Rates 2y'!$K$2:$K$11,MATCH($A2,'Rates 2y'!$A$2:$A$11,0))-INDEX('Rates 2y'!$K$2:$K$11,MATCH("USD",'Rates 2y'!$A$2:$A$11,0)))*2) -> 1
A3: CAD | B3: ='FX year-end'!B3*EXP((INDEX('Rates 2y'!$B$2:$B$11,MATCH($A3,'Rates 2y'!$A$2:$A$11,0))-INDEX('Rates 2y'!$B$2:$B$11,MATCH("USD",'Rates 2y'!$A$2:$A$11,0)))*2) -> 1.2515338 | C3: ='FX year-end'!C3*EXP((INDEX('Rates 2y'!$C$2:$C$11,MATCH($A3,'Rates 2y'!$A$2:$A$11,0))-INDEX('Rates 2y'!$C$2:$C$11,MATCH("USD",'Rates 2y'!$A$2:$A$11,0)))*2) -> 1.345144 | D3: ='FX year-end'!D3*EXP((INDEX('Rates 2y'!$D$2:$D$11,MATCH($A3,'Rates 2y'!$A$2:$A$11,0))-INDEX('Rates 2y'!$D$2:$D$11,MATCH("USD",'Rates 2y'!$A$2:$A$11,0)))*2) -> 1.3091983 | E3: ='FX year-end'!E3*EXP((INDEX('Rates 2y'!$E$2:$E$11,MATCH($A3,'Rates 2y'!$A$2:$A$11,0))-INDEX('Rates 2y'!$E$2:$E$11,MATCH("USD",'Rates 2y'!$A$2:$A$11,0)))*2) -> 1.2768563 | F3: ='FX year-end'!F3*EXP((INDEX('Rates 2y'!$F$2:$F$11,MATCH($A3,'Rates 2y'!$A$2:$A$11,0))-INDEX('Rates 2y'!$F$2:$F$11,MATCH("USD",'Rates 2y'!$A$2:$A$11,0)))*2) -> 1.2800599 | G3: ='FX year-end'!G3*EXP((INDEX('Rates 2y'!$G$2:$G$11,MATCH($A3,'Rates 2y'!$A$2:$A$11,0))-INDEX('Rates 2y'!$G$2:$G$11,MATCH("USD",'Rates 2y'!$A$2:$A$11,0)))*2) -> 1.3449395 | H3: ='FX year-end'!H3*EXP((INDEX('Rates 2y'!$H$2:$H$11,MATCH($A3,'Rates 2y'!$A$2:$A$11,0))-INDEX('Rates 2y'!$H$2:$H$11,MATCH("USD",'Rates 2y'!$A$2:$A$11,0)))*2) -> 1.3132062 | I3: ='FX year-end'!I3*EXP((INDEX('Rates 2y'!$I$2:$I$11,MATCH($A3,'Rates 2y'!$A$2:$A$11,0))-INDEX('Rates 2y'!$I$2:$I$11,MATCH("USD",'Rates 2y'!$A$2:$A$11,0)))*2) -> 1.3978718 | J3: ='FX year-end'!J3*EXP((INDEX('Rates 2y'!$J$2:$J$11,MATCH($A3,'Rates 2y'!$A$2:$A$11,0))-INDEX('Rates 2y'!$J$2:$J$11,MATCH("USD",'Rates 2y'!$A$2:$A$11,0)))*2) -> 1.3455782 | K3: ='FX year-end'!K3*EXP((INDEX('Rates 2y'!$K$2:$K$11,MATCH($A3,'Rates 2y'!$A$2:$A$11,0))-INDEX('Rates 2y'!$K$2:$K$11,MATCH("USD",'Rates 2y'!$A$2:$A$11,0)))*2) -> 1.3883488
A4: AUD | B4: ='FX year-end'!B4*EXP((INDEX('Rates 2y'!$B$2:$B$11,MATCH($A4,'Rates 2y'!$A$2:$A$11,0))-INDEX('Rates 2y'!$B$2:$B$11,MATCH("USD",'Rates 2y'!$A$2:$A$11,0)))*2) -> 1.2858157 | C4: ='FX year-end'!C4*EXP((INDEX('Rates 2y'!$C$2:$C$11,MATCH($A4,'Rates 2y'!$A$2:$A$11,0))-INDEX('Rates 2y'!$C$2:$C$11,MATCH("USD",'Rates 2y'!$A$2:$A$11,0)))*2) -> 1.4028483 | D4: ='FX year-end'!D4*EXP((INDEX('Rates 2y'!$D$2:$D$11,MATCH($A4,'Rates 2y'!$A$2:$A$11,0))-INDEX('Rates 2y'!$D$2:$D$11,MATCH("USD",'Rates 2y'!$A$2:$A$11,0)))*2) -> 1.4089928 | E4: ='FX year-end'!E4*EXP((INDEX('Rates 2y'!$E$2:$E$11,MATCH($A4,'Rates 2y'!$A$2:$A$11,0))-INDEX('Rates 2y'!$E$2:$E$11,MATCH("USD",'Rates 2y'!$A$2:$A$11,0)))*2) -> 1.2997299 | F4: ='FX year-end'!F4*EXP((INDEX('Rates 2y'!$F$2:$F$11,MATCH($A4,'Rates 2y'!$A$2:$A$11,0))-INDEX('Rates 2y'!$F$2:$F$11,MATCH("USD",'Rates 2y'!$A$2:$A$11,0)))*2) -> 1.3757664 | G4: ='FX year-end'!G4*EXP((INDEX('Rates 2y'!$G$2:$G$11,MATCH($A4,'Rates 2y'!$A$2:$A$11,0))-INDEX('Rates 2y'!$G$2:$G$11,MATCH("USD",'Rates 2y'!$A$2:$A$11,0)))*2) -> 1.4507417 | H4: ='FX year-end'!H4*EXP((INDEX('Rates 2y'!$H$2:$H$11,MATCH($A4,'Rates 2y'!$A$2:$A$11,0))-INDEX('Rates 2y'!$H$2:$H$11,MATCH("USD",'Rates 2y'!$A$2:$A$11,0)))*2) -> 1.4488962 | I4: ='FX year-end'!I4*EXP((INDEX('Rates 2y'!$I$2:$I$11,MATCH($A4,'Rates 2y'!$A$2:$A$11,0))-INDEX('Rates 2y'!$I$2:$I$11,MATCH("USD",'Rates 2y'!$A$2:$A$11,0)))*2) -> 1.5952256 | J4: ='FX year-end'!J4*EXP((INDEX('Rates 2y'!$J$2:$J$11,MATCH($A4,'Rates 2y'!$A$2:$A$11,0))-INDEX('Rates 2y'!$J$2:$J$11,MATCH("USD",'Rates 2y'!$A$2:$A$11,0)))*2) -> 1.5055769 | K4: ='FX year-end'!K4*EXP((INDEX('Rates 2y'!$K$2:$K$11,MATCH($A4,'Rates 2y'!$A$2:$A$11,0))-INDEX('Rates 2y'!$K$2:$K$11,MATCH("USD",'Rates 2y'!$A$2:$A$11,0)))*2) -> 1.4378272
A5: GBP | B5: ='FX year-end'!B5*EXP((INDEX('Rates 2y'!$B$2:$B$11,MATCH($A5,'Rates 2y'!$A$2:$A$11,0))-INDEX('Rates 2y'!$B$2:$B$11,MATCH("USD",'Rates 2y'!$A$2:$A$11,0)))*2) -> 0.72287841 | C5: ='FX year-end'!C5*EXP((INDEX('Rates 2y'!$C$2:$C$11,MATCH($A5,'Rates 2y'!$A$2:$A$11,0))-INDEX('Rates 2y'!$C$2:$C$11,MATCH("USD",'Rates 2y'!$A$2:$A$11,0)))*2) -> 0.7608561 | D5: ='FX year-end'!D5*EXP((INDEX('Rates 2y'!$D$2:$D$11,MATCH($A5,'Rates 2y'!$A$2:$A$11,0))-INDEX('Rates 2y'!$D$2:$D$11,MATCH("USD",'Rates 2y'!$A$2:$A$11,0)))*2) -> 0.74705114 | E5: ='FX year-end'!E5*EXP((INDEX('Rates 2y'!$E$2:$E$11,MATCH($A5,'Rates 2y'!$A$2:$A$11,0))-INDEX('Rates 2y'!$E$2:$E$11,MATCH("USD",'Rates 2y'!$A$2:$A$11,0)))*2) -> 0.7295431 | F5: ='FX year-end'!F5*EXP((INDEX('Rates 2y'!$F$2:$F$11,MATCH($A5,'Rates 2y'!$A$2:$A$11,0))-INDEX('Rates 2y'!$F$2:$F$11,MATCH("USD",'Rates 2y'!$A$2:$A$11,0)))*2) -> 0.74038564 | G5: ='FX year-end'!G5*EXP((INDEX('Rates 2y'!$G$2:$G$11,MATCH($A5,'Rates 2y'!$A$2:$A$11,0))-INDEX('Rates 2y'!$G$2:$G$11,MATCH("USD",'Rates 2y'!$A$2:$A$11,0)))*2) -> 0.81578495 | H5: ='FX year-end'!H5*EXP((INDEX('Rates 2y'!$H$2:$H$11,MATCH($A5,'Rates 2y'!$A$2:$A$11,0))-INDEX('Rates 2y'!$H$2:$H$11,MATCH("USD",'Rates 2y'!$A$2:$A$11,0)))*2) -> 0.7813833 | I5: ='FX year-end'!I5*EXP((INDEX('Rates 2y'!$I$2:$I$11,MATCH($A5,'Rates 2y'!$A$2:$A$11,0))-INDEX('Rates 2y'!$I$2:$I$11,MATCH("USD",'Rates 2y'!$A$2:$A$11,0)))*2) -> 0.79942407 | J5: ='FX year-end'!J5*EXP((INDEX('Rates 2y'!$J$2:$J$11,MATCH($A5,'Rates 2y'!$A$2:$A$11,0))-INDEX('Rates 2y'!$J$2:$J$11,MATCH("USD",'Rates 2y'!$A$2:$A$11,0)))*2) -> 0.74656559 | K5: ='FX year-end'!K5*EXP((INDEX('Rates 2y'!$K$2:$K$11,MATCH($A5,'Rates 2y'!$A$2:$A$11,0))-INDEX('Rates 2y'!$K$2:$K$11,MATCH("USD",'Rates 2y'!$A$2:$A$11,0)))*2) -> 0.7597516
A6: MXN | B6: ='FX year-end'!B6*EXP((INDEX('Rates 2y'!$B$2:$B$11,MATCH($A6,'Rates 2y'!$A$2:$A$11,0))-INDEX('Rates 2y'!$B$2:$B$11,MATCH("USD",'Rates 2y'!$A$2:$A$11,0)))*2) -> 22.033226 | C6: ='FX year-end'!C6*EXP((INDEX('Rates 2y'!$C$2:$C$11,MATCH($A6,'Rates 2y'!$A$2:$A$11,0))-INDEX('Rates 2y'!$C$2:$C$11,MATCH("USD",'Rates 2y'!$A$2:$A$11,0)))*2) -> 22.198877 | D6: ='FX year-end'!D6*EXP((INDEX('Rates 2y'!$D$2:$D$11,MATCH($A6,'Rates 2y'!$A$2:$A$11,0))-INDEX('Rates 2y'!$D$2:$D$11,MATCH("USD",'Rates 2y'!$A$2:$A$11,0)))*2) -> 21.041528 | E6: ='FX year-end'!E6*EXP((INDEX('Rates 2y'!$E$2:$E$11,MATCH($A6,'Rates 2y'!$A$2:$A$11,0))-INDEX('Rates 2y'!$E$2:$E$11,MATCH("USD",'Rates 2y'!$A$2:$A$11,0)))*2) -> 21.620941 | F6: ='FX year-end'!F6*EXP((INDEX('Rates 2y'!$F$2:$F$11,MATCH($A6,'Rates 2y'!$A$2:$A$11,0))-INDEX('Rates 2y'!$F$2:$F$11,MATCH("USD",'Rates 2y'!$A$2:$A$11,0)))*2) -> 23.285429 | G6: ='FX year-end'!G6*EXP((INDEX('Rates 2y'!$G$2:$G$11,MATCH($A6,'Rates 2y'!$A$2:$A$11,0))-INDEX('Rates 2y'!$G$2:$G$11,MATCH("USD",'Rates 2y'!$A$2:$A$11,0)))*2) -> 21.969118 | H6: ='FX year-end'!H6*EXP((INDEX('Rates 2y'!$H$2:$H$11,MATCH($A6,'Rates 2y'!$A$2:$A$11,0))-INDEX('Rates 2y'!$H$2:$H$11,MATCH("USD",'Rates 2y'!$A$2:$A$11,0)))*2) -> 19.131547 | I6: ='FX year-end'!I6*EXP((INDEX('Rates 2y'!$I$2:$I$11,MATCH($A6,'Rates 2y'!$A$2:$A$11,0))-INDEX('Rates 2y'!$I$2:$I$11,MATCH("USD",'Rates 2y'!$A$2:$A$11,0)))*2) -> 23.105091 | J6: ='FX year-end'!J6*EXP((INDEX('Rates 2y'!$J$2:$J$11,MATCH($A6,'Rates 2y'!$A$2:$A$11,0))-INDEX('Rates 2y'!$J$2:$J$11,MATCH("USD",'Rates 2y'!$A$2:$A$11,0)))*2) -> 19.406213 | K6: ='FX year-end'!K6*EXP((INDEX('Rates 2y'!$K$2:$K$11,MATCH($A6,'Rates 2y'!$A$2:$A$11,0))-INDEX('Rates 2y'!$K$2:$K$11,MATCH("USD",'Rates 2y'!$A$2:$A$11,0)))*2) -> 19.140358
A7: BRL | B7: ='FX year-end'!B7*EXP((INDEX('Rates 2y'!$B$2:$B$11,MATCH($A7,'Rates 2y'!$A$2:$A$11,0))-INDEX('Rates 2y'!$B$2:$B$11,MATCH("USD",'Rates 2y'!$A$2:$A$11,0)))*2) -> 3.7042487 | C7: ='FX year-end'!C7*EXP((INDEX('Rates 2y'!$C$2:$C$11,MATCH($A7,'Rates 2y'!$A$2:$A$11,0))-INDEX('Rates 2y'!$C$2:$C$11,MATCH("USD",'Rates 2y'!$A$2:$A$11,0)))*2) -> 4.2568915 | D7: ='FX year-end'!D7*EXP((INDEX('Rates 2y'!$D$2:$D$11,MATCH($A7,'Rates 2y'!$A$2:$A$11,0))-INDEX('Rates 2y'!$D$2:$D$11,MATCH("USD",'Rates 2y'!$A$2:$A$11,0)))*2) -> 4.3258749 | E7: ='FX year-end'!E7*EXP((INDEX('Rates 2y'!$E$2:$E$11,MATCH($A7,'Rates 2y'!$A$2:$A$11,0))-INDEX('Rates 2y'!$E$2:$E$11,MATCH("USD",'Rates 2y'!$A$2:$A$11,0)))*2) -> 5.6423201 | F7: ='FX year-end'!F7*EXP((INDEX('Rates 2y'!$F$2:$F$11,MATCH($A7,'Rates 2y'!$A$2:$A$11,0))-INDEX('Rates 2y'!$F$2:$F$11,MATCH("USD",'Rates 2y'!$A$2:$A$11,0)))*2) -> 6.8814608 | G7: ='FX year-end'!G7*EXP((INDEX('Rates 2y'!$G$2:$G$11,MATCH($A7,'Rates 2y'!$A$2:$A$11,0))-INDEX('Rates 2y'!$G$2:$G$11,MATCH("USD",'Rates 2y'!$A$2:$A$11,0)))*2) -> 6.3230199 | H7: ='FX year-end'!H7*EXP((INDEX('Rates 2y'!$H$2:$H$11,MATCH($A7,'Rates 2y'!$A$2:$A$11,0))-INDEX('Rates 2y'!$H$2:$H$11,MATCH("USD",'Rates 2y'!$A$2:$A$11,0)))*2) -> 5.4740565 | I7: ='FX year-end'!I7*EXP((INDEX('Rates 2y'!$I$2:$I$11,MATCH($A7,'Rates 2y'!$A$2:$A$11,0))-INDEX('Rates 2y'!$I$2:$I$11,MATCH("USD",'Rates 2y'!$A$2:$A$11,0)))*2) -> 7.7228109 | J7: ='FX year-end'!J7*EXP((INDEX('Rates 2y'!$J$2:$J$11,MATCH($A7,'Rates 2y'!$A$2:$A$11,0))-INDEX('Rates 2y'!$J$2:$J$11,MATCH("USD",'Rates 2y'!$A$2:$A$11,0)))*2) -> 6.745067 | K7: ='FX year-end'!K7*EXP((INDEX('Rates 2y'!$K$2:$K$11,MATCH($A7,'Rates 2y'!$A$2:$A$11,0))-INDEX('Rates 2y'!$K$2:$K$11,MATCH("USD",'Rates 2y'!$A$2:$A$11,0)))*2) -> 6.385409
A8: SAR | B8: ='FX year-end'!B8*EXP((INDEX('Rates 2y'!$B$2:$B$11,MATCH($A8,'Rates 2y'!$A$2:$A$11,0))-INDEX('Rates 2y'!$B$2:$B$11,MATCH("USD",'Rates 2y'!$A$2:$A$11,0)))*2) -> 3.7538494 | C8: ='FX year-end'!C8*EXP((INDEX('Rates 2y'!$C$2:$C$11,MATCH($A8,'Rates 2y'!$A$2:$A$11,0))-INDEX('Rates 2y'!$C$2:$C$11,MATCH("USD",'Rates 2y'!$A$2:$A$11,0)))*2) -> 3.7823888 | D8: ='FX year-end'!D8*EXP((INDEX('Rates 2y'!$D$2:$D$11,MATCH($A8,'Rates 2y'!$A$2:$A$11,0))-INDEX('Rates 2y'!$D$2:$D$11,MATCH("USD",'Rates 2y'!$A$2:$A$11,0)))*2) -> 3.8027269 | E8: ='FX year-end'!E8*EXP((INDEX('Rates 2y'!$E$2:$E$11,MATCH($A8,'Rates 2y'!$A$2:$A$11,0))-INDEX('Rates 2y'!$E$2:$E$11,MATCH("USD",'Rates 2y'!$A$2:$A$11,0)))*2) -> 3.8058674 | F8: ='FX year-end'!F8*EXP((INDEX('Rates 2y'!$F$2:$F$11,MATCH($A8,'Rates 2y'!$A$2:$A$11,0))-INDEX('Rates 2y'!$F$2:$F$11,MATCH("USD",'Rates 2y'!$A$2:$A$11,0)))*2) -> 3.7853879 | G8: ='FX year-end'!G8*EXP((INDEX('Rates 2y'!$G$2:$G$11,MATCH($A8,'Rates 2y'!$A$2:$A$11,0))-INDEX('Rates 2y'!$G$2:$G$11,MATCH("USD",'Rates 2y'!$A$2:$A$11,0)))*2) -> 3.7979933 | H8: ='FX year-end'!H8*EXP((INDEX('Rates 2y'!$H$2:$H$11,MATCH($A8,'Rates 2y'!$A$2:$A$11,0))-INDEX('Rates 2y'!$H$2:$H$11,MATCH("USD",'Rates 2y'!$A$2:$A$11,0)))*2) -> 3.8323573 | I8: ='FX year-end'!I8*EXP((INDEX('Rates 2y'!$I$2:$I$11,MATCH($A8,'Rates 2y'!$A$2:$A$11,0))-INDEX('Rates 2y'!$I$2:$I$11,MATCH("USD",'Rates 2y'!$A$2:$A$11,0)))*2) -> 3.8247171 | J8: ='FX year-end'!J8*EXP((INDEX('Rates 2y'!$J$2:$J$11,MATCH($A8,'Rates 2y'!$A$2:$A$11,0))-INDEX('Rates 2y'!$J$2:$J$11,MATCH("USD",'Rates 2y'!$A$2:$A$11,0)))*2) -> 3.8328003 | K8: ='FX year-end'!K8*EXP((INDEX('Rates 2y'!$K$2:$K$11,MATCH($A8,'Rates 2y'!$A$2:$A$11,0))-INDEX('Rates 2y'!$K$2:$K$11,MATCH("USD",'Rates 2y'!$A$2:$A$11,0)))*2) -> 3.8393453
A9: HKD | B9: ='FX year-end'!B9*EXP((INDEX('Rates 2y'!$B$2:$B$11,MATCH($A9,'Rates 2y'!$A$2:$A$11,0))-INDEX('Rates 2y'!$B$2:$B$11,MATCH("USD",'Rates 2y'!$A$2:$A$11,0)))*2) -> 7.7251038 | C9: ='FX year-end'!C9*EXP((INDEX('Rates 2y'!$C$2:$C$11,MATCH($A9,'Rates 2y'!$A$2:$A$11,0))-INDEX('Rates 2y'!$C$2:$C$11,MATCH("USD",'Rates 2y'!$A$2:$A$11,0)))*2) -> 7.7235758 | D9: ='FX year-end'!D9*EXP((INDEX('Rates 2y'!$D$2:$D$11,MATCH($A9,'Rates 2y'!$A$2:$A$11,0))-INDEX('Rates 2y'!$D$2:$D$11,MATCH("USD",'Rates 2y'!$A$2:$A$11,0)))*2) -> 7.8068139 | E9: ='FX year-end'!E9*EXP((INDEX('Rates 2y'!$E$2:$E$11,MATCH($A9,'Rates 2y'!$A$2:$A$11,0))-INDEX('Rates 2y'!$E$2:$E$11,MATCH("USD",'Rates 2y'!$A$2:$A$11,0)))*2) -> 7.7630407 | F9: ='FX year-end'!F9*EXP((INDEX('Rates 2y'!$F$2:$F$11,MATCH($A9,'Rates 2y'!$A$2:$A$11,0))-INDEX('Rates 2y'!$F$2:$F$11,MATCH("USD",'Rates 2y'!$A$2:$A$11,0)))*2) -> 7.7773127 | G9: ='FX year-end'!G9*EXP((INDEX('Rates 2y'!$G$2:$G$11,MATCH($A9,'Rates 2y'!$A$2:$A$11,0))-INDEX('Rates 2y'!$G$2:$G$11,MATCH("USD",'Rates 2y'!$A$2:$A$11,0)))*2) -> 7.7276556 | H9: ='FX year-end'!H9*EXP((INDEX('Rates 2y'!$H$2:$H$11,MATCH($A9,'Rates 2y'!$A$2:$A$11,0))-INDEX('Rates 2y'!$H$2:$H$11,MATCH("USD",'Rates 2y'!$A$2:$A$11,0)))*2) -> 7.7109038 | I9: ='FX year-end'!I9*EXP((INDEX('Rates 2y'!$I$2:$I$11,MATCH($A9,'Rates 2y'!$A$2:$A$11,0))-INDEX('Rates 2y'!$I$2:$I$11,MATCH("USD",'Rates 2y'!$A$2:$A$11,0)))*2) -> 7.6341627 | J9: ='FX year-end'!J9*EXP((INDEX('Rates 2y'!$J$2:$J$11,MATCH($A9,'Rates 2y'!$A$2:$A$11,0))-INDEX('Rates 2y'!$J$2:$J$11,MATCH("USD",'Rates 2y'!$A$2:$A$11,0)))*2) -> 7.6449184 | K9: ='FX year-end'!K9*EXP((INDEX('Rates 2y'!$K$2:$K$11,MATCH($A9,'Rates 2y'!$A$2:$A$11,0))-INDEX('Rates 2y'!$K$2:$K$11,MATCH("USD",'Rates 2y'!$A$2:$A$11,0)))*2) -> 7.7065639
A10: CNY | B10: ='FX year-end'!B10*EXP((INDEX('Rates 2y'!$B$2:$B$11,MATCH($A10,'Rates 2y'!$A$2:$A$11,0))-INDEX('Rates 2y'!$B$2:$B$11,MATCH("USD",'Rates 2y'!$A$2:$A$11,0)))*2) -> 6.7453403 | C10: ='FX year-end'!C10*EXP((INDEX('Rates 2y'!$C$2:$C$11,MATCH($A10,'Rates 2y'!$A$2:$A$11,0))-INDEX('Rates 2y'!$C$2:$C$11,MATCH("USD",'Rates 2y'!$A$2:$A$11,0)))*2) -> 6.906145 | D10: ='FX year-end'!D10*EXP((INDEX('Rates 2y'!$D$2:$D$11,MATCH($A10,'Rates 2y'!$A$2:$A$11,0))-INDEX('Rates 2y'!$D$2:$D$11,MATCH("USD",'Rates 2y'!$A$2:$A$11,0)))*2) -> 7.1296718 | E10: ='FX year-end'!E10*EXP((INDEX('Rates 2y'!$E$2:$E$11,MATCH($A10,'Rates 2y'!$A$2:$A$11,0))-INDEX('Rates 2y'!$E$2:$E$11,MATCH("USD",'Rates 2y'!$A$2:$A$11,0)))*2) -> 6.8662063 | F10: ='FX year-end'!F10*EXP((INDEX('Rates 2y'!$F$2:$F$11,MATCH($A10,'Rates 2y'!$A$2:$A$11,0))-INDEX('Rates 2y'!$F$2:$F$11,MATCH("USD",'Rates 2y'!$A$2:$A$11,0)))*2) -> 6.5753584 | G10: ='FX year-end'!G10*EXP((INDEX('Rates 2y'!$G$2:$G$11,MATCH($A10,'Rates 2y'!$A$2:$A$11,0))-INDEX('Rates 2y'!$G$2:$G$11,MATCH("USD",'Rates 2y'!$A$2:$A$11,0)))*2) -> 6.6727013 | H10: ='FX year-end'!H10*EXP((INDEX('Rates 2y'!$H$2:$H$11,MATCH($A10,'Rates 2y'!$A$2:$A$11,0))-INDEX('Rates 2y'!$H$2:$H$11,MATCH("USD",'Rates 2y'!$A$2:$A$11,0)))*2) -> 6.8215056 | I10: ='FX year-end'!I10*EXP((INDEX('Rates 2y'!$I$2:$I$11,MATCH($A10,'Rates 2y'!$A$2:$A$11,0))-INDEX('Rates 2y'!$I$2:$I$11,MATCH("USD",'Rates 2y'!$A$2:$A$11,0)))*2) -> 6.853874 | J10: ='FX year-end'!J10*EXP((INDEX('Rates 2y'!$J$2:$J$11,MATCH($A10,'Rates 2y'!$A$2:$A$11,0))-INDEX('Rates 2y'!$J$2:$J$11,MATCH("USD",'Rates 2y'!$A$2:$A$11,0)))*2) -> 6.7110327 | K10: ='FX year-end'!K10*EXP((INDEX('Rates 2y'!$K$2:$K$11,MATCH($A10,'Rates 2y'!$A$2:$A$11,0))-INDEX('Rates 2y'!$K$2:$K$11,MATCH("USD",'Rates 2y'!$A$2:$A$11,0)))*2) -> 6.4387966
A11: IDR | B11: ='FX year-end'!B11*EXP((INDEX('Rates 2y'!$B$2:$B$11,MATCH($A11,'Rates 2y'!$A$2:$A$11,0))-INDEX('Rates 2y'!$B$2:$B$11,MATCH("USD",'Rates 2y'!$A$2:$A$11,0)))*2) -> 14660.793 | C11: ='FX year-end'!C11*EXP((INDEX('Rates 2y'!$C$2:$C$11,MATCH($A11,'Rates 2y'!$A$2:$A$11,0))-INDEX('Rates 2y'!$C$2:$C$11,MATCH("USD",'Rates 2y'!$A$2:$A$11,0)))*2) -> 16151.245 | D11: ='FX year-end'!D11*EXP((INDEX('Rates 2y'!$D$2:$D$11,MATCH($A11,'Rates 2y'!$A$2:$A$11,0))-INDEX('Rates 2y'!$D$2:$D$11,MATCH("USD",'Rates 2y'!$A$2:$A$11,0)))*2) -> 15114.504 | E11: ='FX year-end'!E11*EXP((INDEX('Rates 2y'!$E$2:$E$11,MATCH($A11,'Rates 2y'!$A$2:$A$11,0))-INDEX('Rates 2y'!$E$2:$E$11,MATCH("USD",'Rates 2y'!$A$2:$A$11,0)))*2) -> 14975.645 | F11: ='FX year-end'!F11*EXP((INDEX('Rates 2y'!$F$2:$F$11,MATCH($A11,'Rates 2y'!$A$2:$A$11,0))-INDEX('Rates 2y'!$F$2:$F$11,MATCH("USD",'Rates 2y'!$A$2:$A$11,0)))*2) -> 15220.208 | G11: ='FX year-end'!G11*EXP((INDEX('Rates 2y'!$G$2:$G$11,MATCH($A11,'Rates 2y'!$A$2:$A$11,0))-INDEX('Rates 2y'!$G$2:$G$11,MATCH("USD",'Rates 2y'!$A$2:$A$11,0)))*2) -> 16086.045 | H11: ='FX year-end'!H11*EXP((INDEX('Rates 2y'!$H$2:$H$11,MATCH($A11,'Rates 2y'!$A$2:$A$11,0))-INDEX('Rates 2y'!$H$2:$H$11,MATCH("USD",'Rates 2y'!$A$2:$A$11,0)))*2) -> 16102.742 | I11: ='FX year-end'!I11*EXP((INDEX('Rates 2y'!$I$2:$I$11,MATCH($A11,'Rates 2y'!$A$2:$A$11,0))-INDEX('Rates 2y'!$I$2:$I$11,MATCH("USD",'Rates 2y'!$A$2:$A$11,0)))*2) -> 16964.526 | J11: ='FX year-end'!J11*EXP((INDEX('Rates 2y'!$J$2:$J$11,MATCH($A11,'Rates 2y'!$A$2:$A$11,0))-INDEX('Rates 2y'!$J$2:$J$11,MATCH("USD",'Rates 2y'!$A$2:$A$11,0)))*2) -> 17224.753 | K11: ='FX year-end'!K11*EXP((INDEX('Rates 2y'!$K$2:$K$11,MATCH($A11,'Rates 2y'!$A$2:$A$11,0))-INDEX('Rates 2y'!$K$2:$K$11,MATCH("USD",'Rates 2y'!$A$2:$A$11,0)))*2) -> 18464.886
A13: Covered-interest-parity forward: spot x exp((r_ccy - r_usd) x 2). Column '2017->2019' = rate agreed at end-2017 for delivery at end-2019.

Sheet Detail
A1: ticker | B1: company | C1: currency | D1: year | E1: last_trading_day | F1: open | G1: high | H1: low | I1: close | J1: average_close | K1: dividends_in_year | L1: dividend_yield | M1: rate_2y | N1: forward_2y_price | O1: forward_for_year | P1: actual_close_in_forward_year | Q1: forward_error
A2: 000408.SZ | B2: Zangge Mining Co Ltd | C2: CNY | D2: 2017 | E2: 43098 | F2: 15.12 | G2: 21.95 | H2: 12.65 | I2: 17.7 | J2: 15.9407 | K2: 0.3 | L2: 0.0169 | M2: 0.035 | N2: 18.3507 | O2: 2019 | P2: 7.38 | Q2: -0.5978
A3: 000408.SZ | B3: Zangge Mining Co Ltd | C3: CNY | D3: 2018 | E3: 43462 | F3: 17.72 | G3: 19.97 | H3: 10.38 | I3: 11.22 | J3: 14.1027 | K3: 0 | L3: 0 | M3: 0.027 | N3: 11.8425 | O3: 2020 | P3: 8.01 | Q3: -0.3236
A4: 000408.SZ | B4: Zangge Mining Co Ltd | C4: CNY | D4: 2019 | E4: 43830 | F4: 11.15 | G4: 13.2 | H4: 6.46 | I4: 7.38 | J4: 9.5288 | K4: 0 | L4: 0 | M4: 0.026 | N4: 7.7739 | O4: 2021 | P4: 41 | Q4: 4.274
A5: 000408.SZ | B5: Zangge Mining Co Ltd | C5: CNY | D5: 2020 | E5: 44196 | F5: 7.42 | G5: 8.96 | H5: 3.55 | I5: 8.01 | J5: 6.8916 | K5: 0 | L5: 0 | M5: 0.027 | N5: 8.4544 | O5: 2022 | P5: 25.97 | Q5: 2.0718
A6: 000408.SZ | B6: Zangge Mining Co Ltd | C6: CNY | D6: 2021 | E6: 44561 | F6: 8 | G6: 41.51 | H6: 7.47 | I6: 41 | J6: 21.0551 | K6: 0 | L6: 0 | M6: 0.023 | N6: 42.9301 | O6: 2023 | P6: 25.34 | Q6: -0.4097
A7: 000408.SZ | B7: Zangge Mining Co Ltd | C7: CNY | D7: 2022 | E7: 44925 | F7: 41.6 | G7: 41.77 | H7: 21.8 | I7: 25.97 | J7: 31.3621 | K7: 1.898 | L7: 0.0731 | M7: 0.023 | N7: 23.4947 | O7: 2024 | P7: 27.73 | Q7: 0.1803
A8: 000408.SZ | B8: Zangge Mining Co Ltd | C8: CNY | D8: 2023 | E8: 45289 | F8: 26.1 | G8: 28.9 | H8: 20.9 | I8: 25.34 | J8: 24.2581 | K8: 1.76 | L8: 0.0695 | M8: 0.022 | N8: 23.0456 | O8: 2025 | P8: 84.4 | Q8: 2.6623
A9: 000408.SZ | B9: Zangge Mining Co Ltd | C9: CNY | D9: 2024 | E9: 45657 | F9: 25.4 | G9: 34.08 | H9: 21.4 | I9: 27.73 | J9: 26.8147 | K9: 1.06 | L9: 0.0382 | M9: 0.011 | N9: 26.2604 | O9: 2026 | P9: 71.46 | Q9: 1.7212
A10: 000408.SZ | B10: Zangge Mining Co Ltd | C10: CNY | D10: 2025 | E10: 46022 | F10: 27.73 | G10: 87.68 | H10: 27.1 | I10: 84.4 | J10: 46.3005 | K10: 1 | L10: 0.0118 | M10: 0.014 | N10: 84.764 | O10: 2027
A11: 000408.SZ | B11: Zangge Mining Co Ltd | C11: CNY | D11: 2026 | E11: 46289 | F11: 85.01 | G11: 97.28 | H11: 66.5 | I11: 71.46 | J11: 80.5279 | K11: 2.5 | L11: 0.035 | M11: 0.014 | N11: 68.5229 | O11: 2028
A12: 1208.HK | B12: MMG Ltd | C12: HKD | D12: 2017 | E12: 43098 | F12: 1.97 | G12: 4.05 | H12: 1.92 | I12: 3.88 | J12: 3.1063 | K12: 0 | L12: 0 | M12: 0.013 | N12: 3.9822 | O12: 2019 | P12: 2.34 | Q12: -0.4124
A13: 1208.HK | B13: MMG Ltd | C13: HKD | D13: 2018 | E13: 43465 | F13: 3.88 | G13: 6.53 | H13: 2.73 | I13: 3.37 | J13: 4.6502 | K13: 0 | L13: 0 | M13: 0.018 | N13: 3.4935 | O13: 2020 | P13: 3.35 | Q13: -0.0411
A14: 1208.HK | B14: MMG Ltd | C14: HKD | D14: 2019 | E14: 43830 | F14: 3.3 | G14: 4.04 | H14: 1.48 | I14: 2.34 | J14: 2.5197 | K14: 0 | L14: 0 | M14: 0.017 | N14: 2.4209 | O14: 2021 | P14: 2.5 | Q14: 0.0327
A15: 1208.HK | B15: MMG Ltd | C15: HKD | D15: 2020 | E15: 44196 | F15: 2.34 | G15: 3.72 | H15: 1.02 | I15: 3.35 | J15: 1.9502 | K15: 0 | L15: 0 | M15: 0.002 | N15: 3.3634 | O15: 2022 | P15: 2 | Q15: -0.4054
A16: 1208.HK | B16: MMG Ltd | C16: HKD | D16: 2021 | E16: 44561 | F16: 3.29 | G16: 6.5 | H16: 2.14 | I16: 2.5 | J16: 3.849 | K16: 0 | L16: 0 | M16: 0.006 | N16: 2.5302 | O16: 2023 | P16: 2.31 | Q16: -0.087
A17: 1208.HK | B17: MMG Ltd | C17: HKD | D17: 2022 | E17: 44925 | F17: 2.51 | G17: 4.06 | H17: 1.51 | I17: 2 | J17: 2.5699 | K17: 0 | L17: 0 | M17: 0.04 | N17: 2.1666 | O17: 2024 | P17: 2.57 | Q17: 0.1862
A18: 1208.HK | B18: MMG Ltd | C18: HKD | D18: 2023 | E18: 45289 | F18: 1.99 | G18: 3.58 | H18: 1.94 | I18: 2.31 | J18: 2.4644 | K18: 0 | L18: 0 | M18: 0.036 | N18: 2.4825 | O18: 2025 | P18: 8.81 | Q18: 2.5489
A19: 1208.HK | B19: MMG Ltd | C19: HKD | D19: 2024 | E19: 45657 | F19: 2.34 | G19: 4.51 | H19: 1.75 | I19: 2.57 | J19: 2.7732 | K19: 0 | L19: 0 | M19: 0.034 | N19: 2.7508 | O19: 2026 | P19: 8.545 | Q19: 2.1063
A20: 1208.HK | B20: MMG Ltd | C20: HKD | D20: 2025 | E20: 46022 | F20: 2.54 | G20: 9.19 | H20: 1.95 | I20: 8.81 | J20: 4.4061 | K20: 0 | L20: 0 | M20: 0.026 | N20: 9.2802 | O20: 2027
A21: 1208.HK | B21: MMG Ltd | C21: HKD | D21: 2026 | E21: 46290 | F21: 8.76 | G21: 11.96 | H21: 6.53 | I21: 8.545 | J21: 8.8797 | K21: 0 | L21: 0 | M21: 0.026 | N21: 9.0011 | O21: 2028
A22: 1211.SR | B22: Saudi Arabian Mining Co (Maaden) | C22: SAR | D22: 2017 | E22: 43100 | F22: 39.1 | G22: 57 | H22: 38.5 | I22: 52.1 | J22: 46.3504 | K22: 0 | L22: 0 | M22: 0.02 | N22: 54.2262 | O22: 2019 | P22: 44.4 | Q22: -0.1812
A23: 1211.SR | B23: Saudi Arabian Mining Co (Maaden) | C23: SAR | D23: 2018 | E23: 43465 | F23: 51.2 | G23: 60 | H23: 40.9 | I23: 49.3 | J23: 52.886 | K23: 0 | L23: 0 | M23: 0.029 | N23: 52.2439 | O23: 2020 | P23: 40.5 | Q23: -0.2248
A24: 1211.SR | B24: Saudi Arabian Mining Co (Maaden) | C24: SAR | D24: 2019 | E24: 43830 | F24: 49 | G24: 59.6 | H24: 39.6 | I24: 44.4 | J24: 49.1308 | K24: 0 | L24: 0 | M24: 0.023 | N24: 46.4901 | O24: 2021 | P24: 78.5 | Q24: 0.6885
A25: 1211.SR | B25: Saudi Arabian Mining Co (Maaden) | C25: SAR | D25: 2020 | E25: 44196 | F25: 44.15 | G25: 46.5 | H25: 27.8 | I25: 40.5 | J25: 38.3618 | K25: 0 | L25: 0 | M25: 0.009 | N25: 41.2356 | O25: 2022 | P25: 64.7 | Q25: 2.1381
A26: 1211.SR | B26: Saudi Arabian Mining Co (Maaden) | C26: SAR | D26: 2021 | E26: 44560 | F26: 40.5 | G26: 89.5 | H26: 39.85 | I26: 78.5 | J26: 64.021 | K26: 0 | L26: 0 | M26: 0.012 | N26: 80.4068 | O26: 2023 | P26: 48.55 | Q26: 0.8114
A27: 1211.SR | B27: Saudi Arabian Mining Co (Maaden) | C27: SAR | D27: 2022 | E27: 44924 | F27: 78.4 | G27: 150.8 | H27: 45.1 | I27: 64.7 | J27: 85.1885 | K27: 0 | L27: 0 | M27: 0.05 | N27: 71.5046 | O27: 2024 | P27: 50.3 | Q27: 0.0552
A28: 1211.SR | B28: Saudi Arabian Mining Co (Maaden) | C28: SAR | D28: 2023 | E28: 45291 | F28: 65.3 | G28: 76.7 | H28: 35.4 | I28: 48.55 | J28: 52.437 | K28: 0 | L28: 0 | M28: 0.054 | N28: 54.087 | O28: 2025 | P28: 60.95 | Q28: 0.1269
A29: 1211.SR | B29: Saudi Arabian Mining Co (Maaden) | C29: SAR | D29: 2024 | E29: 45657 | F29: 51.4 | G29: 57.4 | H29: 39 | I29: 50.3 | J29: 48.0612 | K29: 0 | L29: 0 | M29: 0.052 | N29: 55.8129 | O29: 2026 | P29: 61.1 | Q29: 0.0947
A30: 1211.SR | B30: Saudi Arabian Mining Co (Maaden) | C30: SAR | D30: 2025 | E30: 46022 | F30: 50.3 | G30: 68.45 | H30: 37.85 | I30: 60.95 | J30: 53.3839 | K30: 0 | L30: 0 | M30: 0.046 | N30: 66.8234 | O30: 2027
A31: 1211.SR | B31: Saudi Arabian Mining Co (Maaden) | C31: SAR | D31: 2026 | E31: 46289 | F31: 61.2 | G31: 79.9 | H31: 54.9 | I31: 61.1 | J31: 65.5639 | K31: 0 | L31: 0 | M31: 0.046 | N31: 66.9879 | O31: 2028
A32: 2899.HK | B32: Zijin Mining Group Co Ltd | C32: HKD | D32: 2017 | E32: 43098 | F32: 2.5 | G32: 3.18 | H32: 2.48 | I32: 2.95 | J32: 2.75 | K32: 0.0687 | L32: 0.0233 | M32: 0.013 | N32: 2.89 | O32: 2019 | P32: 3.88 | Q32: 0.3426
A33: 2899.HK | B33: Zijin Mining Group Co Ltd | C33: HKD | D33: 2018 | E33: 43465 | F33: 3.02 | G33: 4.37 | H33: 2.57 | I33: 2.97 | J33: 3.2065 | K33: 0.1111 | L33: 0.0374 | M33: 0.018 | N33: 2.8569 | O33: 2020 | P33: 8.77 | Q33: 2.0698
A34: 2899.HK | B34: Zijin Mining Group Co Ltd | C34: HKD | D34: 2019 | E34: 43830 | F34: 2.97 | G34: 3.89 | H34: 2.62 | I34: 3.88 | J34: 3.015 | K34: 0.1138 | L34: 0.0293 | M34: 0.017 | N34: 3.7855 | O34: 2021 | P34: 9.28 | Q34: 1.4515
A35: 2899.HK | B35: Zijin Mining Group Co Ltd | C35: HKD | D35: 2020 | E35: 44196 | F35: 3.9 | G35: 8.89 | H35: 2.3 | I35: 8.77 | J35: 4.6719 | K35: 0.1095 | L35: 0.0125 | M35: 0.002 | N35: 8.588 | O35: 2022 | P35: 10.58 | Q35: 0.232
A36: 2899.HK | B36: Zijin Mining Group Co Ltd | C36: HKD | D36: 2021 | E36: 44561 | F36: 8.77 | G36: 16.24 | H36: 8.47 | I36: 9.28 | J36: 10.711 | K36: 0.1451 | L36: 0.0156 | M36: 0.006 | N36: 9.103 | O36: 2023 | P36: 12.72 | Q36: 0.3973
A37: 2899.HK | B37: Zijin Mining Group Co Ltd | C37: HKD | D37: 2022 | E37: 44925 | F37: 9.34 | G37: 14.18 | H37: 7.18 | I37: 10.58 | J37: 9.9719 | K37: 0.2326 | L37: 0.022 | M37: 0.04 | N37: 10.9682 | O37: 2024 | P37: 14.16 | Q37: 0.291
A38: 2899.HK | B38: Zijin Mining Group Co Ltd | C38: HKD | D38: 2023 | E38: 45289 | F38: 10.5 | G38: 14.8 | H38: 10.38 | I38: 12.72 | J38: 12.3085 | K38: 0.2777 | L38: 0.0218 | M38: 0.036 | N38: 13.0856 | O38: 2025 | P38: 35.66 | Q38: 1.7251
A39: 2899.HK | B39: Zijin Mining Group Co Ltd | C39: HKD | D39: 2024 | E39: 45657 | F39: 12.7 | G39: 20.1 | H39: 10.7 | I39: 14.16 | J39: 15.5004 | K39: 0.3294 | L39: 0.0233 | M39: 0.034 | N39: 14.4673 | O39: 2026 | P39: 32.5 | Q39: 1.2464
A40: 2899.HK | B40: Zijin Mining Group Co Ltd | C40: HKD | D40: 2025 | E40: 46022 | F40: 14.02 | G40: 36.92 | H40: 13.86 | I40: 35.66 | J40: 22.8656 | K40: 0.5443 | L40: 0.0153 | M40: 0.026 | N40: 36.434 | O40: 2027
A41: 2899.HK | B41: Zijin Mining Group Co Ltd | C41: HKD | D41: 2026 | E41: 46290 | F41: 35.66 | G41: 46.98 | H41: 26.58 | I41: 32.5 | J41: 36.0909 | K41: 0.9207 | L41: 0.0283 | M41: 0.026 | N41: 32.3489 | O41: 2028
A42: AAL.L | B42: Anglo American plc | C42: GBp | D42: 2017 | E42: 43098 | F42: 1166.0059 | G42: 1554.5079 | H42: 950.1048 | I42: 1549.5078 | J42: 1265.1588 | K42: 42.9552 | L42: 0.0277 | M42: 0.0045 | N42: 1479.1885 | O42: 2019 | P42: 2173.0111 | Q42: 0.4691
A43: AAL.L | B43: Anglo American plc | C43: GBp | D43: 2018 | E43: 43465 | F43: 1559.008 | G43: 1948.0099 | H43: 1433.8073 | I43: 1747.8088 | J43: 1691.2292 | K43: 89.0212 | L43: 0.0509 | M43: 0.0075 | N43: 1602.3909 | O43: 2020 | P43: 2424.5124 | Q43: 0.5131
A44: AAL.L | B44: Anglo American plc | C44: GBp | D44: 2019 | E44: 43830 | F44: 1715.0088 | G44: 2294.0117 | H44: 1654.8085 | I44: 2173.0111 | J44: 1985.42 | K44: 105.093 | L44: 0.0484 | M44: 0.0055 | N44: 1994.4895 | O44: 2021 | P44: 3015.987 | Q44: 0.5192
A45: AAL.L | B45: Anglo American plc | C45: GBp | D45: 2020 | E45: 44196 | F45: 2182.5112 | G45: 2564.513 | H45: 1018.2051 | I45: 2424.5124 | J45: 1877.4608 | K45: 68.8747 | L45: 0.0284 | M45: -0.0015 | N45: 2283.7415 | O45: 2022 | P45: 3236.4859 | Q45: 0.4238
A46: AAL.L | B46: Anglo American plc | C46: GBp | D46: 2021 | E46: 44561 | F46: 2478.5127 | G46: 3509.0179 | H46: 2321.012 | I46: 3015.987 | J46: 2916.9277 | K46: 270.6098 | L46: 0.0896 | M46: 0.007 | N46: 2556.5546 | O46: 2023 | P46: 1970.5915 | Q46: -0.2292
A47: AAL.L | B47: Anglo American plc | C47: GBp | D47: 2022 | E47: 44925 | F47: 3025.4868 | G47: 4996.7783 | H47: 2487.4892 | I47: 3236.4859 | J47: 3243.97 | K47: 273.4709 | L47: 0.0845 | M47: 0.036 | N47: 2937.3143 | O47: 2024 | P47: 2363.9897 | Q47: -0.1952
A48: AAL.L | B48: Anglo American plc | C48: GBp | D48: 2023 | E48: 45289 | F48: 3231.486 | G48: 3698.984 | H48: 1629.9929 | I48: 1970.5915 | J48: 2472.6371 | K48: 119.2608 | L48: 0.0605 | M48: 0.04 | N48: 1891.3543 | O48: 2025 | P48: 3085 | Q48: 0.6628
A49: AAL.L | B49: Anglo American plc | C49: GBp | D49: 2024 | E49: 45657 | F49: 1983.9915 | G49: 2812.9877 | H49: 1657.5928 | I49: 2363.9897 | J49: 2223.0443 | K49: 75.0852 | L49: 0.0318 | M49: 0.044 | N49: 2422.5644 | O49: 2026 | P49: 4042 | Q49: 0.7009
A50: AAL.L | B50: Anglo American plc | C50: GBp | D50: 2025 | E50: 46022 | F50: 2385.9896 | G50: 3093.8149 | H50: 1673.3927 | I50: 3085 | J50: 2418.8185 | K50: 24.3828 | L50: 0.0078 | M50: 0.0375 | N50: 3273.9 | O50: 2027
A51: AAL.L | B51: Anglo American plc | C51: GBp | D51: 2026 | E51: 46290 | F51: 3098 | G51: 4348 | H51: 2757 | I51: 4042 | J51: 3663.9328 | K51: 28.809 | L51: 0.0071 | M51: 0.0375 | N51: 4295.1428 | O51: 2028
A52: AEM | B52: Agnico Eagle Mines Ltd | C52: USD | D52: 2017 | E52: 43098 | F52: 41.9 | G52: 51.86 | H52: 39.3 | I52: 46.18 | J52: 45.836 | K52: 0.41 | L52: 0.0089 | M52: 0.0189 | N52: 47.1149 | O52: 2019 | P52: 61.61 | Q52: 0.3077
A53: AEM | B53: Agnico Eagle Mines Ltd | C53: USD | D53: 2018 | E53: 43465 | F53: 46.47 | G53: 49.8 | H53: 32.18 | I53: 40.4 | J53: 40.7645 | K53: 0.44 | L53: 0.0109 | M53: 0.0249 | N53: 41.5479 | O53: 2020 | P53: 70.51 | Q53: 0.6971
A54: AEM | B54: Agnico Eagle Mines Ltd | C54: USD | D54: 2019 | E54: 43830 | F54: 40.48 | G54: 64.88 | H54: 38.72 | I54: 61.61 | J54: 50.2829 | K54: 0.55 | L54: 0.0089 | M54: 0.0158 | N54: 62.4627 | O54: 2021 | P54: 53.14 | Q54: -0.1493
A55: AEM | B55: Agnico Eagle Mines Ltd | C55: USD | D55: 2020 | E55: 44196 | F55: 62.08 | G55: 89.23 | H55: 31 | I55: 70.51 | J55: 65.8719 | K55: 0.95 | L55: 0.0135 | M55: 0.0013 | N55: 68.8141 | O55: 2022 | P55: 51.99 | Q55: -0.2445
A56: AEM | B56: Agnico Eagle Mines Ltd | C56: USD | D56: 2021 | E56: 44561 | F56: 73.45 | G56: 76.69 | H56: 47.07 | I56: 53.14 | J56: 60.6234 | K56: 1.4 | L56: 0.0263 | M56: 0.0073 | N56: 51.1539 | O56: 2023 | P56: 54.85 | Q56: 0.0723
A57: AEM | B57: Agnico Eagle Mines Ltd | C57: USD | D57: 2022 | E57: 44925 | F57: 52.03 | G57: 67.14 | H57: 36.69 | I57: 51.99 | J57: 49.8861 | K57: 1.6 | L57: 0.0308 | M57: 0.0443 | N57: 53.4155 | O57: 2024 | P57: 78.21 | Q57: 0.4642
A58: AEM | B58: Agnico Eagle Mines Ltd | C58: USD | D58: 2023 | E58: 45289 | F58: 52.82 | G58: 61.15 | H58: 43.22 | I58: 54.85 | J58: 51.1018 | K58: 1.6 | L58: 0.0292 | M58: 0.0425 | N58: 56.3319 | O58: 2025 | P58: 169.53 | Q58: 2.0095
A59: AEM | B59: Agnico Eagle Mines Ltd | C59: USD | D59: 2024 | E59: 45657 | F59: 54.58 | G59: 89 | H59: 44.37 | I59: 78.21 | J59: 69.3142 | K59: 1.6 | L59: 0.0205 | M59: 0.0424 | N59: 81.7186 | O59: 2026 | P59: 194.48 | Q59: 1.3799
A60: AEM | B60: Agnico Eagle Mines Ltd | C60: USD | D60: 2025 | E60: 46022 | F60: 79.4 | G60: 187.5 | H60: 79.39 | I60: 169.53 | J60: 129.935 | K60: 1.6 | L60: 0.0094 | M60: 0.0348 | N60: 178.3511 | O60: 2027
A61: AEM | B61: Agnico Eagle Mines Ltd | C61: USD | D61: 2026 | E61: 46290 | F61: 170.24 | G61: 255.24 | H61: 134.38 | I61: 194.48 | J61: 190.1248 | K61: 1.35 | L61: 0.0069 | M61: 0.0348 | N61: 205.6234 | O61: 2028
A62: B | B62: Barrick Mining Corp | C62: USD | D62: 2017 | E62: 43098 | F62: 16 | G62: 20.78 | H62: 13.28 | I62: 14.47 | J62: 16.7512 | K62: 0.12 | L62: 0.0083 | M62: 0.0189 | N62: 14.7802 | O62: 2019 | P62: 18.59 | Q62: 0.2578
A63: B | B63: Barrick Mining Corp | C63: USD | D63: 2018 | E63: 43465 | F63: 14.65 | G63: 15.52 | H63: 9.53 | I63: 13.54 | J63: 12.611 | K63: 0.19 | L63: 0.014 | M63: 0.0249 | N63: 13.8375 | O63: 2020 | P63: 22.78 | Q63: 0.6462
A64: B | B64: Barrick Mining Corp | C64: USD | D64: 2019 | E64: 43830 | F64: 13.64 | G64: 20.07 | H64: 11.52 | I64: 18.59 | J64: 15.2866 | K64: 0.13 | L64: 0.007 | M64: 0.0158 | N64: 18.9203 | O64: 2021 | P64: 19 | Q64: 0.0042
A65: B | B65: Barrick Mining Corp | C65: USD | D65: 2020 | E65: 44196 | F65: 18.71 | G65: 31.22 | H65: 12.65 | I65: 22.78 | J65: 24.4271 | K65: 0.31 | L65: 0.0136 | M65: 0.0013 | N65: 22.2261 | O65: 2022 | P65: 17.18 | Q65: -0.227
A66: B | B66: Barrick Mining Corp | C66: USD | D66: 2021 | E66: 44561 | F66: 23.85 | G66: 25.37 | H66: 17.27 | I66: 19 | J66: 20.7749 | K66: 0.78 | L66: 0.0411 | M66: 0.0073 | N66: 17.7597 | O66: 2023 | P66: 18.09 | Q66: 0.0186
A67: B | B67: Barrick Mining Corp | C67: USD | D67: 2022 | E67: 44925 | F67: 18.78 | G67: 26.07 | H67: 13.01 | I67: 17.18 | J67: 18.6931 | K67: 0.65 | L67: 0.0378 | M67: 0.0443 | N67: 17.4036 | O67: 2024 | P67: 15.5 | Q67: -0.1094
A68: B | B68: Barrick Mining Corp | C68: USD | D68: 2023 | E68: 45289 | F68: 17.54 | G68: 20.75 | H68: 13.82 | I68: 18.09 | J68: 17.2442 | K68: 0.4 | L68: 0.0221 | M68: 0.0425 | N68: 18.8429 | O68: 2025 | P68: 43.55 | Q68: 1.3112
A69: B | B69: Barrick Mining Corp | C69: USD | D69: 2024 | E69: 45657 | F69: 18.02 | G69: 21.35 | H69: 13.76 | I69: 15.5 | J69: 17.4878 | K69: 0.4 | L69: 0.0258 | M69: 0.0424 | N69: 16.023 | O69: 2026 | P69: 42.88 | Q69: 1.6761
A70: B | B70: Barrick Mining Corp | C70: USD | D70: 2025 | E70: 46022 | F70: 15.76 | G70: 46.45 | H70: 15.31 | I70: 43.55 | J70: 25.1436 | K70: 0.525 | L70: 0.0121 | M70: 0.0348 | N70: 45.5768 | O70: 2027
A71: B | B71: Barrick Mining Corp | C71: USD | D71: 2026 | E71: 46290 | F71: 44.15 | G71: 54.69 | H71: 34.03 | I71: 42.88 | J71: 42.7072 | K71: 0.77 | L71: 0.018 | M71: 0.0348 | N71: 44.3491 | O71: 2028
A72: BHP.AX | B72: BHP Group Ltd | C72: AUD | D72: 2017 | E72: 43098 | F72: 25.0199 | G72: 29.7599 | H72: 22.0599 | I72: 29.5699 | J72: 25.6658 | K72: 1.1919 | L72: 0.0403 | M72: 0.02 | N72: 28.393 | O72: 2019 | P72: 38.9199 | Q72: 0.3708
A73: BHP.AX | B73: BHP Group Ltd | C73: AUD | D73: 2018 | E73: 43465 | F73: 29.4999 | G73: 35.6799 | H73: 28.1299 | I73: 34.2299 | J73: 32.039 | K73: 1.7541 | L73: 0.0512 | M73: 0.019 | N73: 32.0922 | O73: 2020 | P73: 42.4299 | Q73: 0.3221
A74: BHP.AX | B74: BHP Group Ltd | C74: AUD | D74: 2019 | E74: 43830 | F74: 34.2799 | G74: 42.3299 | H74: 32.2449 | I74: 38.9199 | J74: 37.4919 | K74: 3.7405 | L74: 0.0961 | M74: 0.009 | N74: 32.6972 | O74: 2021 | P74: 41.4999 | Q74: 0.2692
A75: BHP.AX | B75: BHP Group Ltd | C75: AUD | D75: 2020 | E75: 44196 | F75: 38.6999 | G75: 43.6599 | H75: 24.0499 | I75: 42.4299 | J75: 36.1864 | K75: 1.9638 | L75: 0.0463 | M75: 0.001 | N75: 38.756 | O75: 2022 | P75: 45.63 | Q75: 0.3223
A76: BHP.AX | B76: BHP Group Ltd | C76: AUD | D76: 2021 | E76: 44561 | F76: 42.6299 | G76: 54.5499 | H76: 35.5599 | I76: 41.4999 | J76: 44.8667 | K76: 4.5222 | L76: 0.109 | M76: 0.006 | N76: 33.7761 | O76: 2023 | P76: 50.41 | Q76: 0.6762
A77: BHP.AX | B77: BHP Group Ltd | C77: AUD | D77: 2022 | E77: 44925 | F77: 41.7499 | G77: 53.7199 | H77: 35.83 | I77: 45.63 | J77: 43.6558 | K77: 4.8885 | L77: 0.1015 | M77: 0.035 | N77: 39.9458 | O77: 2024 | P77: 39.55 | Q77: -0.0099
A78: BHP.AX | B78: BHP Group Ltd | C78: AUD | D78: 2023 | E78: 45289 | F78: 46.1 | G78: 50.84 | H78: 41.66 | I78: 50.41 | J78: 45.694 | K78: 2.6143 | L78: 0.0519 | M78: 0.037 | N78: 48.9338 | O78: 2025 | P78: 45.49 | Q78: -0.0704
A79: BHP.AX | B79: BHP Group Ltd | C79: AUD | D79: 2024 | E79: 45657 | F79: 50.13 | G79: 50.605 | H79: 38.28 | I79: 39.55 | J79: 43.1465 | K79: 2.2062 | L79: 0.0558 | M79: 0.0385 | N79: 38.2063 | O79: 2026 | P79: 60.72 | Q79: 0.5893
A80: BHP.AX | B80: BHP Group Ltd | C80: AUD | D80: 2025 | E80: 46022 | F80: 39.5 | G80: 46.03 | H80: 33.25 | I80: 45.49 | J80: 40.3183 | K80: 1.7102 | L80: 0.0376 | M80: 0.039 | N80: 45.618 | O80: 2027
A81: BHP.AX | B81: BHP Group Ltd | C81: AUD | D81: 2026 | E81: 46290 | F81: 45.53 | G81: 68.77 | H81: 45.37 | I81: 60.72 | J81: 57.0201 | K81: 2.4184 | L81: 0.0398 | M81: 0.039 | N81: 60.6195 | O81: 2028
A82: EQX | B82: Equinox Gold Corp | C82: USD | D82: 2019 | E82: 43830 | F82: 0.75 | G82: 8.18 | H82: 0.73 | I82: 7.7 | J82: 2.8306 | K82: 0 | L82: 0 | M82: 0.0158 | N82: 7.9472 | O82: 2021 | P82: 6.76 | Q82: -0.1494
A83: EQX | B83: Equinox Gold Corp | C83: USD | D83: 2020 | E83: 44196 | F83: 7.9 | G83: 13.662 | H83: 4.63 | I83: 10.34 | J83: 9.9641 | K83: 0 | L83: 0 | M83: 0.0013 | N83: 10.3669 | O83: 2022 | P83: 3.28 | Q83: -0.6836
A84: EQX | B84: Equinox Gold Corp | C84: USD | D84: 2021 | E84: 44561 | F84: 10.8 | G84: 11.24 | H84: 5.9 | I84: 6.76 | J84: 7.9372 | K84: 0 | L84: 0 | M84: 0.0073 | N84: 6.8594 | O84: 2023 | P84: 4.89 | Q84: -0.2871
A85: EQX | B85: Equinox Gold Corp | C85: USD | D85: 2022 | E85: 44925 | F85: 6.69 | G85: 9.07 | H85: 2.35 | I85: 3.28 | J85: 5.1929 | K85: 0 | L85: 0 | M85: 0.0443 | N85: 3.5839 | O85: 2024 | P85: 5.02 | Q85: 0.4007
A86: EQX | B86: Equinox Gold Corp | C86: USD | D86: 2023 | E86: 45289 | F86: 3.35 | G86: 5.845 | H86: 3.32 | I86: 4.89 | J86: 4.687 | K86: 0 | L86: 0 | M86: 0.0425 | N86: 5.3238 | O86: 2025 | P86: 14.04 | Q86: 1.6372
A87: EQX | B87: Equinox Gold Corp | C87: USD | D87: 2024 | E87: 45657 | F87: 4.93 | G87: 6.5 | H87: 3.95 | I87: 5.02 | J87: 5.3678 | K87: 0 | L87: 0 | M87: 0.0424 | N87: 5.4643 | O87: 2026 | P87: 11.94 | Q87: 1.1851
A88: EQX | B88: Equinox Gold Corp | C88: USD | D88: 2025 | E88: 46022 | F88: 5.13 | G88: 15.1 | H88: 5.04 | I88: 14.04 | J88: 8.4156 | K88: 0 | L88: 0 | M88: 0.0348 | N88: 15.052 | O88: 2027
A89: EQX | B89: Equinox Gold Corp | C89: USD | D89: 2026 | E89: 46290 | F89: 14.39 | G89: 18.96 | H89: 8.485 | I89: 11.94 | J89: 13.1057 | K89: 0.053 | L89: 0.0044 | M89: 0.0348 | N89: 12.6875 | O89: 2028
A90: EVN.AX | B90: Evolution Mining Ltd | C90: AUD | D90: 2017 | E90: 43098 | F90: 2.05 | G90: 2.69 | H90: 1.89 | I90: 2.65 | J90: 2.3197 | K90: 0.05 | L90: 0.0189 | M90: 0.02 | N90: 2.656 | O90: 2019 | P90: 3.8 | Q90: 0.4307
A91: EVN.AX | B91: Evolution Mining Ltd | C91: AUD | D91: 2018 | E91: 43465 | F91: 2.65 | G91: 3.69 | H91: 2.49 | I91: 3.69 | J91: 3.0382 | K91: 0.075 | L91: 0.0203 | M91: 0.019 | N91: 3.6802 | O91: 2020 | P91: 4.99 | Q91: 0.3559
A92: EVN.AX | B92: Evolution Mining Ltd | C92: AUD | D92: 2019 | E92: 43830 | F92: 3.69 | G92: 5.585 | H92: 3.04 | I92: 3.8 | J92: 4.0952 | K92: 0.095 | L92: 0.025 | M92: 0.009 | N92: 3.6803 | O92: 2021 | P92: 4.06 | Q92: 0.1032
A93: EVN.AX | B93: Evolution Mining Ltd | C93: AUD | D93: 2020 | E93: 44196 | F93: 3.78 | G93: 6.585 | H93: 3.285 | I93: 4.99 | J93: 5.1846 | K93: 0.16 | L93: 0.0321 | M93: 0.001 | N93: 4.6894 | O93: 2022 | P93: 2.98 | Q93: -0.3645
A94: EVN.AX | B94: Evolution Mining Ltd | C94: AUD | D94: 2021 | E94: 44561 | F94: 5.06 | G94: 5.44 | H94: 3.27 | I94: 4.06 | J94: 4.305 | K94: 0.12 | L94: 0.0296 | M94: 0.006 | N94: 3.8732 | O94: 2023 | P94: 3.96 | Q94: 0.0224
A95: EVN.AX | B95: Evolution Mining Ltd | C95: AUD | D95: 2022 | E95: 44925 | F95: 4.04 | G95: 4.75 | H95: 1.8 | I95: 2.98 | J95: 3.1492 | K95: 0.06 | L95: 0.0201 | M95: 0.035 | N95: 3.0699 | O95: 2024 | P95: 4.81 | Q95: 0.5668
A96: EVN.AX | B96: Evolution Mining Ltd | C96: AUD | D96: 2023 | E96: 45289 | F96: 3.01 | G96: 4.23 | H96: 2.555 | I96: 3.96 | J96: 3.4562 | K96: 0.04 | L96: 0.0101 | M96: 0.037 | N96: 4.1789 | O96: 2025 | P96: 12.68 | Q96: 2.0343
A97: EVN.AX | B97: Evolution Mining Ltd | C97: AUD | D97: 2024 | E97: 45657 | F97: 3.92 | G97: 5.38 | H97: 2.83 | I97: 4.81 | J97: 4.0338 | K97: 0.07 | L97: 0.0146 | M97: 0.0385 | N97: 5.046 | O97: 2026 | P97: 13.71 | Q97: 1.717
A98: EVN.AX | B98: Evolution Mining Ltd | C98: AUD | D98: 2025 | E98: 46022 | F98: 4.83 | G98: 13.3 | H98: 4.8 | I98: 12.68 | J98: 8.5276 | K98: 0.2 | L98: 0.0158 | M98: 0.039 | N98: 13.2829 | O98: 2027
A99: EVN.AX | B99: Evolution Mining Ltd | C99: AUD | D99: 2026 | E99: 46290 | F99: 12.57 | G99: 17.75 | H99: 10.205 | I99: 13.71 | J99: 13.3245 | K99: 0.41 | L99: 0.0299 | M99: 0.039 | N99: 13.9617 | O99: 2028
A100: FCX | B100: Freeport-McMoRan Inc | C100: USD | D100: 2017 | E100: 43098 | F100: 13.49 | G100: 19.45 | H100: 11.05 | I100: 18.96 | J100: 13.9081 | K100: 0 | L100: 0 | M100: 0.0189 | N100: 19.6904 | O100: 2019 | P100: 13.12 | Q100: -0.3337
...

Sheet Analyst targets (now)
A1: ticker | B1: company | C1: currency | D1: current | E1: mean | F1: median | G1: low | H1: high
A2: 000408.SZ | B2: Zangge Mining Co Ltd | C2: CNY | D2: 71.46
A3: 1208.HK | B3: MMG Ltd | C3: HKD | D3: 8.545 | E3: 11.8078 | F3: 11.9926 | G3: 9.9925 | H3: 13.0044
A4: 1211.SR | B4: Saudi Arabian Mining Co (Maaden) | C4: SAR | D4: 62.1 | E4: 66.7 | F4: 66.2 | G4: 46 | H4: 80
A5: 2899.HK | B5: Zijin Mining Group Co Ltd | C5: HKD | D5: 32.5 | E5: 51.2647 | F5: 50.298 | G5: 43.5124 | H5: 61.2599
A6: AAL.L | B6: Anglo American plc | C6: GBp | D6: 4042 | E6: 4114.689 | F6: 4272.254 | G6: 2333.2515 | H6: 5321.736
A7: AEM | B7: Agnico Eagle Mines Ltd | C7: USD | D7: 194.48 | E7: 215.9636 | F7: 222.745 | G7: 87 | H7: 300
A8: B | B8: Barrick Mining Corp | C8: USD | D8: 42.88 | E8: 51.7044 | F8: 53.5 | G8: 29 | H8: 63
A9: BHP.AX | B9: BHP Group Ltd | C9: AUD | D9: 60.72 | E9: 60.3607 | F9: 63.0845 | G9: 43.0777 | H9: 68.7863
A10: EQX | B10: Equinox Gold Corp | C10: USD | D10: 11.94 | E10: 14 | F10: 14 | G10: 14 | H10: 14
A11: EVN.AX | B11: Evolution Mining Ltd | C11: AUD | D11: 13.71 | E11: 13.5412 | F11: 14.2 | G11: 4.8 | H11: 18
A12: FCX | B12: Freeport-McMoRan Inc | C12: USD | D12: 72.31 | E12: 72.4545 | F12: 76 | G12: 30 | H12: 85
A13: FMG.AX | B13: Fortescue Ltd | C13: AUD | D13: 16.37 | E13: 17.5212 | F13: 16.7831 | G13: 15.209 | H13: 22.3309
A14: FRES.L | B14: Fresnillo plc | C14: GBp | D14: 2890 | E14: 3297.0059 | F14: 2999.6711 | G14: 2231.8032 | H14: 4847.257
... A26: VALE3.SA | B26: Vale SA | C26: BRL | D26: 70.77 | E26: 88.7375 | F26: 86.2651 | G26: 65.238 | H26: 109.2415
A28: 12-month consensus price targets as of the data download date. Source: Yahoo Finance.
