Workbook

Sheet Entities
A1: entity | B1: listed_parent | C1: ticker | D1: exchange | E1: currency | F1: cross_check | G1: note
A2: iShares MSCI Global Metals & Mining Producers ETF | B2: iShares MSCI Global Metals & Mining Producers ETF | C2: PICK | D2: Cboe BZX | E2: USD | G2: ETF: no analyst price targets or revenue; tracks MSCI ACWI Select Metals & Mining Producers ex Gold & Silver IMI

Sheet Year-end close
A1: ticker | B1: company | C1: currency | D1: 2017 | E1: 2018 | F1: 2019 | G1: 2020 | H1: 2021 | I1: 2022 | J1: 2023 | K1: 2024 | L1: 2025 | M1: 2026
A2: PICK | B2: iShares MSCI Global Metals & Mining Producers ETF | C2: USD | D2: 34.63 | E2: 26.98 | F2: 29.73 | G2: 36.85 | H2: 42.62 | I2: 41 | J2: 43.07 | K2: 34.99 | L2: 51.34 | M2: 61.14
A4: Last close of each year, in the currency the stock trades in (GBp = pence). 2026 = latest close. Highlighted cells were corrected to the as-traded price; hover for Yahoo's rescaled figure.

Sheet Year-end close USD
A1: ticker | B1: company | C1: currency | D1: 2017 | E1: 2018 | F1: 2019 | G1: 2020 | H1: 2021 | I1: 2022 | J1: 2023 | K1: 2024 | L1: 2025 | M1: 2026
A2: PICK | B2: iShares MSCI Global Metals & Mining Producers ETF | C2: USD | D2: =IF('Year-end close'!D2="","",'Year-end close'!D2/IF('Year-end close'!$C2="GBp",100,1)/INDEX('FX year-end'!$B$2:$B$14,MATCH(IF('Year-end close'!$C2="GBp","GBP",'Year-end close'!$C2),'FX year-end'!$A$2:$A$14,0))) -> 34.63 | E2: =IF('Year-end close'!E2="","",'Year-end close'!E2/IF('Year-end close'!$C2="GBp",100,1)/INDEX('FX year-end'!$C$2:$C$14,MATCH(IF('Year-end close'!$C2="GBp","GBP",'Year-end close'!$C2),'FX year-end'!$A$2:$A$14,0))) -> 26.98 | F2: =IF('Year-end close'!F2="","",'Year-end close'!F2/IF('Year-end close'!$C2="GBp",100,1)/INDEX('FX year-end'!$D$2:$D$14,MATCH(IF('Year-end close'!$C2="GBp","GBP",'Year-end close'!$C2),'FX year-end'!$A$2:$A$14,0))) -> 29.73 | G2: =IF('Year-end close'!G2="","",'Year-end close'!G2/IF('Year-end close'!$C2="GBp",100,1)/INDEX('FX year-end'!$E$2:$E$14,MATCH(IF('Year-end close'!$C2="GBp","GBP",'Year-end close'!$C2),'FX year-end'!$A$2:$A$14,0))) -> 36.85 | H2: =IF('Year-end close'!H2="","",'Year-end close'!H2/IF('Year-end close'!$C2="GBp",100,1)/INDEX('FX year-end'!$F$2:$F$14,MATCH(IF('Year-end close'!$C2="GBp","GBP",'Year-end close'!$C2),'FX year-end'!$A$2:$A$14,0))) -> 42.62 | I2: =IF('Year-end close'!I2="","",'Year-end close'!I2/IF('Year-end close'!$C2="GBp",100,1)/INDEX('FX year-end'!$G$2:$G$14,MATCH(IF('Year-end close'!$C2="GBp","GBP",'Year-end close'!$C2),'FX year-end'!$A$2:$A$14,0))) -> 41 | J2: =IF('Year-end close'!J2="","",'Year-end close'!J2/IF('Year-end close'!$C2="GBp",100,1)/INDEX('FX year-end'!$H$2:$H$14,MATCH(IF('Year-end close'!$C2="GBp","GBP",'Year-end close'!$C2),'FX year-end'!$A$2:$A$14,0))) -> 43.07 | K2: =IF('Year-end close'!K2="","",'Year-end close'!K2/IF('Year-end close'!$C2="GBp",100,1)/INDEX('FX year-end'!$I$2:$I$14,MATCH(IF('Year-end close'!$C2="GBp","GBP",'Year-end close'!$C2),'FX year-end'!$A$2:$A$14,0))) -> 34.99 | L2: =IF('Year-end close'!L2="","",'Year-end close'!L2/IF('Year-end close'!$C2="GBp",100,1)/INDEX('FX year-end'!$J$2:$J$14,MATCH(IF('Year-end close'!$C2="GBp","GBP",'Year-end close'!$C2),'FX year-end'!$A$2:$A$14,0))) -> 51.34 | M2: =IF('Year-end close'!M2="","",'Year-end close'!M2/IF('Year-end close'!$C2="GBp",100,1)/INDEX('FX year-end'!$K$2:$K$14,MATCH(IF('Year-end close'!$C2="GBp","GBP",'Year-end close'!$C2),'FX year-end'!$A$2:$A$14,0))) -> 61.14
A4: Year-end close / year-end FX rate (pence divided by 100 first).

Sheet 2y forward
A1: ticker | B1: company | C1: currency | D1: 2019 | E1: 2020 | F1: 2021 | G1: 2022 | H1: 2023 | I1: 2024 | J1: 2025 | K1: 2026 | L1: 2027 | M1: 2028
A2: PICK | B2: iShares MSCI Global Metals & Mining Producers ETF | C2: USD | D2: =IF('Year-end close'!D2="","",'Year-end close'!D2*EXP((INDEX('Rates 2y'!$B$2:$B$14,MATCH(IF($C2="GBp","GBP",$C2),'Rates 2y'!$A$2:$A$14,0))-'Dividend yield'!D2)*2)) -> 34.270892 | E2: =IF('Year-end close'!E2="","",'Year-end close'!E2*EXP((INDEX('Rates 2y'!$C$2:$C$14,MATCH(IF($C2="GBp","GBP",$C2),'Rates 2y'!$A$2:$A$14,0))-'Dividend yield'!E2)*2)) -> 25.779145 | F2: =IF('Year-end close'!F2="","",'Year-end close'!F2*EXP((INDEX('Rates 2y'!$D$2:$D$14,MATCH(IF($C2="GBp","GBP",$C2),'Rates 2y'!$A$2:$A$14,0))-'Dividend yield'!F2)*2)) -> 27.482918 | G2: =IF('Year-end close'!G2="","",'Year-end close'!G2*EXP((INDEX('Rates 2y'!$E$2:$E$14,MATCH(IF($C2="GBp","GBP",$C2),'Rates 2y'!$A$2:$A$14,0))-'Dividend yield'!G2)*2)) -> 35.307013 | H2: =IF('Year-end close'!H2="","",'Year-end close'!H2*EXP((INDEX('Rates 2y'!$F$2:$F$14,MATCH(IF($C2="GBp","GBP",$C2),'Rates 2y'!$A$2:$A$14,0))-'Dividend yield'!H2)*2)) -> 38.441501 | I2: =IF('Year-end close'!I2="","",'Year-end close'!I2*EXP((INDEX('Rates 2y'!$G$2:$G$14,MATCH(IF($C2="GBp","GBP",$C2),'Rates 2y'!$A$2:$A$14,0))-'Dividend yield'!I2)*2)) -> 38.997209 | J2: =IF('Year-end close'!J2="","",'Year-end close'!J2*EXP((INDEX('Rates 2y'!$H$2:$H$14,MATCH(IF($C2="GBp","GBP",$C2),'Rates 2y'!$A$2:$A$14,0))-'Dividend yield'!J2)*2)) -> 43.118955 | K2: =IF('Year-end close'!K2="","",'Year-end close'!K2*EXP((INDEX('Rates 2y'!$I$2:$I$14,MATCH(IF($C2="GBp","GBP",$C2),'Rates 2y'!$A$2:$A$14,0))-'Dividend yield'!K2)*2)) -> 35.685995 | L2: =IF('Year-end close'!L2="","",'Year-end close'!L2*EXP((INDEX('Rates 2y'!$J$2:$J$14,MATCH(IF($C2="GBp","GBP",$C2),'Rates 2y'!$A$2:$A$14,0))-'Dividend yield'!L2)*2)) -> 51.964988 | M2: =IF('Year-end close'!M2="","",'Year-end close'!M2*EXP((INDEX('Rates 2y'!$K$2:$K$14,MATCH(IF($C2="GBp","GBP",$C2),'Rates 2y'!$A$2:$A$14,0))-'Dividend yield'!M2)*2)) -> 64.395021
A4: Price a 2-year future set at the end of (column year - 2) would have had: close x exp((2y rate - dividend yield) x 2). Carry only, not a forecast.

Sheet 2y forward USD
A1: ticker | B1: company | C1: currency | D1: 2019 | E1: 2020 | F1: 2021 | G1: 2022 | H1: 2023 | I1: 2024 | J1: 2025 | K1: 2026 | L1: 2027 | M1: 2028
A2: PICK | B2: iShares MSCI Global Metals & Mining Producers ETF | C2: USD | D2: =IF('2y forward'!D2="","",'2y forward'!D2/IF('2y forward'!$C2="GBp",100,1)/INDEX('FX 2y forward'!$B$2:$B$14,MATCH(IF('2y forward'!$C2="GBp","GBP",'2y forward'!$C2),'FX 2y forward'!$A$2:$A$14,0))) -> 34.270892 | E2: =IF('2y forward'!E2="","",'2y forward'!E2/IF('2y forward'!$C2="GBp",100,1)/INDEX('FX 2y forward'!$C$2:$C$14,MATCH(IF('2y forward'!$C2="GBp","GBP",'2y forward'!$C2),'FX 2y forward'!$A$2:$A$14,0))) -> 25.779145 | F2: =IF('2y forward'!F2="","",'2y forward'!F2/IF('2y forward'!$C2="GBp",100,1)/INDEX('FX 2y forward'!$D$2:$D$14,MATCH(IF('2y forward'!$C2="GBp","GBP",'2y forward'!$C2),'FX 2y forward'!$A$2:$A$14,0))) -> 27.482918 | G2: =IF('2y forward'!G2="","",'2y forward'!G2/IF('2y forward'!$C2="GBp",100,1)/INDEX('FX 2y forward'!$E$2:$E$14,MATCH(IF('2y forward'!$C2="GBp","GBP",'2y forward'!$C2),'FX 2y forward'!$A$2:$A$14,0))) -> 35.307013 | H2: =IF('2y forward'!H2="","",'2y forward'!H2/IF('2y forward'!$C2="GBp",100,1)/INDEX('FX 2y forward'!$F$2:$F$14,MATCH(IF('2y forward'!$C2="GBp","GBP",'2y forward'!$C2),'FX 2y forward'!$A$2:$A$14,0))) -> 38.441501 | I2: =IF('2y forward'!I2="","",'2y forward'!I2/IF('2y forward'!$C2="GBp",100,1)/INDEX('FX 2y forward'!$G$2:$G$14,MATCH(IF('2y forward'!$C2="GBp","GBP",'2y forward'!$C2),'FX 2y forward'!$A$2:$A$14,0))) -> 38.997209 | J2: =IF('2y forward'!J2="","",'2y forward'!J2/IF('2y forward'!$C2="GBp",100,1)/INDEX('FX 2y forward'!$H$2:$H$14,MATCH(IF('2y forward'!$C2="GBp","GBP",'2y forward'!$C2),'FX 2y forward'!$A$2:$A$14,0))) -> 43.118955 | K2: =IF('2y forward'!K2="","",'2y forward'!K2/IF('2y forward'!$C2="GBp",100,1)/INDEX('FX 2y forward'!$I$2:$I$14,MATCH(IF('2y forward'!$C2="GBp","GBP",'2y forward'!$C2),'FX 2y forward'!$A$2:$A$14,0))) -> 35.685995 | L2: =IF('2y forward'!L2="","",'2y forward'!L2/IF('2y forward'!$C2="GBp",100,1)/INDEX('FX 2y forward'!$J$2:$J$14,MATCH(IF('2y forward'!$C2="GBp","GBP",'2y forward'!$C2),'FX 2y forward'!$A$2:$A$14,0))) -> 51.964988 | M2: =IF('2y forward'!M2="","",'2y forward'!M2/IF('2y forward'!$C2="GBp",100,1)/INDEX('FX 2y forward'!$K$2:$K$14,MATCH(IF('2y forward'!$C2="GBp","GBP",'2y forward'!$C2),'FX 2y forward'!$A$2:$A$14,0))) -> 64.395021
A4: 2y forward (local) / 2-year FX forward from the 'FX 2y forward' tab.

Sheet Dividend yield
A1: ticker | B1: company | C1: currency | D1: 2017 | E1: 2018 | F1: 2019 | G1: 2020 | H1: 2021 | I1: 2022 | J1: 2023 | K1: 2024 | L1: 2025 | M1: 2026
A2: PICK | B2: iShares MSCI Global Metals & Mining Producers ETF | C2: USD | D2: 0.024112 | E2: 0.047665 | F2: 0.055096 | G2: 0.022687 | H2: 0.058893 | I2: 0.069341 | J2: 0.041932 | K2: 0.032552 | L2: 0.02875 | M2: 0.008865
A4: Dividends paid during the year / year-end close.

Sheet Rates 2y
A1: currency | B1: 2017 | C1: 2018 | D1: 2019 | E1: 2020 | F1: 2021 | G1: 2022 | H1: 2023 | I1: 2024 | J1: 2025 | K1: 2026
A2: USD | B2: 0.0189 | C2: 0.0249 | D2: 0.0158 | E2: 0.0013 | F2: 0.0073 | G2: 0.0443 | H2: 0.0425 | I2: 0.0424 | J2: 0.0348 | K2: 0.0348
A3: CAD | B3: 0.0169 | C3: 0.0186 | D3: 0.017 | E3: 0.002 | F3: 0.0095 | G3: 0.0405 | H3: 0.0388 | I3: 0.0293 | J3: 0.026 | K3: 0.026
A4: AUD | B4: 0.02 | C4: 0.019 | D4: 0.009 | E4: 0.001 | F4: 0.006 | G4: 0.035 | H4: 0.037 | I4: 0.0385 | J4: 0.039 | K4: 0.039
A5: GBP | B5: 0.0045 | C5: 0.0075 | D5: 0.0055 | E5: -0.0015 | F5: 0.007 | G5: 0.036 | H5: 0.04 | I5: 0.044 | J5: 0.0375 | K5: 0.0375
A6: MXN | B6: 0.076 | C6: 0.086 | D6: 0.069 | E6: 0.043 | F6: 0.072 | G6: 0.105 | H6: 0.103 | I6: 0.099 | J6: 0.073 | K6: 0.073
A7: BRL | B7: 0.075 | C7: 0.072 | D7: 0.053 | E7: 0.043 | F7: 0.113 | G7: 0.134 | H7: 0.103 | I7: 0.154 | J7: 0.139 | K7: 0.139
A8: SAR | B8: 0.02 | C8: 0.029 | D8: 0.023 | E8: 0.009 | F8: 0.012 | G8: 0.05 | H8: 0.054 | I8: 0.052 | J8: 0.046 | K8: 0.046
A9: HKD | B9: 0.013 | C9: 0.018 | D9: 0.017 | E9: 0.002 | F9: 0.006 | G9: 0.04 | H9: 0.036 | I9: 0.034 | J9: 0.026 | K9: 0.026
A10: CNY | B10: 0.035 | C10: 0.027 | D10: 0.026 | E10: 0.027 | F10: 0.023 | G10: 0.023 | H10: 0.022 | I10: 0.011 | J10: 0.014 | K10: 0.014
A11: IDR | B11: 0.058 | C11: 0.077 | D11: 0.057 | E11: 0.041 | F11: 0.039 | G11: 0.059 | H11: 0.064 | I11: 0.069 | J11: 0.05 | K11: 0.05
A12: ZAR | B12: 0.07 | C12: 0.073 | D12: 0.069 | E12: 0.045 | F12: 0.056 | G12: 0.08 | H12: 0.082 | I12: 0.076 | J12: 0.07 | K12: 0.07
A13: SEK | B13: -0.006 | C13: -0.005 | D13: -0.003 | E13: -0.003 | F13: 0.003 | G13: 0.027 | H13: 0.029 | I13: 0.02 | J13: 0.019 | K13: 0.019
A14: EUR | B14: -0.006 | C14: -0.006 | D14: -0.006 | E14: -0.007 | F14: -0.006 | G14: 0.0275 | H14: 0.024 | I14: 0.021 | J14: 0.021 | K14: 0.021
A16: Approximate year-end 2-year government bond yields (SAR: interbank proxy). Entered from memory, not from a data source: replace with exact figures if needed. 2026 repeats 2025.

Sheet FX year-end
A1: currency | B1: 2017 | C1: 2018 | D1: 2019 | E1: 2020 | F1: 2021 | G1: 2022 | H1: 2023 | I1: 2024 | J1: 2025 | K1: 2026
A2: USD | B2: 1 | C2: 1 | D2: 1 | E2: 1 | F2: 1 | G2: 1 | H2: 1 | I2: 1 | J2: 1 | K2: 1
A3: CAD | B3: 1.25655 | C3: 1.3622 | D3: 1.30606 | E3: 1.27507 | F3: 1.27444 | G3: 1.3552 | H3: 1.32296 | I3: 1.43498 | J3: 1.36947 | K3: 1.41538
A4: AUD | B4: 1.28299 | C4: 1.4195 | D4: 1.428286 | E4: 1.30051 | F4: 1.379348 | G4: 1.477978 | H4: 1.464922 | I4: 1.607717 | J4: 1.492983 | K4: 1.4255
A5: GBP | B5: 0.744 | C5: 0.7878 | D5: 0.7626 | E5: 0.73364 | F5: 0.74083 | G5: 0.82944 | H5: 0.7853 | I5: 0.79687 | J5: 0.742545 | K5: 0.75604
A6: MXN | B6: 19.65539 | C6: 19.64537 | D6: 18.9177 | E6: 19.8909 | F6: 20.459101 | G6: 19.4576 | H6: 16.9512 | I6: 20.6322 | J6: 17.9788 | K6: 17.740999
A7: BRL | B7: 3.3111 | C7: 3.8742 | D7: 4.015711 | E7: 5.190839 | F7: 5.5702 | G7: 5.2846 | H7: 4.8502 | I7: 6.1779 | J7: 5.4762 | K7: 5.1842
A8: SAR | B8: 3.7456 | C8: 3.7515 | D8: 3.74836 | E8: 3.747706 | F8: 3.749972 | G8: 3.754942 | H8: 3.745219 | I8: 3.751983 | J8: 3.7479 | K8: 3.7543
A9: HKD | B9: 7.8168 | C9: 7.8309 | D9: 7.7881 | E9: 7.75218 | F9: 7.79756 | G9: 7.7944 | H9: 7.8118 | I9: 7.7635 | J9: 7.78066 | K9: 7.84357
A10: CNY | B10: 6.5316 | C10: 6.8772 | D10: 6.9857 | E10: 6.5222 | F10: 6.3721 | G10: 6.9631 | H10: 7.107 | I10: 7.2981 | J10: 6.9961 | K10: 6.7037
A11: IDR | B11: 13558 | C11: 14553 | D11: 13919 | E11: 13832.56 | F11: 14285.2 | G11: 15620 | H11: 15425 | I11: 16085.6 | J11: 16709 | K11: 17912
A12: ZAR | B12: 12.3955 | C12: 14.4153 | D12: 14.09859 | E12: 14.6413 | F12: 15.8891 | G12: 16.920601 | H12: 18.567301 | I12: 18.7649 | J12: 16.58547 | K12: 16.3232
A13: SEK | B13: 8.24572 | C13: 8.9801 | D13: 9.34468 | E13: 8.18877 | F13: 9.04681 | G13: 10.4522 | H13: 9.97109 | I13: 11.02383 | J13: 9.19474 | K13: 9.9316
A14: EUR | B14: 0.8374 | C14: 0.87413 | D14: 0.892674 | E14: 0.813015 | F14: 0.883 | G14: 0.93802 | H14: 0.90349 | I14: 0.96097 | J14: 0.85126 | K14: 0.8786
A16: Units of currency per 1 USD at the last trading day of each year (2026: latest). Source: Yahoo Finance (CAD=X, GBP=X, ...).

Sheet FX 2y forward
A1: currency | B1: 2017->2019 | C1: 2018->2020 | D1: 2019->2021 | E1: 2020->2022 | F1: 2021->2023 | G1: 2022->2024 | H1: 2023->2025 | I1: 2024->2026 | J1: 2025->2027 | K1: 2026->2028
A2: USD | B2: ='FX year-end'!B2*EXP((INDEX('Rates 2y'!$B$2:$B$14,MATCH($A2,'Rates 2y'!$A$2:$A$14,0))-INDEX('Rates 2y'!$B$2:$B$14,MATCH("USD",'Rates 2y'!$A$2:$A$14,0)))*2) -> 1 | C2: ='FX year-end'!C2*EXP((INDEX('Rates 2y'!$C$2:$C$14,MATCH($A2,'Rates 2y'!$A$2:$A$14,0))-INDEX('Rates 2y'!$C$2:$C$14,MATCH("USD",'Rates 2y'!$A$2:$A$14,0)))*2) -> 1 | D2: ='FX year-end'!D2*EXP((INDEX('Rates 2y'!$D$2:$D$14,MATCH($A2,'Rates 2y'!$A$2:$A$14,0))-INDEX('Rates 2y'!$D$2:$D$14,MATCH("USD",'Rates 2y'!$A$2:$A$14,0)))*2) -> 1 | E2: ='FX year-end'!E2*EXP((INDEX('Rates 2y'!$E$2:$E$14,MATCH($A2,'Rates 2y'!$A$2:$A$14,0))-INDEX('Rates 2y'!$E$2:$E$14,MATCH("USD",'Rates 2y'!$A$2:$A$14,0)))*2) -> 1 | F2: ='FX year-end'!F2*EXP((INDEX('Rates 2y'!$F$2:$F$14,MATCH($A2,'Rates 2y'!$A$2:$A$14,0))-INDEX('Rates 2y'!$F$2:$F$14,MATCH("USD",'Rates 2y'!$A$2:$A$14,0)))*2) -> 1 | G2: ='FX year-end'!G2*EXP((INDEX('Rates 2y'!$G$2:$G$14,MATCH($A2,'Rates 2y'!$A$2:$A$14,0))-INDEX('Rates 2y'!$G$2:$G$14,MATCH("USD",'Rates 2y'!$A$2:$A$14,0)))*2) -> 1 | H2: ='FX year-end'!H2*EXP((INDEX('Rates 2y'!$H$2:$H$14,MATCH($A2,'Rates 2y'!$A$2:$A$14,0))-INDEX('Rates 2y'!$H$2:$H$14,MATCH("USD",'Rates 2y'!$A$2:$A$14,0)))*2) -> 1 | I2: ='FX year-end'!I2*EXP((INDEX('Rates 2y'!$I$2:$I$14,MATCH($A2,'Rates 2y'!$A$2:$A$14,0))-INDEX('Rates 2y'!$I$2:$I$14,MATCH("USD",'Rates 2y'!$A$2:$A$14,0)))*2) -> 1 | J2: ='FX year-end'!J2*EXP((INDEX('Rates 2y'!$J$2:$J$14,MATCH($A2,'Rates 2y'!$A$2:$A$14,0))-INDEX('Rates 2y'!$J$2:$J$14,MATCH("USD",'Rates 2y'!$A$2:$A$14,0)))*2) -> 1 | K2: ='FX year-end'!K2*EXP((INDEX('Rates 2y'!$K$2:$K$14,MATCH($A2,'Rates 2y'!$A$2:$A$14,0))-INDEX('Rates 2y'!$K$2:$K$14,MATCH("USD",'Rates 2y'!$A$2:$A$14,0)))*2) -> 1
A3: CAD | B3: ='FX year-end'!B3*EXP((INDEX('Rates 2y'!$B$2:$B$14,MATCH($A3,'Rates 2y'!$A$2:$A$14,0))-INDEX('Rates 2y'!$B$2:$B$14,MATCH("USD",'Rates 2y'!$A$2:$A$14,0)))*2) -> 1.2515338 | C3: ='FX year-end'!C3*EXP((INDEX('Rates 2y'!$C$2:$C$14,MATCH($A3,'Rates 2y'!$A$2:$A$14,0))-INDEX('Rates 2y'!$C$2:$C$14,MATCH("USD",'Rates 2y'!$A$2:$A$14,0)))*2) -> 1.345144 | D3: ='FX year-end'!D3*EXP((INDEX('Rates 2y'!$D$2:$D$14,MATCH($A3,'Rates 2y'!$A$2:$A$14,0))-INDEX('Rates 2y'!$D$2:$D$14,MATCH("USD",'Rates 2y'!$A$2:$A$14,0)))*2) -> 1.3091983 | E3: ='FX year-end'!E3*EXP((INDEX('Rates 2y'!$E$2:$E$14,MATCH($A3,'Rates 2y'!$A$2:$A$14,0))-INDEX('Rates 2y'!$E$2:$E$14,MATCH("USD",'Rates 2y'!$A$2:$A$14,0)))*2) -> 1.2768563 | F3: ='FX year-end'!F3*EXP((INDEX('Rates 2y'!$F$2:$F$14,MATCH($A3,'Rates 2y'!$A$2:$A$14,0))-INDEX('Rates 2y'!$F$2:$F$14,MATCH("USD",'Rates 2y'!$A$2:$A$14,0)))*2) -> 1.2800599 | G3: ='FX year-end'!G3*EXP((INDEX('Rates 2y'!$G$2:$G$14,MATCH($A3,'Rates 2y'!$A$2:$A$14,0))-INDEX('Rates 2y'!$G$2:$G$14,MATCH("USD",'Rates 2y'!$A$2:$A$14,0)))*2) -> 1.3449395 | H3: ='FX year-end'!H3*EXP((INDEX('Rates 2y'!$H$2:$H$14,MATCH($A3,'Rates 2y'!$A$2:$A$14,0))-INDEX('Rates 2y'!$H$2:$H$14,MATCH("USD",'Rates 2y'!$A$2:$A$14,0)))*2) -> 1.3132062 | I3: ='FX year-end'!I3*EXP((INDEX('Rates 2y'!$I$2:$I$14,MATCH($A3,'Rates 2y'!$A$2:$A$14,0))-INDEX('Rates 2y'!$I$2:$I$14,MATCH("USD",'Rates 2y'!$A$2:$A$14,0)))*2) -> 1.3978718 | J3: ='FX year-end'!J3*EXP((INDEX('Rates 2y'!$J$2:$J$14,MATCH($A3,'Rates 2y'!$A$2:$A$14,0))-INDEX('Rates 2y'!$J$2:$J$14,MATCH("USD",'Rates 2y'!$A$2:$A$14,0)))*2) -> 1.3455782 | K3: ='FX year-end'!K3*EXP((INDEX('Rates 2y'!$K$2:$K$14,MATCH($A3,'Rates 2y'!$A$2:$A$14,0))-INDEX('Rates 2y'!$K$2:$K$14,MATCH("USD",'Rates 2y'!$A$2:$A$14,0)))*2) -> 1.3906872
A4: AUD | B4: ='FX year-end'!B4*EXP((INDEX('Rates 2y'!$B$2:$B$14,MATCH($A4,'Rates 2y'!$A$2:$A$14,0))-INDEX('Rates 2y'!$B$2:$B$14,MATCH("USD",'Rates 2y'!$A$2:$A$14,0)))*2) -> 1.2858157 | C4: ='FX year-end'!C4*EXP((INDEX('Rates 2y'!$C$2:$C$14,MATCH($A4,'Rates 2y'!$A$2:$A$14,0))-INDEX('Rates 2y'!$C$2:$C$14,MATCH("USD",'Rates 2y'!$A$2:$A$14,0)))*2) -> 1.4028483 | D4: ='FX year-end'!D4*EXP((INDEX('Rates 2y'!$D$2:$D$14,MATCH($A4,'Rates 2y'!$A$2:$A$14,0))-INDEX('Rates 2y'!$D$2:$D$14,MATCH("USD",'Rates 2y'!$A$2:$A$14,0)))*2) -> 1.4089928 | E4: ='FX year-end'!E4*EXP((INDEX('Rates 2y'!$E$2:$E$14,MATCH($A4,'Rates 2y'!$A$2:$A$14,0))-INDEX('Rates 2y'!$E$2:$E$14,MATCH("USD",'Rates 2y'!$A$2:$A$14,0)))*2) -> 1.2997299 | F4: ='FX year-end'!F4*EXP((INDEX('Rates 2y'!$F$2:$F$14,MATCH($A4,'Rates 2y'!$A$2:$A$14,0))-INDEX('Rates 2y'!$F$2:$F$14,MATCH("USD",'Rates 2y'!$A$2:$A$14,0)))*2) -> 1.3757664 | G4: ='FX year-end'!G4*EXP((INDEX('Rates 2y'!$G$2:$G$14,MATCH($A4,'Rates 2y'!$A$2:$A$14,0))-INDEX('Rates 2y'!$G$2:$G$14,MATCH("USD",'Rates 2y'!$A$2:$A$14,0)))*2) -> 1.4507417 | H4: ='FX year-end'!H4*EXP((INDEX('Rates 2y'!$H$2:$H$14,MATCH($A4,'Rates 2y'!$A$2:$A$14,0))-INDEX('Rates 2y'!$H$2:$H$14,MATCH("USD",'Rates 2y'!$A$2:$A$14,0)))*2) -> 1.4488962 | I4: ='FX year-end'!I4*EXP((INDEX('Rates 2y'!$I$2:$I$14,MATCH($A4,'Rates 2y'!$A$2:$A$14,0))-INDEX('Rates 2y'!$I$2:$I$14,MATCH("USD",'Rates 2y'!$A$2:$A$14,0)))*2) -> 1.5952256 | J4: ='FX year-end'!J4*EXP((INDEX('Rates 2y'!$J$2:$J$14,MATCH($A4,'Rates 2y'!$A$2:$A$14,0))-INDEX('Rates 2y'!$J$2:$J$14,MATCH("USD",'Rates 2y'!$A$2:$A$14,0)))*2) -> 1.5055769 | K4: ='FX year-end'!K4*EXP((INDEX('Rates 2y'!$K$2:$K$14,MATCH($A4,'Rates 2y'!$A$2:$A$14,0))-INDEX('Rates 2y'!$K$2:$K$14,MATCH("USD",'Rates 2y'!$A$2:$A$14,0)))*2) -> 1.4375246
A5: GBP | B5: ='FX year-end'!B5*EXP((INDEX('Rates 2y'!$B$2:$B$14,MATCH($A5,'Rates 2y'!$A$2:$A$14,0))-INDEX('Rates 2y'!$B$2:$B$14,MATCH("USD",'Rates 2y'!$A$2:$A$14,0)))*2) -> 0.72287841 | C5: ='FX year-end'!C5*EXP((INDEX('Rates 2y'!$C$2:$C$14,MATCH($A5,'Rates 2y'!$A$2:$A$14,0))-INDEX('Rates 2y'!$C$2:$C$14,MATCH("USD",'Rates 2y'!$A$2:$A$14,0)))*2) -> 0.7608561 | D5: ='FX year-end'!D5*EXP((INDEX('Rates 2y'!$D$2:$D$14,MATCH($A5,'Rates 2y'!$A$2:$A$14,0))-INDEX('Rates 2y'!$D$2:$D$14,MATCH("USD",'Rates 2y'!$A$2:$A$14,0)))*2) -> 0.74705114 | E5: ='FX year-end'!E5*EXP((INDEX('Rates 2y'!$E$2:$E$14,MATCH($A5,'Rates 2y'!$A$2:$A$14,0))-INDEX('Rates 2y'!$E$2:$E$14,MATCH("USD",'Rates 2y'!$A$2:$A$14,0)))*2) -> 0.7295431 | F5: ='FX year-end'!F5*EXP((INDEX('Rates 2y'!$F$2:$F$14,MATCH($A5,'Rates 2y'!$A$2:$A$14,0))-INDEX('Rates 2y'!$F$2:$F$14,MATCH("USD",'Rates 2y'!$A$2:$A$14,0)))*2) -> 0.74038564 | G5: ='FX year-end'!G5*EXP((INDEX('Rates 2y'!$G$2:$G$14,MATCH($A5,'Rates 2y'!$A$2:$A$14,0))-INDEX('Rates 2y'!$G$2:$G$14,MATCH("USD",'Rates 2y'!$A$2:$A$14,0)))*2) -> 0.81578495 | H5: ='FX year-end'!H5*EXP((INDEX('Rates 2y'!$H$2:$H$14,MATCH($A5,'Rates 2y'!$A$2:$A$14,0))-INDEX('Rates 2y'!$H$2:$H$14,MATCH("USD",'Rates 2y'!$A$2:$A$14,0)))*2) -> 0.7813833 | I5: ='FX year-end'!I5*EXP((INDEX('Rates 2y'!$I$2:$I$14,MATCH($A5,'Rates 2y'!$A$2:$A$14,0))-INDEX('Rates 2y'!$I$2:$I$14,MATCH("USD",'Rates 2y'!$A$2:$A$14,0)))*2) -> 0.79942407 | J5: ='FX year-end'!J5*EXP((INDEX('Rates 2y'!$J$2:$J$14,MATCH($A5,'Rates 2y'!$A$2:$A$14,0))-INDEX('Rates 2y'!$J$2:$J$14,MATCH("USD",'Rates 2y'!$A$2:$A$14,0)))*2) -> 0.74656559 | K5: ='FX year-end'!K5*EXP((INDEX('Rates 2y'!$K$2:$K$14,MATCH($A5,'Rates 2y'!$A$2:$A$14,0))-INDEX('Rates 2y'!$K$2:$K$14,MATCH("USD",'Rates 2y'!$A$2:$A$14,0)))*2) -> 0.76013366
A6: MXN | B6: ='FX year-end'!B6*EXP((INDEX('Rates 2y'!$B$2:$B$14,MATCH($A6,'Rates 2y'!$A$2:$A$14,0))-INDEX('Rates 2y'!$B$2:$B$14,MATCH("USD",'Rates 2y'!$A$2:$A$14,0)))*2) -> 22.033226 | C6: ='FX year-end'!C6*EXP((INDEX('Rates 2y'!$C$2:$C$14,MATCH($A6,'Rates 2y'!$A$2:$A$14,0))-INDEX('Rates 2y'!$C$2:$C$14,MATCH("USD",'Rates 2y'!$A$2:$A$14,0)))*2) -> 22.198877 | D6: ='FX year-end'!D6*EXP((INDEX('Rates 2y'!$D$2:$D$14,MATCH($A6,'Rates 2y'!$A$2:$A$14,0))-INDEX('Rates 2y'!$D$2:$D$14,MATCH("USD",'Rates 2y'!$A$2:$A$14,0)))*2) -> 21.041528 | E6: ='FX year-end'!E6*EXP((INDEX('Rates 2y'!$E$2:$E$14,MATCH($A6,'Rates 2y'!$A$2:$A$14,0))-INDEX('Rates 2y'!$E$2:$E$14,MATCH("USD",'Rates 2y'!$A$2:$A$14,0)))*2) -> 21.620941 | F6: ='FX year-end'!F6*EXP((INDEX('Rates 2y'!$F$2:$F$14,MATCH($A6,'Rates 2y'!$A$2:$A$14,0))-INDEX('Rates 2y'!$F$2:$F$14,MATCH("USD",'Rates 2y'!$A$2:$A$14,0)))*2) -> 23.285429 | G6: ='FX year-end'!G6*EXP((INDEX('Rates 2y'!$G$2:$G$14,MATCH($A6,'Rates 2y'!$A$2:$A$14,0))-INDEX('Rates 2y'!$G$2:$G$14,MATCH("USD",'Rates 2y'!$A$2:$A$14,0)))*2) -> 21.969118 | H6: ='FX year-end'!H6*EXP((INDEX('Rates 2y'!$H$2:$H$14,MATCH($A6,'Rates 2y'!$A$2:$A$14,0))-INDEX('Rates 2y'!$H$2:$H$14,MATCH("USD",'Rates 2y'!$A$2:$A$14,0)))*2) -> 19.131547 | I6: ='FX year-end'!I6*EXP((INDEX('Rates 2y'!$I$2:$I$14,MATCH($A6,'Rates 2y'!$A$2:$A$14,0))-INDEX('Rates 2y'!$I$2:$I$14,MATCH("USD",'Rates 2y'!$A$2:$A$14,0)))*2) -> 23.105091 | J6: ='FX year-end'!J6*EXP((INDEX('Rates 2y'!$J$2:$J$14,MATCH($A6,'Rates 2y'!$A$2:$A$14,0))-INDEX('Rates 2y'!$J$2:$J$14,MATCH("USD",'Rates 2y'!$A$2:$A$14,0)))*2) -> 19.406213 | K6: ='FX year-end'!K6*EXP((INDEX('Rates 2y'!$K$2:$K$14,MATCH($A6,'Rates 2y'!$A$2:$A$14,0))-INDEX('Rates 2y'!$K$2:$K$14,MATCH("USD",'Rates 2y'!$A$2:$A$14,0)))*2) -> 19.149532
A7: BRL | B7: ='FX year-end'!B7*EXP((INDEX('Rates 2y'!$B$2:$B$14,MATCH($A7,'Rates 2y'!$A$2:$A$14,0))-INDEX('Rates 2y'!$B$2:$B$14,MATCH("USD",'Rates 2y'!$A$2:$A$14,0)))*2) -> 3.7042487 | C7: ='FX year-end'!C7*EXP((INDEX('Rates 2y'!$C$2:$C$14,MATCH($A7,'Rates 2y'!$A$2:$A$14,0))-INDEX('Rates 2y'!$C$2:$C$14,MATCH("USD",'Rates 2y'!$A$2:$A$14,0)))*2) -> 4.2568915 | D7: ='FX year-end'!D7*EXP((INDEX('Rates 2y'!$D$2:$D$14,MATCH($A7,'Rates 2y'!$A$2:$A$14,0))-INDEX('Rates 2y'!$D$2:$D$14,MATCH("USD",'Rates 2y'!$A$2:$A$14,0)))*2) -> 4.3258749 | E7: ='FX year-end'!E7*EXP((INDEX('Rates 2y'!$E$2:$E$14,MATCH($A7,'Rates 2y'!$A$2:$A$14,0))-INDEX('Rates 2y'!$E$2:$E$14,MATCH("USD",'Rates 2y'!$A$2:$A$14,0)))*2) -> 5.6423201 | F7: ='FX year-end'!F7*EXP((INDEX('Rates 2y'!$F$2:$F$14,MATCH($A7,'Rates 2y'!$A$2:$A$14,0))-INDEX('Rates 2y'!$F$2:$F$14,MATCH("USD",'Rates 2y'!$A$2:$A$14,0)))*2) -> 6.8814608 | G7: ='FX year-end'!G7*EXP((INDEX('Rates 2y'!$G$2:$G$14,MATCH($A7,'Rates 2y'!$A$2:$A$14,0))-INDEX('Rates 2y'!$G$2:$G$14,MATCH("USD",'Rates 2y'!$A$2:$A$14,0)))*2) -> 6.3230199 | H7: ='FX year-end'!H7*EXP((INDEX('Rates 2y'!$H$2:$H$14,MATCH($A7,'Rates 2y'!$A$2:$A$14,0))-INDEX('Rates 2y'!$H$2:$H$14,MATCH("USD",'Rates 2y'!$A$2:$A$14,0)))*2) -> 5.4740565 | I7: ='FX year-end'!I7*EXP((INDEX('Rates 2y'!$I$2:$I$14,MATCH($A7,'Rates 2y'!$A$2:$A$14,0))-INDEX('Rates 2y'!$I$2:$I$14,MATCH("USD",'Rates 2y'!$A$2:$A$14,0)))*2) -> 7.7228109 | J7: ='FX year-end'!J7*EXP((INDEX('Rates 2y'!$J$2:$J$14,MATCH($A7,'Rates 2y'!$A$2:$A$14,0))-INDEX('Rates 2y'!$J$2:$J$14,MATCH("USD",'Rates 2y'!$A$2:$A$14,0)))*2) -> 6.745067 | K7: ='FX year-end'!K7*EXP((INDEX('Rates 2y'!$K$2:$K$14,MATCH($A7,'Rates 2y'!$A$2:$A$14,0))-INDEX('Rates 2y'!$K$2:$K$14,MATCH("USD",'Rates 2y'!$A$2:$A$14,0)))*2) -> 6.385409
A8: SAR | B8: ='FX year-end'!B8*EXP((INDEX('Rates 2y'!$B$2:$B$14,MATCH($A8,'Rates 2y'!$A$2:$A$14,0))-INDEX('Rates 2y'!$B$2:$B$14,MATCH("USD",'Rates 2y'!$A$2:$A$14,0)))*2) -> 3.7538494 | C8: ='FX year-end'!C8*EXP((INDEX('Rates 2y'!$C$2:$C$14,MATCH($A8,'Rates 2y'!$A$2:$A$14,0))-INDEX('Rates 2y'!$C$2:$C$14,MATCH("USD",'Rates 2y'!$A$2:$A$14,0)))*2) -> 3.7823888 | D8: ='FX year-end'!D8*EXP((INDEX('Rates 2y'!$D$2:$D$14,MATCH($A8,'Rates 2y'!$A$2:$A$14,0))-INDEX('Rates 2y'!$D$2:$D$14,MATCH("USD",'Rates 2y'!$A$2:$A$14,0)))*2) -> 3.8027269 | E8: ='FX year-end'!E8*EXP((INDEX('Rates 2y'!$E$2:$E$14,MATCH($A8,'Rates 2y'!$A$2:$A$14,0))-INDEX('Rates 2y'!$E$2:$E$14,MATCH("USD",'Rates 2y'!$A$2:$A$14,0)))*2) -> 3.8058674 | F8: ='FX year-end'!F8*EXP((INDEX('Rates 2y'!$F$2:$F$14,MATCH($A8,'Rates 2y'!$A$2:$A$14,0))-INDEX('Rates 2y'!$F$2:$F$14,MATCH("USD",'Rates 2y'!$A$2:$A$14,0)))*2) -> 3.7853879 | G8: ='FX year-end'!G8*EXP((INDEX('Rates 2y'!$G$2:$G$14,MATCH($A8,'Rates 2y'!$A$2:$A$14,0))-INDEX('Rates 2y'!$G$2:$G$14,MATCH("USD",'Rates 2y'!$A$2:$A$14,0)))*2) -> 3.7979933 | H8: ='FX year-end'!H8*EXP((INDEX('Rates 2y'!$H$2:$H$14,MATCH($A8,'Rates 2y'!$A$2:$A$14,0))-INDEX('Rates 2y'!$H$2:$H$14,MATCH("USD",'Rates 2y'!$A$2:$A$14,0)))*2) -> 3.8323573 | I8: ='FX year-end'!I8*EXP((INDEX('Rates 2y'!$I$2:$I$14,MATCH($A8,'Rates 2y'!$A$2:$A$14,0))-INDEX('Rates 2y'!$I$2:$I$14,MATCH("USD",'Rates 2y'!$A$2:$A$14,0)))*2) -> 3.8247171 | J8: ='FX year-end'!J8*EXP((INDEX('Rates 2y'!$J$2:$J$14,MATCH($A8,'Rates 2y'!$A$2:$A$14,0))-INDEX('Rates 2y'!$J$2:$J$14,MATCH("USD",'Rates 2y'!$A$2:$A$14,0)))*2) -> 3.8328003 | K8: ='FX year-end'!K8*EXP((INDEX('Rates 2y'!$K$2:$K$14,MATCH($A8,'Rates 2y'!$A$2:$A$14,0))-INDEX('Rates 2y'!$K$2:$K$14,MATCH("USD",'Rates 2y'!$A$2:$A$14,0)))*2) -> 3.8393453
A9: HKD | B9: ='FX year-end'!B9*EXP((INDEX('Rates 2y'!$B$2:$B$14,MATCH($A9,'Rates 2y'!$A$2:$A$14,0))-INDEX('Rates 2y'!$B$2:$B$14,MATCH("USD",'Rates 2y'!$A$2:$A$14,0)))*2) -> 7.7251038 | C9: ='FX year-end'!C9*EXP((INDEX('Rates 2y'!$C$2:$C$14,MATCH($A9,'Rates 2y'!$A$2:$A$14,0))-INDEX('Rates 2y'!$C$2:$C$14,MATCH("USD",'Rates 2y'!$A$2:$A$14,0)))*2) -> 7.7235758 | D9: ='FX year-end'!D9*EXP((INDEX('Rates 2y'!$D$2:$D$14,MATCH($A9,'Rates 2y'!$A$2:$A$14,0))-INDEX('Rates 2y'!$D$2:$D$14,MATCH("USD",'Rates 2y'!$A$2:$A$14,0)))*2) -> 7.8068139 | E9: ='FX year-end'!E9*EXP((INDEX('Rates 2y'!$E$2:$E$14,MATCH($A9,'Rates 2y'!$A$2:$A$14,0))-INDEX('Rates 2y'!$E$2:$E$14,MATCH("USD",'Rates 2y'!$A$2:$A$14,0)))*2) -> 7.7630407 | F9: ='FX year-end'!F9*EXP((INDEX('Rates 2y'!$F$2:$F$14,MATCH($A9,'Rates 2y'!$A$2:$A$14,0))-INDEX('Rates 2y'!$F$2:$F$14,MATCH("USD",'Rates 2y'!$A$2:$A$14,0)))*2) -> 7.7773127 | G9: ='FX year-end'!G9*EXP((INDEX('Rates 2y'!$G$2:$G$14,MATCH($A9,'Rates 2y'!$A$2:$A$14,0))-INDEX('Rates 2y'!$G$2:$G$14,MATCH("USD",'Rates 2y'!$A$2:$A$14,0)))*2) -> 7.7276556 | H9: ='FX year-end'!H9*EXP((INDEX('Rates 2y'!$H$2:$H$14,MATCH($A9,'Rates 2y'!$A$2:$A$14,0))-INDEX('Rates 2y'!$H$2:$H$14,MATCH("USD",'Rates 2y'!$A$2:$A$14,0)))*2) -> 7.7109038 | I9: ='FX year-end'!I9*EXP((INDEX('Rates 2y'!$I$2:$I$14,MATCH($A9,'Rates 2y'!$A$2:$A$14,0))-INDEX('Rates 2y'!$I$2:$I$14,MATCH("USD",'Rates 2y'!$A$2:$A$14,0)))*2) -> 7.6341627 | J9: ='FX year-end'!J9*EXP((INDEX('Rates 2y'!$J$2:$J$14,MATCH($A9,'Rates 2y'!$A$2:$A$14,0))-INDEX('Rates 2y'!$J$2:$J$14,MATCH("USD",'Rates 2y'!$A$2:$A$14,0)))*2) -> 7.6449184 | K9: ='FX year-end'!K9*EXP((INDEX('Rates 2y'!$K$2:$K$14,MATCH($A9,'Rates 2y'!$A$2:$A$14,0))-INDEX('Rates 2y'!$K$2:$K$14,MATCH("USD",'Rates 2y'!$A$2:$A$14,0)))*2) -> 7.7067309
A10: CNY | B10: ='FX year-end'!B10*EXP((INDEX('Rates 2y'!$B$2:$B$14,MATCH($A10,'Rates 2y'!$A$2:$A$14,0))-INDEX('Rates 2y'!$B$2:$B$14,MATCH("USD",'Rates 2y'!$A$2:$A$14,0)))*2) -> 6.7453403 | C10: ='FX year-end'!C10*EXP((INDEX('Rates 2y'!$C$2:$C$14,MATCH($A10,'Rates 2y'!$A$2:$A$14,0))-INDEX('Rates 2y'!$C$2:$C$14,MATCH("USD",'Rates 2y'!$A$2:$A$14,0)))*2) -> 6.906145 | D10: ='FX year-end'!D10*EXP((INDEX('Rates 2y'!$D$2:$D$14,MATCH($A10,'Rates 2y'!$A$2:$A$14,0))-INDEX('Rates 2y'!$D$2:$D$14,MATCH("USD",'Rates 2y'!$A$2:$A$14,0)))*2) -> 7.1296718 | E10: ='FX year-end'!E10*EXP((INDEX('Rates 2y'!$E$2:$E$14,MATCH($A10,'Rates 2y'!$A$2:$A$14,0))-INDEX('Rates 2y'!$E$2:$E$14,MATCH("USD",'Rates 2y'!$A$2:$A$14,0)))*2) -> 6.8662063 | F10: ='FX year-end'!F10*EXP((INDEX('Rates 2y'!$F$2:$F$14,MATCH($A10,'Rates 2y'!$A$2:$A$14,0))-INDEX('Rates 2y'!$F$2:$F$14,MATCH("USD",'Rates 2y'!$A$2:$A$14,0)))*2) -> 6.5753584 | G10: ='FX year-end'!G10*EXP((INDEX('Rates 2y'!$G$2:$G$14,MATCH($A10,'Rates 2y'!$A$2:$A$14,0))-INDEX('Rates 2y'!$G$2:$G$14,MATCH("USD",'Rates 2y'!$A$2:$A$14,0)))*2) -> 6.6727013 | H10: ='FX year-end'!H10*EXP((INDEX('Rates 2y'!$H$2:$H$14,MATCH($A10,'Rates 2y'!$A$2:$A$14,0))-INDEX('Rates 2y'!$H$2:$H$14,MATCH("USD",'Rates 2y'!$A$2:$A$14,0)))*2) -> 6.8215056 | I10: ='FX year-end'!I10*EXP((INDEX('Rates 2y'!$I$2:$I$14,MATCH($A10,'Rates 2y'!$A$2:$A$14,0))-INDEX('Rates 2y'!$I$2:$I$14,MATCH("USD",'Rates 2y'!$A$2:$A$14,0)))*2) -> 6.853874 | J10: ='FX year-end'!J10*EXP((INDEX('Rates 2y'!$J$2:$J$14,MATCH($A10,'Rates 2y'!$A$2:$A$14,0))-INDEX('Rates 2y'!$J$2:$J$14,MATCH("USD",'Rates 2y'!$A$2:$A$14,0)))*2) -> 6.7110327 | K10: ='FX year-end'!K10*EXP((INDEX('Rates 2y'!$K$2:$K$14,MATCH($A10,'Rates 2y'!$A$2:$A$14,0))-INDEX('Rates 2y'!$K$2:$K$14,MATCH("USD",'Rates 2y'!$A$2:$A$14,0)))*2) -> 6.4305471
A11: IDR | B11: ='FX year-end'!B11*EXP((INDEX('Rates 2y'!$B$2:$B$14,MATCH($A11,'Rates 2y'!$A$2:$A$14,0))-INDEX('Rates 2y'!$B$2:$B$14,MATCH("USD",'Rates 2y'!$A$2:$A$14,0)))*2) -> 14660.793 | C11: ='FX year-end'!C11*EXP((INDEX('Rates 2y'!$C$2:$C$14,MATCH($A11,'Rates 2y'!$A$2:$A$14,0))-INDEX('Rates 2y'!$C$2:$C$14,MATCH("USD",'Rates 2y'!$A$2:$A$14,0)))*2) -> 16151.245 | D11: ='FX year-end'!D11*EXP((INDEX('Rates 2y'!$D$2:$D$14,MATCH($A11,'Rates 2y'!$A$2:$A$14,0))-INDEX('Rates 2y'!$D$2:$D$14,MATCH("USD",'Rates 2y'!$A$2:$A$14,0)))*2) -> 15114.504 | E11: ='FX year-end'!E11*EXP((INDEX('Rates 2y'!$E$2:$E$14,MATCH($A11,'Rates 2y'!$A$2:$A$14,0))-INDEX('Rates 2y'!$E$2:$E$14,MATCH("USD",'Rates 2y'!$A$2:$A$14,0)))*2) -> 14975.645 | F11: ='FX year-end'!F11*EXP((INDEX('Rates 2y'!$F$2:$F$14,MATCH($A11,'Rates 2y'!$A$2:$A$14,0))-INDEX('Rates 2y'!$F$2:$F$14,MATCH("USD",'Rates 2y'!$A$2:$A$14,0)))*2) -> 15220.208 | G11: ='FX year-end'!G11*EXP((INDEX('Rates 2y'!$G$2:$G$14,MATCH($A11,'Rates 2y'!$A$2:$A$14,0))-INDEX('Rates 2y'!$G$2:$G$14,MATCH("USD",'Rates 2y'!$A$2:$A$14,0)))*2) -> 16086.045 | H11: ='FX year-end'!H11*EXP((INDEX('Rates 2y'!$H$2:$H$14,MATCH($A11,'Rates 2y'!$A$2:$A$14,0))-INDEX('Rates 2y'!$H$2:$H$14,MATCH("USD",'Rates 2y'!$A$2:$A$14,0)))*2) -> 16102.742 | I11: ='FX year-end'!I11*EXP((INDEX('Rates 2y'!$I$2:$I$14,MATCH($A11,'Rates 2y'!$A$2:$A$14,0))-INDEX('Rates 2y'!$I$2:$I$14,MATCH("USD",'Rates 2y'!$A$2:$A$14,0)))*2) -> 16964.526 | J11: ='FX year-end'!J11*EXP((INDEX('Rates 2y'!$J$2:$J$14,MATCH($A11,'Rates 2y'!$A$2:$A$14,0))-INDEX('Rates 2y'!$J$2:$J$14,MATCH("USD",'Rates 2y'!$A$2:$A$14,0)))*2) -> 17224.753 | K11: ='FX year-end'!K11*EXP((INDEX('Rates 2y'!$K$2:$K$14,MATCH($A11,'Rates 2y'!$A$2:$A$14,0))-INDEX('Rates 2y'!$K$2:$K$14,MATCH("USD",'Rates 2y'!$A$2:$A$14,0)))*2) -> 18464.886
A12: ZAR | B12: ='FX year-end'!B12*EXP((INDEX('Rates 2y'!$B$2:$B$14,MATCH($A12,'Rates 2y'!$A$2:$A$14,0))-INDEX('Rates 2y'!$B$2:$B$14,MATCH("USD",'Rates 2y'!$A$2:$A$14,0)))*2) -> 13.729317 | C12: ='FX year-end'!C12*EXP((INDEX('Rates 2y'!$C$2:$C$14,MATCH($A12,'Rates 2y'!$A$2:$A$14,0))-INDEX('Rates 2y'!$C$2:$C$14,MATCH("USD",'Rates 2y'!$A$2:$A$14,0)))*2) -> 15.870946 | D12: ='FX year-end'!D12*EXP((INDEX('Rates 2y'!$D$2:$D$14,MATCH($A12,'Rates 2y'!$A$2:$A$14,0))-INDEX('Rates 2y'!$D$2:$D$14,MATCH("USD",'Rates 2y'!$A$2:$A$14,0)))*2) -> 15.681392 | E12: ='FX year-end'!E12*EXP((INDEX('Rates 2y'!$E$2:$E$14,MATCH($A12,'Rates 2y'!$A$2:$A$14,0))-INDEX('Rates 2y'!$E$2:$E$14,MATCH("USD",'Rates 2y'!$A$2:$A$14,0)))*2) -> 15.978536 | F12: ='FX year-end'!F12*EXP((INDEX('Rates 2y'!$F$2:$F$14,MATCH($A12,'Rates 2y'!$A$2:$A$14,0))-INDEX('Rates 2y'!$F$2:$F$14,MATCH("USD",'Rates 2y'!$A$2:$A$14,0)))*2) -> 17.514574 | G12: ='FX year-end'!G12*EXP((INDEX('Rates 2y'!$G$2:$G$14,MATCH($A12,'Rates 2y'!$A$2:$A$14,0))-INDEX('Rates 2y'!$G$2:$G$14,MATCH("USD",'Rates 2y'!$A$2:$A$14,0)))*2) -> 18.172907 | H12: ='FX year-end'!H12*EXP((INDEX('Rates 2y'!$H$2:$H$14,MATCH($A12,'Rates 2y'!$A$2:$A$14,0))-INDEX('Rates 2y'!$H$2:$H$14,MATCH("USD",'Rates 2y'!$A$2:$A$14,0)))*2) -> 20.093613 | I12: ='FX year-end'!I12*EXP((INDEX('Rates 2y'!$I$2:$I$14,MATCH($A12,'Rates 2y'!$A$2:$A$14,0))-INDEX('Rates 2y'!$I$2:$I$14,MATCH("USD",'Rates 2y'!$A$2:$A$14,0)))*2) -> 20.069236 | J12: ='FX year-end'!J12*EXP((INDEX('Rates 2y'!$J$2:$J$14,MATCH($A12,'Rates 2y'!$A$2:$A$14,0))-INDEX('Rates 2y'!$J$2:$J$14,MATCH("USD",'Rates 2y'!$A$2:$A$14,0)))*2) -> 17.795169 | K12: ='FX year-end'!K12*EXP((INDEX('Rates 2y'!$K$2:$K$14,MATCH($A12,'Rates 2y'!$A$2:$A$14,0))-INDEX('Rates 2y'!$K$2:$K$14,MATCH("USD",'Rates 2y'!$A$2:$A$14,0)))*2) -> 17.51377
A13: SEK | B13: ='FX year-end'!B13*EXP((INDEX('Rates 2y'!$B$2:$B$14,MATCH($A13,'Rates 2y'!$A$2:$A$14,0))-INDEX('Rates 2y'!$B$2:$B$14,MATCH("USD",'Rates 2y'!$A$2:$A$14,0)))*2) -> 7.8451404 | C13: ='FX year-end'!C13*EXP((INDEX('Rates 2y'!$C$2:$C$14,MATCH($A13,'Rates 2y'!$A$2:$A$14,0))-INDEX('Rates 2y'!$C$2:$C$14,MATCH("USD",'Rates 2y'!$A$2:$A$14,0)))*2) -> 8.4588313 | D13: ='FX year-end'!D13*EXP((INDEX('Rates 2y'!$D$2:$D$14,MATCH($A13,'Rates 2y'!$A$2:$A$14,0))-INDEX('Rates 2y'!$D$2:$D$14,MATCH("USD",'Rates 2y'!$A$2:$A$14,0)))*2) -> 8.9998436 | E13: ='FX year-end'!E13*EXP((INDEX('Rates 2y'!$E$2:$E$14,MATCH($A13,'Rates 2y'!$A$2:$A$14,0))-INDEX('Rates 2y'!$E$2:$E$14,MATCH("USD",'Rates 2y'!$A$2:$A$14,0)))*2) -> 8.1186485 | F13: ='FX year-end'!F13*EXP((INDEX('Rates 2y'!$F$2:$F$14,MATCH($A13,'Rates 2y'!$A$2:$A$14,0))-INDEX('Rates 2y'!$F$2:$F$14,MATCH("USD",'Rates 2y'!$A$2:$A$14,0)))*2) -> 8.969341 | G13: ='FX year-end'!G13*EXP((INDEX('Rates 2y'!$G$2:$G$14,MATCH($A13,'Rates 2y'!$A$2:$A$14,0))-INDEX('Rates 2y'!$G$2:$G$14,MATCH("USD",'Rates 2y'!$A$2:$A$14,0)))*2) -> 10.096739 | H13: ='FX year-end'!H13*EXP((INDEX('Rates 2y'!$H$2:$H$14,MATCH($A13,'Rates 2y'!$A$2:$A$14,0))-INDEX('Rates 2y'!$H$2:$H$14,MATCH("USD",'Rates 2y'!$A$2:$A$14,0)))*2) -> 9.7054725 | I13: ='FX year-end'!I13*EXP((INDEX('Rates 2y'!$I$2:$I$14,MATCH($A13,'Rates 2y'!$A$2:$A$14,0))-INDEX('Rates 2y'!$I$2:$I$14,MATCH("USD",'Rates 2y'!$A$2:$A$14,0)))*2) -> 10.540862 | J13: ='FX year-end'!J13*EXP((INDEX('Rates 2y'!$J$2:$J$14,MATCH($A13,'Rates 2y'!$A$2:$A$14,0))-INDEX('Rates 2y'!$J$2:$J$14,MATCH("USD",'Rates 2y'!$A$2:$A$14,0)))*2) -> 8.908729 | K13: ='FX year-end'!K13*EXP((INDEX('Rates 2y'!$K$2:$K$14,MATCH($A13,'Rates 2y'!$A$2:$A$14,0))-INDEX('Rates 2y'!$K$2:$K$14,MATCH("USD",'Rates 2y'!$A$2:$A$14,0)))*2) -> 9.6226683
A14: EUR | B14: ='FX year-end'!B14*EXP((INDEX('Rates 2y'!$B$2:$B$14,MATCH($A14,'Rates 2y'!$A$2:$A$14,0))-INDEX('Rates 2y'!$B$2:$B$14,MATCH("USD",'Rates 2y'!$A$2:$A$14,0)))*2) -> 0.79671885 | C14: ='FX year-end'!C14*EXP((INDEX('Rates 2y'!$C$2:$C$14,MATCH($A14,'Rates 2y'!$A$2:$A$14,0))-INDEX('Rates 2y'!$C$2:$C$14,MATCH("USD",'Rates 2y'!$A$2:$A$14,0)))*2) -> 0.82174416 | D14: ='FX year-end'!D14*EXP((INDEX('Rates 2y'!$D$2:$D$14,MATCH($A14,'Rates 2y'!$A$2:$A$14,0))-INDEX('Rates 2y'!$D$2:$D$14,MATCH("USD",'Rates 2y'!$A$2:$A$14,0)))*2) -> 0.85458968 | E14: ='FX year-end'!E14*EXP((INDEX('Rates 2y'!$E$2:$E$14,MATCH($A14,'Rates 2y'!$A$2:$A$14,0))-INDEX('Rates 2y'!$E$2:$E$14,MATCH("USD",'Rates 2y'!$A$2:$A$14,0)))*2) -> 0.79963035 | F14: ='FX year-end'!F14*EXP((INDEX('Rates 2y'!$F$2:$F$14,MATCH($A14,'Rates 2y'!$A$2:$A$14,0))-INDEX('Rates 2y'!$F$2:$F$14,MATCH("USD",'Rates 2y'!$A$2:$A$14,0)))*2) -> 0.85982184 | G14: ='FX year-end'!G14*EXP((INDEX('Rates 2y'!$G$2:$G$14,MATCH($A14,'Rates 2y'!$A$2:$A$14,0))-INDEX('Rates 2y'!$G$2:$G$14,MATCH("USD",'Rates 2y'!$A$2:$A$14,0)))*2) -> 0.90702614 | H14: ='FX year-end'!H14*EXP((INDEX('Rates 2y'!$H$2:$H$14,MATCH($A14,'Rates 2y'!$A$2:$A$14,0))-INDEX('Rates 2y'!$H$2:$H$14,MATCH("USD",'Rates 2y'!$A$2:$A$14,0)))*2) -> 0.87067175 | I14: ='FX year-end'!I14*EXP((INDEX('Rates 2y'!$I$2:$I$14,MATCH($A14,'Rates 2y'!$A$2:$A$14,0))-INDEX('Rates 2y'!$I$2:$I$14,MATCH("USD",'Rates 2y'!$A$2:$A$14,0)))*2) -> 0.92070823 | J14: ='FX year-end'!J14*EXP((INDEX('Rates 2y'!$J$2:$J$14,MATCH($A14,'Rates 2y'!$A$2:$A$14,0))-INDEX('Rates 2y'!$J$2:$J$14,MATCH("USD",'Rates 2y'!$A$2:$A$14,0)))*2) -> 0.82808649 | K14: ='FX year-end'!K14*EXP((INDEX('Rates 2y'!$K$2:$K$14,MATCH($A14,'Rates 2y'!$A$2:$A$14,0))-INDEX('Rates 2y'!$K$2:$K$14,MATCH("USD",'Rates 2y'!$A$2:$A$14,0)))*2) -> 0.85468222
A16: Covered-interest-parity forward: spot x exp((r_ccy - r_usd) x 2). Column '2017->2019' = rate agreed at end-2017 for delivery at end-2019.

Sheet Detail
A1: ticker | B1: company | C1: currency | D1: year | E1: last_trading_day | F1: open | G1: high | H1: low | I1: close | J1: average_close | K1: dividends_in_year | L1: dividend_yield | M1: rate_2y | N1: forward_2y_price | O1: forward_for_year | P1: actual_close_in_forward_year | Q1: forward_error
A2: PICK | B2: iShares MSCI Global Metals & Mining Producers ETF | C2: USD | D2: 2017 | E2: 43098 | F2: 26.18 | G2: 35 | H2: 25.02 | I2: 34.63 | J2: 29.5293 | K2: 0.835 | L2: 0.0241 | M2: 0.0189 | N2: 34.2709 | O2: 2019 | P2: 29.73 | Q2: -0.1325
A3: PICK | B3: iShares MSCI Global Metals & Mining Producers ETF | C3: USD | D3: 2018 | E3: 43465 | F3: 35.2 | G3: 37.91 | H3: 26 | I3: 26.98 | J3: 32.7918 | K3: 1.286 | L3: 0.0477 | M3: 0.0249 | N3: 25.7791 | O3: 2020 | P3: 36.85 | Q3: 0.4294
A4: PICK | B4: iShares MSCI Global Metals & Mining Producers ETF | C4: USD | D4: 2019 | E4: 43830 | F4: 26.35 | G4: 32.97 | H4: 24.51 | I4: 29.73 | J4: 28.846 | K4: 1.638 | L4: 0.0551 | M4: 0.0158 | N4: 27.4829 | O4: 2021 | P4: 42.62 | Q4: 0.5508
A5: PICK | B5: iShares MSCI Global Metals & Mining Producers ETF | C5: USD | D5: 2020 | E5: 44196 | F5: 30.13 | G5: 37.28 | H5: 16.01 | I5: 36.85 | J5: 26.504 | K5: 0.836 | L5: 0.0227 | M5: 0.0013 | N5: 35.307 | O5: 2022 | P5: 41 | Q5: 0.1612
A6: PICK | B6: iShares MSCI Global Metals & Mining Producers ETF | C6: USD | D6: 2021 | E6: 44561 | F6: 38.04 | G6: 52.39 | H6: 36.36 | I6: 42.62 | J6: 43.5231 | K6: 2.51 | L6: 0.0589 | M6: 0.0073 | N6: 38.4415 | O6: 2023 | P6: 43.07 | Q6: 0.1204
A7: PICK | B7: iShares MSCI Global Metals & Mining Producers ETF | C7: USD | D7: 2022 | E7: 44925 | F7: 42.56 | G7: 53 | H7: 31.86 | I7: 41 | J7: 41.4933 | K7: 2.843 | L7: 0.0693 | M7: 0.0443 | N7: 38.9972 | O7: 2024 | P7: 34.99 | Q7: -0.1028
A8: PICK | B8: iShares MSCI Global Metals & Mining Producers ETF | C8: USD | D8: 2023 | E8: 45289 | F8: 41.39 | G8: 47.7 | H8: 36.21 | I8: 43.07 | J8: 41.2161 | K8: 1.806 | L8: 0.0419 | M8: 0.0425 | N8: 43.119 | O8: 2025 | P8: 51.34 | Q8: 0.1907
A9: PICK | B9: iShares MSCI Global Metals & Mining Producers ETF | C9: USD | D9: 2024 | E9: 45657 | F9: 42.86 | G9: 46.4 | H9: 34.78 | I9: 34.99 | J9: 40.5666 | K9: 1.139 | L9: 0.0326 | M9: 0.0424 | N9: 35.686 | O9: 2026 | P9: 61.14 | Q9: 0.7133
A10: PICK | B10: iShares MSCI Global Metals & Mining Producers ETF | C10: USD | D10: 2025 | E10: 46022 | F10: 35.14 | G10: 52.42 | H10: 29.96 | I10: 51.34 | J10: 40.1501 | K10: 1.476 | L10: 0.0287 | M10: 0.0348 | N10: 51.965 | O10: 2027
A11: PICK | B11: iShares MSCI Global Metals & Mining Producers ETF | C11: USD | D11: 2026 | E11: 46290 | F11: 52.25 | G11: 69.02 | H11: 51.48 | I11: 61.14 | J11: 60.7002 | K11: 0.542 | L11: 0.0089 | M11: 0.0348 | N11: 64.395 | O11: 2028

Sheet Analyst targets (now)
A1: ticker | B1: company | C1: currency | D1: current | E1: mean | F1: median | G1: low | H1: high
A2: PICK | B2: iShares MSCI Global Metals & Mining Producers ETF | C2: USD
A4: 12-month consensus price targets as of the data download date. Source: Yahoo Finance.

Sheet Verification
A1: Cross-check of year-end closes against sources independent of Yahoo Finance
A2: 10 comparisons across 1 tickers: match: 10
A3: Not independently checked (no second source reachable): none
A5: ticker | B5: year | C5: source | D5: source_date | E5: source_close | F5: our_close | G5: status
A6: PICK | B6: 2017 | C6: nasdaq | D6: 2017-12-29 | E6: 34.63 | F6: 34.63 | G6: match
A7: PICK | B7: 2018 | C7: nasdaq | D7: 2018-12-31 | E7: 26.98 | F7: 26.98 | G7: match
A8: PICK | B8: 2019 | C8: nasdaq | D8: 2019-12-31 | E8: 29.73 | F8: 29.73 | G8: match
A9: PICK | B9: 2020 | C9: nasdaq | D9: 2020-12-31 | E9: 36.85 | F9: 36.85 | G9: match
A10: PICK | B10: 2021 | C10: nasdaq | D10: 2021-12-31 | E10: 42.62 | F10: 42.62 | G10: match
A11: PICK | B11: 2022 | C11: nasdaq | D11: 2022-12-30 | E11: 41 | F11: 41 | G11: match
A12: PICK | B12: 2023 | C12: nasdaq | D12: 2023-12-29 | E12: 43.07 | F12: 43.07 | G12: match
A13: PICK | B13: 2024 | C13: nasdaq | D13: 2024-12-31 | E13: 34.99 | F13: 34.99 | G13: match
A14: PICK | B14: 2025 | C14: nasdaq | D14: 2025-12-31 | E14: 51.34 | F14: 51.34 | G14: match
A15: PICK | B15: 2026 | C15: nasdaq | D15: 2026-09-25 | E15: 61.14 | F15: 61.14 | G15: match
